Workbook

Sheet Setup
A1: Once MFL 2024 is live

Sheet TVC-10

Sheet Tracker
C1: Team | D1: The Wild Cards | E1: Hamsterdam | F1: Shankly's Ghost | G1: 2 Roops, 1 Silva | H1: Orcan Terror | I1: The Meaty Ogres | J1: Ted Lasso | K1: Peaky Fookin Blinders | L1: Springfield Isotopes | M1: Battlebots | N1: The Two Tones | O1: Norsemen
B2: =sum(D2:O2) -> 210 | C2: Current Tokens | D2: =sum(D3:D996) -> 11 | E2: =sum(E3:E996) -> 13 | F2: =sum(F3:F996) -> 3 | G2: =sum(G3:G996) -> 12 | H2: =sum(H3:H996) -> 18 | I2: =sum(I3:I996) -> 16 | J2: =sum(J3:J996) -> 3 | K2: =sum(K3:K996) -> 0 | ... O2: =sum(O3:O996) -> 15
A3: Start | B3: 46037 | C3: Start of Year | D3: 11 | E3: 13 | F3: 0 | G3: 9 | H3: 15 | I3: 13 | J3: 3 | K3: 0 | L3: 20 | M3: 84 | N3: 11 | O3: 15
A4: Jan-Mar | B4: 46023 | C4: Trades | D4: =IFERROR(__xludf.DUMMYFUNCTION("IFNA(filter(Trades!$J:$J,Trades!$B:$B=D$1,Trades!$A:$A>=$B4,Trades!$A:$A<=$B6),0)+IFNA(filter(Trades!$J:$J,Trades!$F:$F=D$1,Trades!$A:$A>=$B4,Trades!$A:$A<=$B6),0)"),0.0) -> 0 | E4: =IFERROR(__xludf.DUMMYFUNCTION("IFNA(filter(Trades!$J:$J,Trades!$B:$B=E$1,Trades!$A:$A>=$B4,Trades!$A:$A<=$B6),0)+IFNA(filter(Trades!$J:$J,Trades!$F:$F=E$1,Trades!$A:$A>=$B4,Trades!$A:$A<=$B6),0)"),0.0) -> 0 | F4: =IFERROR(__xludf.DUMMYFUNCTION("IFNA(filter(Trades!$J:$J,Trades!$B:$B=F$1,Trades!$A:$A>=$B4,Trades!$A:$A<=$B6),0)+IFNA(filter(Trades!$J:$J,Trades!$F:$F=F$1,Trades!$A:$A>=$B4,Trades!$A:$A<=$B6),0)"),0.0) -> 0 | G4: =IFERROR(__xludf.DUMMYFUNCTION("IFNA(filter(Trades!$J:$J,Trades!$B:$B=G$1,Trades!$A:$A>=$B4,Trades!$A:$A<=$B6),0)+IFNA(filter(Trades!$J:$J,Trades!$F:$F=G$1,Trades!$A:$A>=$B4,Trades!$A:$A<=$B6),0)"),0.0) -> 0 | H4: =IFERROR(__xludf.DUMMYFUNCTION("IFNA(filter(Trades!$J:$J,Trades!$B:$B=H$1,Trades!$A:$A>=$B4,Trades!$A:$A<=$B6),0)+IFNA(filter(Trades!$J:$J,Trades!$F:$F=H$1,Trades!$A:$A>=$B4,Trades!$A:$A<=$B6),0)"),0.0) -> 0 | I4: =IFERROR(__xludf.DUMMYFUNCTION("IFNA(filter(Trades!$J:$J,Trades!$B:$B=I$1,Trades!$A:$A>=$B4,Trades!$A:$A<=$B6),0)+IFNA(filter(Trades!$J:$J,Trades!$F:$F=I$1,Trades!$A:$A>=$B4,Trades!$A:$A<=$B6),0)"),0.0) -> 0 | J4: =IFERROR(__xludf.DUMMYFUNCTION("IFNA(filter(Trades!$J:$J,Trades!$B:$B=J$1,Trades!$A:$A>=$B4,Trades!$A:$A<=$B6),0)+IFNA(filter(Trades!$J:$J,Trades!$F:$F=J$1,Trades!$A:$A>=$B4,Trades!$A:$A<=$B6),0)"),0.0) -> 0 | K4: =IFERROR(__xludf.DUMMYFUNCTION("IFNA(filter(Trades!$J:$J,Trades!$B:$B=K$1,Trades!$A:$A>=$B4,Trades!$A:$A<=$B6),0)+IFNA(filter(Trades!$J:$J,Trades!$F:$F=K$1,Trades!$A:$A>=$B4,Trades!$A:$A<=$B6),0)"),0.0) -> 0 | L4: =IFERROR(__xludf.DUMMYFUNCTION("IFNA(filter(Trades!$J:$J,Trades!$B:$B=L$1,Trades!$A:$A>=$B4,Trades!$A:$A<=$B6),0)+IFNA(filter(Trades!$J:$J,Trades!$F:$F=L$1,Trades!$A:$A>=$B4,Trades!$A:$A<=$B6),0)"),0.0) -> 0 | M4: =IFERROR(__xludf.DUMMYFUNCTION("IFNA(filter(Trades!$J:$J,Trades!$B:$B=M$1,Trades!$A:$A>=$B4,Trades!$A:$A<=$B6),0)+IFNA(filter(Trades!$J:$J,Trades!$F:$F=M$1,Trades!$A:$A>=$B4,Trades!$A:$A<=$B6),0)"),0.0) -> 0 | N4: =IFERROR(__xludf.DUMMYFUNCTION("IFNA(filter(Trades!$J:$J,Trades!$B:$B=N$1,Trades!$A:$A>=$B4,Trades!$A:$A<=$B6),0)+IFNA(filter(Trades!$J:$J,Trades!$F:$F=N$1,Trades!$A:$A>=$B4,Trades!$A:$A<=$B6),0)"),0.0) -> 0 | O4: =IFERROR(__xludf.DUMMYFUNCTION("IFNA(filter(Trades!$J:$J,Trades!$B:$B=O$1,Trades!$A:$A>=$B4,Trades!$A:$A<=$B6),0)+IFNA(filter(Trades!$J:$J,Trades!$F:$F=O$1,Trades!$A:$A>=$B4,Trades!$A:$A<=$B6),0)"),0.0) -> 0
C5: Tokens Traded/Voided
B6: 46112
A7: Apr-Jun | B7: 46113 | C7: Trades | D7: =IFERROR(__xludf.DUMMYFUNCTION("IFNA(filter(Trades!$J:$J,Trades!$B:$B=D$1,Trades!$A:$A>=$B7,Trades!$A:$A<=$B9),0)+IFNA(filter(Trades!$J:$J,Trades!$F:$F=D$1,Trades!$A:$A>=$B7,Trades!$A:$A<=$B9),0)"),0.0) -> 0 | E7: =IFERROR(__xludf.DUMMYFUNCTION("IFNA(filter(Trades!$J:$J,Trades!$B:$B=E$1,Trades!$A:$A>=$B7,Trades!$A:$A<=$B9),0)+IFNA(filter(Trades!$J:$J,Trades!$F:$F=E$1,Trades!$A:$A>=$B7,Trades!$A:$A<=$B9),0)"),0.0) -> 0 | F7: =IFERROR(__xludf.DUMMYFUNCTION("IFNA(filter(Trades!$J:$J,Trades!$B:$B=F$1,Trades!$A:$A>=$B7,Trades!$A:$A<=$B9),0)+IFNA(filter(Trades!$J:$J,Trades!$F:$F=F$1,Trades!$A:$A>=$B7,Trades!$A:$A<=$B9),0)"),0.0) -> 0 | G7: =IFERROR(__xludf.DUMMYFUNCTION("IFNA(filter(Trades!$J:$J,Trades!$B:$B=G$1,Trades!$A:$A>=$B7,Trades!$A:$A<=$B9),0)+IFNA(filter(Trades!$J:$J,Trades!$F:$F=G$1,Trades!$A:$A>=$B7,Trades!$A:$A<=$B9),0)"),0.0) -> 0 | H7: =IFERROR(__xludf.DUMMYFUNCTION("IFNA(filter(Trades!$J:$J,Trades!$B:$B=H$1,Trades!$A:$A>=$B7,Trades!$A:$A<=$B9),0)+IFNA(filter(Trades!$J:$J,Trades!$F:$F=H$1,Trades!$A:$A>=$B7,Trades!$A:$A<=$B9),0)"),0.0) -> 0 | I7: =IFERROR(__xludf.DUMMYFUNCTION("IFNA(filter(Trades!$J:$J,Trades!$B:$B=I$1,Trades!$A:$A>=$B7,Trades!$A:$A<=$B9),0)+IFNA(filter(Trades!$J:$J,Trades!$F:$F=I$1,Trades!$A:$A>=$B7,Trades!$A:$A<=$B9),0)"),0.0) -> 0 | J7: =IFERROR(__xludf.DUMMYFUNCTION("IFNA(filter(Trades!$J:$J,Trades!$B:$B=J$1,Trades!$A:$A>=$B7,Trades!$A:$A<=$B9),0)+IFNA(filter(Trades!$J:$J,Trades!$F:$F=J$1,Trades!$A:$A>=$B7,Trades!$A:$A<=$B9),0)"),0.0) -> 0 | K7: =IFERROR(__xludf.DUMMYFUNCTION("IFNA(filter(Trades!$J:$J,Trades!$B:$B=K$1,Trades!$A:$A>=$B7,Trades!$A:$A<=$B9),0)+IFNA(filter(Trades!$J:$J,Trades!$F:$F=K$1,Trades!$A:$A>=$B7,Trades!$A:$A<=$B9),0)"),0.0) -> 0 | L7: =IFERROR(__xludf.DUMMYFUNCTION("IFNA(filter(Trades!$J:$J,Trades!$B:$B=L$1,Trades!$A:$A>=$B7,Trades!$A:$A<=$B9),0)+IFNA(filter(Trades!$J:$J,Trades!$F:$F=L$1,Trades!$A:$A>=$B7,Trades!$A:$A<=$B9),0)"),0.0) -> 0 | M7: =IFERROR(__xludf.DUMMYFUNCTION("IFNA(filter(Trades!$J:$J,Trades!$B:$B=M$1,Trades!$A:$A>=$B7,Trades!$A:$A<=$B9),0)+IFNA(filter(Trades!$J:$J,Trades!$F:$F=M$1,Trades!$A:$A>=$B7,Trades!$A:$A<=$B9),0)"),0.0) -> 0 | N7: =IFERROR(__xludf.DUMMYFUNCTION("IFNA(filter(Trades!$J:$J,Trades!$B:$B=N$1,Trades!$A:$A>=$B7,Trades!$A:$A<=$B9),0)+IFNA(filter(Trades!$J:$J,Trades!$F:$F=N$1,Trades!$A:$A>=$B7,Trades!$A:$A<=$B9),0)"),0.0) -> 0 | O7: =IFERROR(__xludf.DUMMYFUNCTION("IFNA(filter(Trades!$J:$J,Trades!$B:$B=O$1,Trades!$A:$A>=$B7,Trades!$A:$A<=$B9),0)+IFNA(filter(Trades!$J:$J,Trades!$F:$F=O$1,Trades!$A:$A>=$B7,Trades!$A:$A<=$B9),0)"),0.0) -> 0
C8: Tokens Traded
B9: 46203
A10: Jul-Wk1 | B10: 46204 | C10: Trades | D10: =IFERROR(__xludf.DUMMYFUNCTION("IFNA(filter(Trades!$J:$J,Trades!$B:$B=D$1,Trades!$A:$A>=$B10,Trades!$A:$A<=$B12),0)+IFNA(filter(Trades!$J:$J,Trades!$F:$F=D$1,Trades!$A:$A>=$B10,Trades!$A:$A<=$B12),0)"),0.0) -> 0 | E10: =IFERROR(__xludf.DUMMYFUNCTION("IFNA(filter(Trades!$J:$J,Trades!$B:$B=E$1,Trades!$A:$A>=$B10,Trades!$A:$A<=$B12),0)+IFNA(filter(Trades!$J:$J,Trades!$F:$F=E$1,Trades!$A:$A>=$B10,Trades!$A:$A<=$B12),0)"),0.0) -> 0 | F10: =IFERROR(__xludf.DUMMYFUNCTION("IFNA(filter(Trades!$J:$J,Trades!$B:$B=F$1,Trades!$A:$A>=$B10,Trades!$A:$A<=$B12),0)+IFNA(filter(Trades!$J:$J,Trades!$F:$F=F$1,Trades!$A:$A>=$B10,Trades!$A:$A<=$B12),0)"),0.0) -> 0 | G10: =IFERROR(__xludf.DUMMYFUNCTION("IFNA(filter(Trades!$J:$J,Trades!$B:$B=G$1,Trades!$A:$A>=$B10,Trades!$A:$A<=$B12),0)+IFNA(filter(Trades!$J:$J,Trades!$F:$F=G$1,Trades!$A:$A>=$B10,Trades!$A:$A<=$B12),0)"),0.0) -> 0 | H10: =IFERROR(__xludf.DUMMYFUNCTION("IFNA(filter(Trades!$J:$J,Trades!$B:$B=H$1,Trades!$A:$A>=$B10,Trades!$A:$A<=$B12),0)+IFNA(filter(Trades!$J:$J,Trades!$F:$F=H$1,Trades!$A:$A>=$B10,Trades!$A:$A<=$B12),0)"),0.0) -> 0 | I10: =IFERROR(__xludf.DUMMYFUNCTION("IFNA(filter(Trades!$J:$J,Trades!$B:$B=I$1,Trades!$A:$A>=$B10,Trades!$A:$A<=$B12),0)+IFNA(filter(Trades!$J:$J,Trades!$F:$F=I$1,Trades!$A:$A>=$B10,Trades!$A:$A<=$B12),0)"),0.0) -> 0 | J10: =IFERROR(__xludf.DUMMYFUNCTION("IFNA(filter(Trades!$J:$J,Trades!$B:$B=J$1,Trades!$A:$A>=$B10,Trades!$A:$A<=$B12),0)+IFNA(filter(Trades!$J:$J,Trades!$F:$F=J$1,Trades!$A:$A>=$B10,Trades!$A:$A<=$B12),0)"),0.0) -> 0 | K10: =IFERROR(__xludf.DUMMYFUNCTION("IFNA(filter(Trades!$J:$J,Trades!$B:$B=K$1,Trades!$A:$A>=$B10,Trades!$A:$A<=$B12),0)+IFNA(filter(Trades!$J:$J,Trades!$F:$F=K$1,Trades!$A:$A>=$B10,Trades!$A:$A<=$B12),0)"),0.0) -> 0 | L10: =IFERROR(__xludf.DUMMYFUNCTION("IFNA(filter(Trades!$J:$J,Trades!$B:$B=L$1,Trades!$A:$A>=$B10,Trades!$A:$A<=$B12),0)+IFNA(filter(Trades!$J:$J,Trades!$F:$F=L$1,Trades!$A:$A>=$B10,Trades!$A:$A<=$B12),0)"),0.0) -> 0 | M10: =IFERROR(__xludf.DUMMYFUNCTION("IFNA(filter(Trades!$J:$J,Trades!$B:$B=M$1,Trades!$A:$A>=$B10,Trades!$A:$A<=$B12),0)+IFNA(filter(Trades!$J:$J,Trades!$F:$F=M$1,Trades!$A:$A>=$B10,Trades!$A:$A<=$B12),0)"),0.0) -> 0 | N10: =IFERROR(__xludf.DUMMYFUNCTION("IFNA(filter(Trades!$J:$J,Trades!$B:$B=N$1,Trades!$A:$A>=$B10,Trades!$A:$A<=$B12),0)+IFNA(filter(Trades!$J:$J,Trades!$F:$F=N$1,Trades!$A:$A>=$B10,Trades!$A:$A<=$B12),0)"),0.0) -> 0 | O10: =IFERROR(__xludf.DUMMYFUNCTION("IFNA(filter(Trades!$J:$J,Trades!$B:$B=O$1,Trades!$A:$A>=$B10,Trades!$A:$A<=$B12),0)+IFNA(filter(Trades!$J:$J,Trades!$F:$F=O$1,Trades!$A:$A>=$B10,Trades!$A:$A<=$B12),0)"),0.0) -> 0
C11: Tokens Traded | K11: -2 | M11: -2
B12: 46266
A13: Q1 Reg | B13: 46267 | C13: Trades | D13: =IFERROR(__xludf.DUMMYFUNCTION("IFNA(filter(Trades!$J:$J,Trades!$B:$B=D$1,Trades!$A:$A>=$B13,Trades!$A:$A<=$B16),0)+IFNA(filter(Trades!$J:$J,Trades!$F:$F=D$1,Trades!$A:$A>=$B13,Trades!$A:$A<=$B16),0)"),0.0) -> 0 | E13: =IFERROR(__xludf.DUMMYFUNCTION("IFNA(filter(Trades!$J:$J,Trades!$B:$B=E$1,Trades!$A:$A>=$B13,Trades!$A:$A<=$B15),0)+IFNA(filter(Trades!$J:$J,Trades!$F:$F=E$1,Trades!$A:$A>=$B13,Trades!$A:$A<=$B15),0)"),0.0) -> 0 | F13: =IFERROR(__xludf.DUMMYFUNCTION("IFNA(filter(Trades!$J:$J,Trades!$B:$B=F$1,Trades!$A:$A>=$B13,Trades!$A:$A<=$B15),0)+IFNA(filter(Trades!$J:$J,Trades!$F:$F=F$1,Trades!$A:$A>=$B13,Trades!$A:$A<=$B15),0)"),0.0) -> 0 | G13: =IFERROR(__xludf.DUMMYFUNCTION("IFNA(filter(Trades!$J:$J,Trades!$B:$B=G$1,Trades!$A:$A>=$B13,Trades!$A:$A<=$B15),0)+IFNA(filter(Trades!$J:$J,Trades!$F:$F=G$1,Trades!$A:$A>=$B13,Trades!$A:$A<=$B15),0)"),0.0) -> 0 | H13: =IFERROR(__xludf.DUMMYFUNCTION("IFNA(filter(Trades!$J:$J,Trades!$B:$B=H$1,Trades!$A:$A>=$B13,Trades!$A:$A<=$B15),0)+IFNA(filter(Trades!$J:$J,Trades!$F:$F=H$1,Trades!$A:$A>=$B13,Trades!$A:$A<=$B15),0)"),0.0) -> 0 | I13: =IFERROR(__xludf.DUMMYFUNCTION("IFNA(filter(Trades!$J:$J,Trades!$B:$B=I$1,Trades!$A:$A>=$B13,Trades!$A:$A<=$B15),0)+IFNA(filter(Trades!$J:$J,Trades!$F:$F=I$1,Trades!$A:$A>=$B13,Trades!$A:$A<=$B15),0)"),0.0) -> 0 | J13: =IFERROR(__xludf.DUMMYFUNCTION("IFNA(filter(Trades!$J:$J,Trades!$B:$B=J$1,Trades!$A:$A>=$B13,Trades!$A:$A<=$B15),0)+IFNA(filter(Trades!$J:$J,Trades!$F:$F=J$1,Trades!$A:$A>=$B13,Trades!$A:$A<=$B15),0)"),0.0) -> 0 | K13: =IFERROR(__xludf.DUMMYFUNCTION("IFNA(filter(Trades!$J:$J,Trades!$B:$B=K$1,Trades!$A:$A>=$B13,Trades!$A:$A<=$B15),0)+IFNA(filter(Trades!$J:$J,Trades!$F:$F=K$1,Trades!$A:$A>=$B13,Trades!$A:$A<=$B15),0)"),0.0) -> 0 | L13: =IFERROR(__xludf.DUMMYFUNCTION("IFNA(filter(Trades!$J:$J,Trades!$B:$B=L$1,Trades!$A:$A>=$B13,Trades!$A:$A<=$B15),0)+IFNA(filter(Trades!$J:$J,Trades!$F:$F=L$1,Trades!$A:$A>=$B13,Trades!$A:$A<=$B15),0)"),0.0) -> 0 | M13: =IFERROR(__xludf.DUMMYFUNCTION("IFNA(filter(Trades!$J:$J,Trades!$B:$B=M$1,Trades!$A:$A>=$B13,Trades!$A:$A<=$B15),0)+IFNA(filter(Trades!$J:$J,Trades!$F:$F=M$1,Trades!$A:$A>=$B13,Trades!$A:$A<=$B15),0)"),0.0) -> 0 | N13: =IFERROR(__xludf.DUMMYFUNCTION("IFNA(filter(Trades!$J:$J,Trades!$B:$B=N$1,Trades!$A:$A>=$B13,Trades!$A:$A<=$B15),0)+IFNA(filter(Trades!$J:$J,Trades!$F:$F=N$1,Trades!$A:$A>=$B13,Trades!$A:$A<=$B15),0)"),0.0) -> 0 | O13: =IFERROR(__xludf.DUMMYFUNCTION("IFNA(filter(Trades!$J:$J,Trades!$B:$B=O$1,Trades!$A:$A>=$B13,Trades!$A:$A<=$B15),0)+IFNA(filter(Trades!$J:$J,Trades!$F:$F=O$1,Trades!$A:$A>=$B13,Trades!$A:$A<=$B15),0)"),0.0) -> 0
C14: Tokens Traded
C15: Adds >= $25 | D15: =IF(countifs(Waivers!$B:$B,"="&D$1,Waivers!$F:$F,">"&datevalue($B12-1),Waivers!$F:$F,"<"&datevalue($B16+1),Waivers!$G:$G,">9")>4,5,countifs(Waivers!$B:$B,"="&D$1,Waivers!$F:$F,">"&datevalue($B12-1),Waivers!$F:$F,"<"&datevalue($B16+1),Waivers!$G:$G,">9")) -> 0 | E15: =IF(countifs(Waivers!$B:$B,"="&E$1,Waivers!$F:$F,">"&datevalue($B12-1),Waivers!$F:$F,"<"&datevalue($B16+1),Waivers!$G:$G,">9")>4,5,countifs(Waivers!$B:$B,"="&E$1,Waivers!$F:$F,">"&datevalue($B12-1),Waivers!$F:$F,"<"&datevalue($B16+1),Waivers!$G:$G,">9")) -> 0 | F15: =IF(countifs(Waivers!$B:$B,"="&F$1,Waivers!$F:$F,">"&datevalue($B12-1),Waivers!$F:$F,"<"&datevalue($B16+1),Waivers!$G:$G,">9")>4,5,countifs(Waivers!$B:$B,"="&F$1,Waivers!$F:$F,">"&datevalue($B12-1),Waivers!$F:$F,"<"&datevalue($B16+1),Waivers!$G:$G,">9")) -> 3 | G15: =IF(countifs(Waivers!$B:$B,"="&G$1,Waivers!$F:$F,">"&datevalue($B12-1),Waivers!$F:$F,"<"&datevalue($B16+1),Waivers!$G:$G,">9")>4,5,countifs(Waivers!$B:$B,"="&G$1,Waivers!$F:$F,">"&datevalue($B12-1),Waivers!$F:$F,"<"&datevalue($B16+1),Waivers!$G:$G,">9")) -> 3 | H15: =IF(countifs(Waivers!$B:$B,"="&H$1,Waivers!$F:$F,">"&datevalue($B12-1),Waivers!$F:$F,"<"&datevalue($B16+1),Waivers!$G:$G,">9")>4,5,countifs(Waivers!$B:$B,"="&H$1,Waivers!$F:$F,">"&datevalue($B12-1),Waivers!$F:$F,"<"&datevalue($B16+1),Waivers!$G:$G,">9")) -> 1 | I15: =IF(countifs(Waivers!$B:$B,"="&I$1,Waivers!$F:$F,">"&datevalue($B12-1),Waivers!$F:$F,"<"&datevalue($B16+1),Waivers!$G:$G,">9")>4,5,countifs(Waivers!$B:$B,"="&I$1,Waivers!$F:$F,">"&datevalue($B12-1),Waivers!$F:$F,"<"&datevalue($B16+1),Waivers!$G:$G,">9")) -> 3 | J15: =IF(countifs(Waivers!$B:$B,"="&J$1,Waivers!$F:$F,">"&datevalue($B12-1),Waivers!$F:$F,"<"&datevalue($B16+1),Waivers!$G:$G,">9")>4,5,countifs(Waivers!$B:$B,"="&J$1,Waivers!$F:$F,">"&datevalue($B12-1),Waivers!$F:$F,"<"&datevalue($B16+1),Waivers!$G:$G,">9")) -> 0 | K15: =IF(countifs(Waivers!$B:$B,"="&K$1,Waivers!$F:$F,">"&datevalue($B12-1),Waivers!$F:$F,"<"&datevalue($B16+1),Waivers!$G:$G,">9")>4,5,countifs(Waivers!$B:$B,"="&K$1,Waivers!$F:$F,">"&datevalue($B12-1),Waivers!$F:$F,"<"&datevalue($B16+1),Waivers!$G:$G,">9")) -> 1 | ... O15: =IF(countifs(Waivers!$B:$B,"="&O$1,Waivers!$F:$F,">"&datevalue($B12-1),Waivers!$F:$F,"<"&datevalue($B16+1),Waivers!$G:$G,">9")>4,5,countifs(Waivers!$B:$B,"="&O$1,Waivers!$F:$F,">"&datevalue($B12-1),Waivers!$F:$F,"<"&datevalue($B16+1),Waivers!$G:$G,">9")) -> 0
B16: 46293 | C16: Promotion Award
A17: Q2 Reg | B17: 46294 | C17: Trades | D17: =IFERROR(__xludf.DUMMYFUNCTION("IFNA(filter(Trades!$J:$J,Trades!$B:$B=D$1,Trades!$A:$A>=$B17,Trades!$A:$A<=$B20),0)+IFNA(filter(Trades!$J:$J,Trades!$F:$F=D$1,Trades!$A:$A>=$B17,Trades!$A:$A<=$B20),0)"),0.0) -> 0 | E17: =IFERROR(__xludf.DUMMYFUNCTION("IFNA(filter(Trades!$J:$J,Trades!$B:$B=E$1,Trades!$A:$A>=$B17,Trades!$A:$A<=$B19),0)+IFNA(filter(Trades!$J:$J,Trades!$F:$F=E$1,Trades!$A:$A>=$B17,Trades!$A:$A<=$B19),0)"),0.0) -> 0 | F17: =IFERROR(__xludf.DUMMYFUNCTION("IFNA(filter(Trades!$J:$J,Trades!$B:$B=F$1,Trades!$A:$A>=$B17,Trades!$A:$A<=$B19),0)+IFNA(filter(Trades!$J:$J,Trades!$F:$F=F$1,Trades!$A:$A>=$B17,Trades!$A:$A<=$B19),0)"),0.0) -> 0 | G17: =IFERROR(__xludf.DUMMYFUNCTION("IFNA(filter(Trades!$J:$J,Trades!$B:$B=G$1,Trades!$A:$A>=$B17,Trades!$A:$A<=$B19),0)+IFNA(filter(Trades!$J:$J,Trades!$F:$F=G$1,Trades!$A:$A>=$B17,Trades!$A:$A<=$B19),0)"),0.0) -> 0 | H17: =IFERROR(__xludf.DUMMYFUNCTION("IFNA(filter(Trades!$J:$J,Trades!$B:$B=H$1,Trades!$A:$A>=$B17,Trades!$A:$A<=$B19),0)+IFNA(filter(Trades!$J:$J,Trades!$F:$F=H$1,Trades!$A:$A>=$B17,Trades!$A:$A<=$B19),0)"),0.0) -> 0 | I17: =IFERROR(__xludf.DUMMYFUNCTION("IFNA(filter(Trades!$J:$J,Trades!$B:$B=I$1,Trades!$A:$A>=$B17,Trades!$A:$A<=$B19),0)+IFNA(filter(Trades!$J:$J,Trades!$F:$F=I$1,Trades!$A:$A>=$B17,Trades!$A:$A<=$B19),0)"),0.0) -> 0 | J17: =IFERROR(__xludf.DUMMYFUNCTION("IFNA(filter(Trades!$J:$J,Trades!$B:$B=J$1,Trades!$A:$A>=$B17,Trades!$A:$A<=$B19),0)+IFNA(filter(Trades!$J:$J,Trades!$F:$F=J$1,Trades!$A:$A>=$B17,Trades!$A:$A<=$B19),0)"),0.0) -> 0 | K17: =IFERROR(__xludf.DUMMYFUNCTION("IFNA(filter(Trades!$J:$J,Trades!$B:$B=K$1,Trades!$A:$A>=$B17,Trades!$A:$A<=$B19),0)+IFNA(filter(Trades!$J:$J,Trades!$F:$F=K$1,Trades!$A:$A>=$B17,Trades!$A:$A<=$B19),0)"),0.0) -> 0 | L17: =IFERROR(__xludf.DUMMYFUNCTION("IFNA(filter(Trades!$J:$J,Trades!$B:$B=L$1,Trades!$A:$A>=$B17,Trades!$A:$A<=$B19),0)+IFNA(filter(Trades!$J:$J,Trades!$F:$F=L$1,Trades!$A:$A>=$B17,Trades!$A:$A<=$B19),0)"),0.0) -> 0 | M17: =IFERROR(__xludf.DUMMYFUNCTION("IFNA(filter(Trades!$J:$J,Trades!$B:$B=M$1,Trades!$A:$A>=$B17,Trades!$A:$A<=$B19),0)+IFNA(filter(Trades!$J:$J,Trades!$F:$F=M$1,Trades!$A:$A>=$B17,Trades!$A:$A<=$B19),0)"),0.0) -> 0 | N17: =IFERROR(__xludf.DUMMYFUNCTION("IFNA(filter(Trades!$J:$J,Trades!$B:$B=N$1,Trades!$A:$A>=$B17,Trades!$A:$A<=$B19),0)+IFNA(filter(Trades!$J:$J,Trades!$F:$F=N$1,Trades!$A:$A>=$B17,Trades!$A:$A<=$B19),0)"),0.0) -> 0 | O17: =IFERROR(__xludf.DUMMYFUNCTION("IFNA(filter(Trades!$J:$J,Trades!$B:$B=O$1,Trades!$A:$A>=$B17,Trades!$A:$A<=$B19),0)+IFNA(filter(Trades!$J:$J,Trades!$F:$F=O$1,Trades!$A:$A>=$B17,Trades!$A:$A<=$B19),0)"),0.0) -> 0
C18: Tokens Traded/Voided
C19: Adds >= $25 | D19: =IF(countifs(Waivers!$B:$B,"="&D$1,Waivers!$F:$F,">"&datevalue($B16-1),Waivers!$F:$F,"<"&datevalue($B20+1),Waivers!$G:$G,">9")>4,5,countifs(Waivers!$B:$B,"="&D$1,Waivers!$F:$F,">"&datevalue($B16-1),Waivers!$F:$F,"<"&datevalue($B20+1),Waivers!$G:$G,">9")) -> 0 | E19: =IF(countifs(Waivers!$B:$B,"="&E$1,Waivers!$F:$F,">"&datevalue($B16-1),Waivers!$F:$F,"<"&datevalue($B20+1),Waivers!$G:$G,">9")>4,5,countifs(Waivers!$B:$B,"="&E$1,Waivers!$F:$F,">"&datevalue($B16-1),Waivers!$F:$F,"<"&datevalue($B20+1),Waivers!$G:$G,">9")) -> 0 | F19: =IF(countifs(Waivers!$B:$B,"="&F$1,Waivers!$F:$F,">"&datevalue($B16-1),Waivers!$F:$F,"<"&datevalue($B20+1),Waivers!$G:$G,">9")>4,5,countifs(Waivers!$B:$B,"="&F$1,Waivers!$F:$F,">"&datevalue($B16-1),Waivers!$F:$F,"<"&datevalue($B20+1),Waivers!$G:$G,">9")) -> 0 | G19: =IF(countifs(Waivers!$B:$B,"="&G$1,Waivers!$F:$F,">"&datevalue($B16-1),Waivers!$F:$F,"<"&datevalue($B20+1),Waivers!$G:$G,">9")>4,5,countifs(Waivers!$B:$B,"="&G$1,Waivers!$F:$F,">"&datevalue($B16-1),Waivers!$F:$F,"<"&datevalue($B20+1),Waivers!$G:$G,">9")) -> 0 | H19: =IF(countifs(Waivers!$B:$B,"="&H$1,Waivers!$F:$F,">"&datevalue($B16-1),Waivers!$F:$F,"<"&datevalue($B20+1),Waivers!$G:$G,">9")>4,5,countifs(Waivers!$B:$B,"="&H$1,Waivers!$F:$F,">"&datevalue($B16-1),Waivers!$F:$F,"<"&datevalue($B20+1),Waivers!$G:$G,">9")) -> 2 | I19: =IF(countifs(Waivers!$B:$B,"="&I$1,Waivers!$F:$F,">"&datevalue($B16-1),Waivers!$F:$F,"<"&datevalue($B20+1),Waivers!$G:$G,">9")>4,5,countifs(Waivers!$B:$B,"="&I$1,Waivers!$F:$F,">"&datevalue($B16-1),Waivers!$F:$F,"<"&datevalue($B20+1),Waivers!$G:$G,">9")) -> 0 | J19: =IF(countifs(Waivers!$B:$B,"="&J$1,Waivers!$F:$F,">"&datevalue($B16-1),Waivers!$F:$F,"<"&datevalue($B20+1),Waivers!$G:$G,">9")>4,5,countifs(Waivers!$B:$B,"="&J$1,Waivers!$F:$F,">"&datevalue($B16-1),Waivers!$F:$F,"<"&datevalue($B20+1),Waivers!$G:$G,">9")) -> 0 | K19: =IF(countifs(Waivers!$B:$B,"="&K$1,Waivers!$F:$F,">"&datevalue($B16-1),Waivers!$F:$F,"<"&datevalue($B20+1),Waivers!$G:$G,">9")>4,5,countifs(Waivers!$B:$B,"="&K$1,Waivers!$F:$F,">"&datevalue($B16-1),Waivers!$F:$F,"<"&datevalue($B20+1),Waivers!$G:$G,">9")) -> 1 | ... O19: =IF(countifs(Waivers!$B:$B,"="&O$1,Waivers!$F:$F,">"&datevalue($B16-1),Waivers!$F:$F,"<"&datevalue($B20+1),Waivers!$G:$G,">9")>4,5,countifs(Waivers!$B:$B,"="&O$1,Waivers!$F:$F,">"&datevalue($B16-1),Waivers!$F:$F,"<"&datevalue($B20+1),Waivers!$G:$G,">9")) -> 0
B20: 46321 | C20: Promotion Award
A21: Q3 Reg | B21: 46322 | C21: Trades | D21: =IFERROR(__xludf.DUMMYFUNCTION("IFNA(filter(Trades!$J:$J,Trades!$B:$B=D$1,Trades!$A:$A>=$B21,Trades!$A:$A<=$B24),0)+IFNA(filter(Trades!$J:$J,Trades!$F:$F=D$1,Trades!$A:$A>=$B21,Trades!$A:$A<=$B24),0)"),0.0) -> 0 | E21: =IFERROR(__xludf.DUMMYFUNCTION("IFNA(filter(Trades!$J:$J,Trades!$B:$B=E$1,Trades!$A:$A>=$B21,Trades!$A:$A<=$B23),0)+IFNA(filter(Trades!$J:$J,Trades!$F:$F=E$1,Trades!$A:$A>=$B21,Trades!$A:$A<=$B23),0)"),0.0) -> 0 | F21: =IFERROR(__xludf.DUMMYFUNCTION("IFNA(filter(Trades!$J:$J,Trades!$B:$B=F$1,Trades!$A:$A>=$B21,Trades!$A:$A<=$B23),0)+IFNA(filter(Trades!$J:$J,Trades!$F:$F=F$1,Trades!$A:$A>=$B21,Trades!$A:$A<=$B23),0)"),0.0) -> 0 | G21: =IFERROR(__xludf.DUMMYFUNCTION("IFNA(filter(Trades!$J:$J,Trades!$B:$B=G$1,Trades!$A:$A>=$B21,Trades!$A:$A<=$B23),0)+IFNA(filter(Trades!$J:$J,Trades!$F:$F=G$1,Trades!$A:$A>=$B21,Trades!$A:$A<=$B23),0)"),0.0) -> 0 | H21: =IFERROR(__xludf.DUMMYFUNCTION("IFNA(filter(Trades!$J:$J,Trades!$B:$B=H$1,Trades!$A:$A>=$B21,Trades!$A:$A<=$B23),0)+IFNA(filter(Trades!$J:$J,Trades!$F:$F=H$1,Trades!$A:$A>=$B21,Trades!$A:$A<=$B23),0)"),0.0) -> 0 | I21: =IFERROR(__xludf.DUMMYFUNCTION("IFNA(filter(Trades!$J:$J,Trades!$B:$B=I$1,Trades!$A:$A>=$B21,Trades!$A:$A<=$B23),0)+IFNA(filter(Trades!$J:$J,Trades!$F:$F=I$1,Trades!$A:$A>=$B21,Trades!$A:$A<=$B23),0)"),0.0) -> 0 | J21: =IFERROR(__xludf.DUMMYFUNCTION("IFNA(filter(Trades!$J:$J,Trades!$B:$B=J$1,Trades!$A:$A>=$B21,Trades!$A:$A<=$B23),0)+IFNA(filter(Trades!$J:$J,Trades!$F:$F=J$1,Trades!$A:$A>=$B21,Trades!$A:$A<=$B23),0)"),0.0) -> 0 | K21: =IFERROR(__xludf.DUMMYFUNCTION("IFNA(filter(Trades!$J:$J,Trades!$B:$B=K$1,Trades!$A:$A>=$B21,Trades!$A:$A<=$B23),0)+IFNA(filter(Trades!$J:$J,Trades!$F:$F=K$1,Trades!$A:$A>=$B21,Trades!$A:$A<=$B23),0)"),0.0) -> 0 | L21: =IFERROR(__xludf.DUMMYFUNCTION("IFNA(filter(Trades!$J:$J,Trades!$B:$B=L$1,Trades!$A:$A>=$B21,Trades!$A:$A<=$B23),0)+IFNA(filter(Trades!$J:$J,Trades!$F:$F=L$1,Trades!$A:$A>=$B21,Trades!$A:$A<=$B23),0)"),0.0) -> 0 | M21: =IFERROR(__xludf.DUMMYFUNCTION("IFNA(filter(Trades!$J:$J,Trades!$B:$B=M$1,Trades!$A:$A>=$B21,Trades!$A:$A<=$B23),0)+IFNA(filter(Trades!$J:$J,Trades!$F:$F=M$1,Trades!$A:$A>=$B21,Trades!$A:$A<=$B23),0)"),0.0) -> 0 | N21: =IFERROR(__xludf.DUMMYFUNCTION("IFNA(filter(Trades!$J:$J,Trades!$B:$B=N$1,Trades!$A:$A>=$B21,Trades!$A:$A<=$B23),0)+IFNA(filter(Trades!$J:$J,Trades!$F:$F=N$1,Trades!$A:$A>=$B21,Trades!$A:$A<=$B23),0)"),0.0) -> 0 | O21: =IFERROR(__xludf.DUMMYFUNCTION("IFNA(filter(Trades!$J:$J,Trades!$B:$B=O$1,Trades!$A:$A>=$B21,Trades!$A:$A<=$B23),0)+IFNA(filter(Trades!$J:$J,Trades!$F:$F=O$1,Trades!$A:$A>=$B21,Trades!$A:$A<=$B23),0)"),0.0) -> 0
C22: Tokens Traded/Voided
C23: Adds >= $25 | D23: =IF(countifs(Waivers!$B:$B,"="&D$1,Waivers!$F:$F,">"&datevalue($B20-1),Waivers!$F:$F,"<"&datevalue($B24+1),Waivers!$G:$G,">9")>4,5,countifs(Waivers!$B:$B,"="&D$1,Waivers!$F:$F,">"&datevalue($B20-1),Waivers!$F:$F,"<"&datevalue($B24+1),Waivers!$G:$G,">9")) -> 0 | E23: =IF(countifs(Waivers!$B:$B,"="&E$1,Waivers!$F:$F,">"&datevalue($B20-1),Waivers!$F:$F,"<"&datevalue($B24+1),Waivers!$G:$G,">9")>4,5,countifs(Waivers!$B:$B,"="&E$1,Waivers!$F:$F,">"&datevalue($B20-1),Waivers!$F:$F,"<"&datevalue($B24+1),Waivers!$G:$G,">9")) -> 0 | F23: =IF(countifs(Waivers!$B:$B,"="&F$1,Waivers!$F:$F,">"&datevalue($B20-1),Waivers!$F:$F,"<"&datevalue($B24+1),Waivers!$G:$G,">9")>4,5,countifs(Waivers!$B:$B,"="&F$1,Waivers!$F:$F,">"&datevalue($B20-1),Waivers!$F:$F,"<"&datevalue($B24+1),Waivers!$G:$G,">9")) -> 0 | G23: =IF(countifs(Waivers!$B:$B,"="&G$1,Waivers!$F:$F,">"&datevalue($B20-1),Waivers!$F:$F,"<"&datevalue($B24+1),Waivers!$G:$G,">9")>4,5,countifs(Waivers!$B:$B,"="&G$1,Waivers!$F:$F,">"&datevalue($B20-1),Waivers!$F:$F,"<"&datevalue($B24+1),Waivers!$G:$G,">9")) -> 0 | H23: =IF(countifs(Waivers!$B:$B,"="&H$1,Waivers!$F:$F,">"&datevalue($B20-1),Waivers!$F:$F,"<"&datevalue($B24+1),Waivers!$G:$G,">9")>4,5,countifs(Waivers!$B:$B,"="&H$1,Waivers!$F:$F,">"&datevalue($B20-1),Waivers!$F:$F,"<"&datevalue($B24+1),Waivers!$G:$G,">9")) -> 0 | I23: =IF(countifs(Waivers!$B:$B,"="&I$1,Waivers!$F:$F,">"&datevalue($B20-1),Waivers!$F:$F,"<"&datevalue($B24+1),Waivers!$G:$G,">9")>4,5,countifs(Waivers!$B:$B,"="&I$1,Waivers!$F:$F,">"&datevalue($B20-1),Waivers!$F:$F,"<"&datevalue($B24+1),Waivers!$G:$G,">9")) -> 0 | J23: =IF(countifs(Waivers!$B:$B,"="&J$1,Waivers!$F:$F,">"&datevalue($B20-1),Waivers!$F:$F,"<"&datevalue($B24+1),Waivers!$G:$G,">9")>4,5,countifs(Waivers!$B:$B,"="&J$1,Waivers!$F:$F,">"&datevalue($B20-1),Waivers!$F:$F,"<"&datevalue($B24+1),Waivers!$G:$G,">9")) -> 0 | K23: =IF(countifs(Waivers!$B:$B,"="&K$1,Waivers!$F:$F,">"&datevalue($B20-1),Waivers!$F:$F,"<"&datevalue($B24+1),Waivers!$G:$G,">9")>4,5,countifs(Waivers!$B:$B,"="&K$1,Waivers!$F:$F,">"&datevalue($B20-1),Waivers!$F:$F,"<"&datevalue($B24+1),Waivers!$G:$G,">9")) -> 0 | ... O23: =IF(countifs(Waivers!$B:$B,"="&O$1,Waivers!$F:$F,">"&datevalue($B20-1),Waivers!$F:$F,"<"&datevalue($B24+1),Waivers!$G:$G,">9")>4,5,countifs(Waivers!$B:$B,"="&O$1,Waivers!$F:$F,">"&datevalue($B20-1),Waivers!$F:$F,"<"&datevalue($B24+1),Waivers!$G:$G,">9")) -> 0
B24: 46349 | C24: Promotion Award
A25: Post | B25: 46350 | C25: Trades | D25: =IFERROR(__xludf.DUMMYFUNCTION("IFNA(filter(Trades!$J:$J,Trades!$B:$B=D$1,Trades!$A:$A>=$B25,Trades!$A:$A<=$B27),0)+IFNA(filter(Trades!$J:$J,Trades!$F:$F=D$1,Trades!$A:$A>=$B25,Trades!$A:$A<=$B27),0)"),0.0) -> 0 | E25: =IFERROR(__xludf.DUMMYFUNCTION("IFNA(filter(Trades!$J:$J,Trades!$B:$B=E$1,Trades!$A:$A>=$B25,Trades!$A:$A<=$B27),0)+IFNA(filter(Trades!$J:$J,Trades!$F:$F=E$1,Trades!$A:$A>=$B25,Trades!$A:$A<=$B27),0)"),0.0) -> 0 | F25: =IFERROR(__xludf.DUMMYFUNCTION("IFNA(filter(Trades!$J:$J,Trades!$B:$B=F$1,Trades!$A:$A>=$B25,Trades!$A:$A<=$B27),0)+IFNA(filter(Trades!$J:$J,Trades!$F:$F=F$1,Trades!$A:$A>=$B25,Trades!$A:$A<=$B27),0)"),0.0) -> 0 | G25: =IFERROR(__xludf.DUMMYFUNCTION("IFNA(filter(Trades!$J:$J,Trades!$B:$B=G$1,Trades!$A:$A>=$B25,Trades!$A:$A<=$B27),0)+IFNA(filter(Trades!$J:$J,Trades!$F:$F=G$1,Trades!$A:$A>=$B25,Trades!$A:$A<=$B27),0)"),0.0) -> 0 | H25: =IFERROR(__xludf.DUMMYFUNCTION("IFNA(filter(Trades!$J:$J,Trades!$B:$B=H$1,Trades!$A:$A>=$B25,Trades!$A:$A<=$B27),0)+IFNA(filter(Trades!$J:$J,Trades!$F:$F=H$1,Trades!$A:$A>=$B25,Trades!$A:$A<=$B27),0)"),0.0) -> 0 | I25: =IFERROR(__xludf.DUMMYFUNCTION("IFNA(filter(Trades!$J:$J,Trades!$B:$B=I$1,Trades!$A:$A>=$B25,Trades!$A:$A<=$B27),0)+IFNA(filter(Trades!$J:$J,Trades!$F:$F=I$1,Trades!$A:$A>=$B25,Trades!$A:$A<=$B27),0)"),0.0) -> 0 | J25: =IFERROR(__xludf.DUMMYFUNCTION("IFNA(filter(Trades!$J:$J,Trades!$B:$B=J$1,Trades!$A:$A>=$B25,Trades!$A:$A<=$B27),0)+IFNA(filter(Trades!$J:$J,Trades!$F:$F=J$1,Trades!$A:$A>=$B25,Trades!$A:$A<=$B27),0)"),0.0) -> 0 | K25: =IFERROR(__xludf.DUMMYFUNCTION("IFNA(filter(Trades!$J:$J,Trades!$B:$B=K$1,Trades!$A:$A>=$B25,Trades!$A:$A<=$B27),0)+IFNA(filter(Trades!$J:$J,Trades!$F:$F=K$1,Trades!$A:$A>=$B25,Trades!$A:$A<=$B27),0)"),0.0) -> 0 | L25: =IFERROR(__xludf.DUMMYFUNCTION("IFNA(filter(Trades!$J:$J,Trades!$B:$B=L$1,Trades!$A:$A>=$B25,Trades!$A:$A<=$B27),0)+IFNA(filter(Trades!$J:$J,Trades!$F:$F=L$1,Trades!$A:$A>=$B25,Trades!$A:$A<=$B27),0)"),0.0) -> 0 | M25: =IFERROR(__xludf.DUMMYFUNCTION("IFNA(filter(Trades!$J:$J,Trades!$B:$B=M$1,Trades!$A:$A>=$B25,Trades!$A:$A<=$B27),0)+IFNA(filter(Trades!$J:$J,Trades!$F:$F=M$1,Trades!$A:$A>=$B25,Trades!$A:$A<=$B27),0)"),0.0) -> 0 | N25: =IFERROR(__xludf.DUMMYFUNCTION("IFNA(filter(Trades!$J:$J,Trades!$B:$B=N$1,Trades!$A:$A>=$B25,Trades!$A:$A<=$B27),0)+IFNA(filter(Trades!$J:$J,Trades!$F:$F=N$1,Trades!$A:$A>=$B25,Trades!$A:$A<=$B27),0)"),0.0) -> 0 | O25: =IFERROR(__xludf.DUMMYFUNCTION("IFNA(filter(Trades!$J:$J,Trades!$B:$B=O$1,Trades!$A:$A>=$B25,Trades!$A:$A<=$B27),0)+IFNA(filter(Trades!$J:$J,Trades!$F:$F=O$1,Trades!$A:$A>=$B25,Trades!$A:$A<=$B27),0)"),0.0) -> 0
A26: Season | C26: Tokens Traded
B27: 46387 | C27: Adds >= $25 | D27: =IF(countifs(Waivers!$B:$B,"="&D$1,Waivers!$F:$F,">"&datevalue($B25-1),Waivers!$F:$F,"<"&datevalue($B27+1),Waivers!$G:$G,">9")>4,5,countifs(Waivers!$B:$B,"="&D$1,Waivers!$F:$F,">"&datevalue($B25-1),Waivers!$F:$F,"<"&datevalue($B27+1),Waivers!$G:$G,">9")) -> 0 | E27: =IF(countifs(Waivers!$B:$B,"="&E$1,Waivers!$F:$F,">"&datevalue($B25-1),Waivers!$F:$F,"<"&datevalue($B27+1),Waivers!$G:$G,">9")>4,5,countifs(Waivers!$B:$B,"="&E$1,Waivers!$F:$F,">"&datevalue($B25-1),Waivers!$F:$F,"<"&datevalue($B27+1),Waivers!$G:$G,">9")) -> 0 | F27: =IF(countifs(Waivers!$B:$B,"="&F$1,Waivers!$F:$F,">"&datevalue($B25-1),Waivers!$F:$F,"<"&datevalue($B27+1),Waivers!$G:$G,">9")>4,5,countifs(Waivers!$B:$B,"="&F$1,Waivers!$F:$F,">"&datevalue($B25-1),Waivers!$F:$F,"<"&datevalue($B27+1),Waivers!$G:$G,">9")) -> 0 | G27: =IF(countifs(Waivers!$B:$B,"="&G$1,Waivers!$F:$F,">"&datevalue($B25-1),Waivers!$F:$F,"<"&datevalue($B27+1),Waivers!$G:$G,">9")>4,5,countifs(Waivers!$B:$B,"="&G$1,Waivers!$F:$F,">"&datevalue($B25-1),Waivers!$F:$F,"<"&datevalue($B27+1),Waivers!$G:$G,">9")) -> 0 | H27: =IF(countifs(Waivers!$B:$B,"="&H$1,Waivers!$F:$F,">"&datevalue($B25-1),Waivers!$F:$F,"<"&datevalue($B27+1),Waivers!$G:$G,">9")>4,5,countifs(Waivers!$B:$B,"="&H$1,Waivers!$F:$F,">"&datevalue($B25-1),Waivers!$F:$F,"<"&datevalue($B27+1),Waivers!$G:$G,">9")) -> 0 | I27: =IF(countifs(Waivers!$B:$B,"="&I$1,Waivers!$F:$F,">"&datevalue($B25-1),Waivers!$F:$F,"<"&datevalue($B27+1),Waivers!$G:$G,">9")>4,5,countifs(Waivers!$B:$B,"="&I$1,Waivers!$F:$F,">"&datevalue($B25-1),Waivers!$F:$F,"<"&datevalue($B27+1),Waivers!$G:$G,">9")) -> 0 | J27: =IF(countifs(Waivers!$B:$B,"="&J$1,Waivers!$F:$F,">"&datevalue($B25-1),Waivers!$F:$F,"<"&datevalue($B27+1),Waivers!$G:$G,">9")>4,5,countifs(Waivers!$B:$B,"="&J$1,Waivers!$F:$F,">"&datevalue($B25-1),Waivers!$F:$F,"<"&datevalue($B27+1),Waivers!$G:$G,">9")) -> 0 | K27: =IF(countifs(Waivers!$B:$B,"="&K$1,Waivers!$F:$F,">"&datevalue($B25-1),Waivers!$F:$F,"<"&datevalue($B27+1),Waivers!$G:$G,">9")>4,5,countifs(Waivers!$B:$B,"="&K$1,Waivers!$F:$F,">"&datevalue($B25-1),Waivers!$F:$F,"<"&datevalue($B27+1),Waivers!$G:$G,">9")) -> 0 | ... O27: =IF(countifs(Waivers!$B:$B,"="&O$1,Waivers!$F:$F,">"&datevalue($B25-1),Waivers!$F:$F,"<"&datevalue($B27+1),Waivers!$G:$G,">9")>4,5,countifs(Waivers!$B:$B,"="&O$1,Waivers!$F:$F,">"&datevalue($B25-1),Waivers!$F:$F,"<"&datevalue($B27+1),Waivers!$G:$G,">9")) -> 0
A28: Token Award Draw | B28: 46395 | C28: Tokens Committed
A29: Token Award Draw | B29: 46397 | C29: Tokens Won

Sheet Trades

Sheet Waivers
A1: Date | B1: Team | C1: Add | D1: Amount | E1: 371
A2: =IFERROR(__xludf.DUMMYFUNCTION("importhtml(""https://www.myfantasyleague.com/2026/options?L=63213&O=03&TYPE=WAIVER&FRANCHISE=0000&DAYS=3000&REFRESH=""&E1,""table"",2)"),"#") -> # | B2: =IFERROR(__xludf.DUMMYFUNCTION("""COMPUTED_VALUE"""),"Franchise") -> Franchise | C2: =IFERROR(__xludf.DUMMYFUNCTION("""COMPUTED_VALUE"""),"Type") -> Type | D2: =IFERROR(__xludf.DUMMYFUNCTION("""COMPUTED_VALUE"""),"Transaction") -> Transaction | E2: =IFERROR(__xludf.DUMMYFUNCTION("""COMPUTED_VALUE"""),"Date") -> Date | F2: Date | G2: Value | H2: Voided
A3: =IFERROR(__xludf.DUMMYFUNCTION("""COMPUTED_VALUE"""),1.0) -> 1 | B3: =IFERROR(__xludf.DUMMYFUNCTION("""COMPUTED_VALUE"""),"BattleBots") -> BattleBots | C3: =IFERROR(__xludf.DUMMYFUNCTION("""COMPUTED_VALUE"""),"Waiver") -> Waiver | D3: =IFERROR(__xludf.DUMMYFUNCTION("""COMPUTED_VALUE"""),"- Acquired Tremble, Tommy CAR TE for $1.00") -> - Acquired Tremble, Tommy CAR TE for $1.00 | E3: =IFERROR(__xludf.DUMMYFUNCTION("""COMPUTED_VALUE"""),"Wed Oct 21 11:00:00 a.m. ET 2026") -> Wed Oct 21 11:00:00 a.m. ET 2026 | F3: =iferror(datevalue(left(E3,10)&right(E3,5)),"") -> 46316 | G3: =iferror(value(mid(D3,find("$",D3)+1,4)),"") -> 1
A4: =IFERROR(__xludf.DUMMYFUNCTION("""COMPUTED_VALUE"""),2.0) -> 2 | B4: =IFERROR(__xludf.DUMMYFUNCTION("""COMPUTED_VALUE"""),"Orcan Terror") -> Orcan Terror | C4: =IFERROR(__xludf.DUMMYFUNCTION("""COMPUTED_VALUE"""),"Waiver") -> Waiver | D4: =IFERROR(__xludf.DUMMYFUNCTION("""COMPUTED_VALUE"""),"- Acquired Cooks, Brandin SFO WR for $25.00 - Dropped Cooper, Darius PHI WR") -> - Acquired Cooks, Brandin SFO WR for $25.00 - Dropped Cooper, Darius PHI WR | E4: =IFERROR(__xludf.DUMMYFUNCTION("""COMPUTED_VALUE"""),"Wed Oct 21 11:00:00 a.m. ET 2026") -> Wed Oct 21 11:00:00 a.m. ET 2026 | F4: =iferror(datevalue(left(E4,10)&right(E4,5)),"") -> 46316 | G4: =iferror(value(mid(D4,find("$",D4)+1,4)),"") -> 25
A5: =IFERROR(__xludf.DUMMYFUNCTION("""COMPUTED_VALUE"""),3.0) -> 3 | B5: =IFERROR(__xludf.DUMMYFUNCTION("""COMPUTED_VALUE"""),"Springfield Isotopes") -> Springfield Isotopes | C5: =IFERROR(__xludf.DUMMYFUNCTION("""COMPUTED_VALUE"""),"Waiver") -> Waiver | D5: =IFERROR(__xludf.DUMMYFUNCTION("""COMPUTED_VALUE"""),"- Acquired Mumpfield, Konata LAR WR for $37.00 - Dropped Patrick, Tim NYJ WR") -> - Acquired Mumpfield, Konata LAR WR for $37.00 - Dropped Patrick, Tim NYJ WR | E5: =IFERROR(__xludf.DUMMYFUNCTION("""COMPUTED_VALUE"""),"Wed Oct 21 11:00:00 a.m. ET 2026") -> Wed Oct 21 11:00:00 a.m. ET 2026 | F5: =iferror(datevalue(left(E5,10)&right(E5,5)),"") -> 46316 | G5: =iferror(value(mid(D5,find("$",D5)+1,4)),"") -> 37
A6: =IFERROR(__xludf.DUMMYFUNCTION("""COMPUTED_VALUE"""),4.0) -> 4 | B6: =IFERROR(__xludf.DUMMYFUNCTION("""COMPUTED_VALUE"""),"BattleBots") -> BattleBots | C6: =IFERROR(__xludf.DUMMYFUNCTION("""COMPUTED_VALUE"""),"Waiver") -> Waiver | D6: =IFERROR(__xludf.DUMMYFUNCTION("""COMPUTED_VALUE"""),"- Acquired Johnson, Roschon CHI RB for $51.00") -> - Acquired Johnson, Roschon CHI RB for $51.00 | E6: =IFERROR(__xludf.DUMMYFUNCTION("""COMPUTED_VALUE"""),"Wed Oct 21 11:00:00 a.m. ET 2026") -> Wed Oct 21 11:00:00 a.m. ET 2026 | F6: =iferror(datevalue(left(E6,10)&right(E6,5)),"") -> 46316 | G6: =iferror(value(mid(D6,find("$",D6)+1,4)),"") -> 51
A7: =IFERROR(__xludf.DUMMYFUNCTION("""COMPUTED_VALUE"""),5.0) -> 5 | B7: =IFERROR(__xludf.DUMMYFUNCTION("""COMPUTED_VALUE"""),"BattleBots") -> BattleBots | C7: =IFERROR(__xludf.DUMMYFUNCTION("""COMPUTED_VALUE"""),"Waiver") -> Waiver | D7: =IFERROR(__xludf.DUMMYFUNCTION("""COMPUTED_VALUE"""),"- Acquired Bagent, Tyson CHI QB for $1.00") -> - Acquired Bagent, Tyson CHI QB for $1.00 | E7: =IFERROR(__xludf.DUMMYFUNCTION("""COMPUTED_VALUE"""),"Fri Oct 16 11:00:00 a.m. ET 2026") -> Fri Oct 16 11:00:00 a.m. ET 2026 | F7: =iferror(datevalue(left(E7,10)&right(E7,5)),"") -> 46311 | G7: =iferror(value(mid(D7,find("$",D7)+1,4)),"") -> 1
A8: =IFERROR(__xludf.DUMMYFUNCTION("""COMPUTED_VALUE"""),6.0) -> 6 | B8: =IFERROR(__xludf.DUMMYFUNCTION("""COMPUTED_VALUE"""),"BattleBots") -> BattleBots | C8: =IFERROR(__xludf.DUMMYFUNCTION("""COMPUTED_VALUE"""),"Waiver") -> Waiver | D8: =IFERROR(__xludf.DUMMYFUNCTION("""COMPUTED_VALUE"""),"- Acquired Treadwell, Laquon IND WR for $1.00 - Dropped Keenum, Case CHI QB") -> - Acquired Treadwell, Laquon IND WR for $1.00 - Dropped Keenum, Case CHI QB | E8: =IFERROR(__xludf.DUMMYFUNCTION("""COMPUTED_VALUE"""),"Wed Oct 14 11:00:00 a.m. ET 2026") -> Wed Oct 14 11:00:00 a.m. ET 2026 | F8: =iferror(datevalue(left(E8,10)&right(E8,5)),"") -> 46309 | G8: =iferror(value(mid(D8,find("$",D8)+1,4)),"") -> 1
A9: =IFERROR(__xludf.DUMMYFUNCTION("""COMPUTED_VALUE"""),7.0) -> 7 | B9: =IFERROR(__xludf.DUMMYFUNCTION("""COMPUTED_VALUE"""),"Norsemen") -> Norsemen | C9: =IFERROR(__xludf.DUMMYFUNCTION("""COMPUTED_VALUE"""),"Waiver") -> Waiver | D9: =IFERROR(__xludf.DUMMYFUNCTION("""COMPUTED_VALUE"""),"- Acquired Felton, Tai MIN WR for $1.00 - Dropped Vaki, Sione DET RB") -> - Acquired Felton, Tai MIN WR for $1.00 - Dropped Vaki, Sione DET RB | E9: =IFERROR(__xludf.DUMMYFUNCTION("""COMPUTED_VALUE"""),"Wed Oct 14 11:00:00 a.m. ET 2026") -> Wed Oct 14 11:00:00 a.m. ET 2026 | F9: =iferror(datevalue(left(E9,10)&right(E9,5)),"") -> 46309 | G9: =iferror(value(mid(D9,find("$",D9)+1,4)),"") -> 1
A10: =IFERROR(__xludf.DUMMYFUNCTION("""COMPUTED_VALUE"""),8.0) -> 8 | B10: =IFERROR(__xludf.DUMMYFUNCTION("""COMPUTED_VALUE"""),"Orcan Terror") -> Orcan Terror | C10: =IFERROR(__xludf.DUMMYFUNCTION("""COMPUTED_VALUE"""),"Waiver") -> Waiver | D10: =IFERROR(__xludf.DUMMYFUNCTION("""COMPUTED_VALUE"""),"- Acquired Pierce, Dameon PHI RB for $28.00 - Dropped Rattler, Spencer NOS QB") -> - Acquired Pierce, Dameon PHI RB for $28.00 - Dropped Rattler, Spencer NOS QB | E10: =IFERROR(__xludf.DUMMYFUNCTION("""COMPUTED_VALUE"""),"Wed Oct 14 11:00:00 a.m. ET 2026") -> Wed Oct 14 11:00:00 a.m. ET 2026 | F10: =iferror(datevalue(left(E10,10)&right(E10,5)),"") -> 46309 | G10: =iferror(value(mid(D10,find("$",D10)+1,4)),"") -> 28
A11: =IFERROR(__xludf.DUMMYFUNCTION("""COMPUTED_VALUE"""),9.0) -> 9 | B11: =IFERROR(__xludf.DUMMYFUNCTION("""COMPUTED_VALUE"""),"Shankly's Ghost") -> Shankly's Ghost | C11: =IFERROR(__xludf.DUMMYFUNCTION("""COMPUTED_VALUE"""),"Waiver") -> Waiver | D11: =IFERROR(__xludf.DUMMYFUNCTION("""COMPUTED_VALUE"""),"- Acquired Ayomanor, Elic TEN WR for $3.00 - Dropped Allen, Kaytron MIA RB") -> - Acquired Ayomanor, Elic TEN WR for $3.00 - Dropped Allen, Kaytron MIA RB | E11: =IFERROR(__xludf.DUMMYFUNCTION("""COMPUTED_VALUE"""),"Fri Oct 9 11:00:00 a.m. ET 2026") -> Fri Oct 9 11:00:00 a.m. ET 2026 | F11: =iferror(datevalue(left(E11,10)&right(E11,5)),"") -> 46304 | G11: =iferror(value(mid(D11,find("$",D11)+1,4)),"") -> 3
A12: =IFERROR(__xludf.DUMMYFUNCTION("""COMPUTED_VALUE"""),10.0) -> 10 | B12: =IFERROR(__xludf.DUMMYFUNCTION("""COMPUTED_VALUE"""),"Springfield Isotopes") -> Springfield Isotopes | C12: =IFERROR(__xludf.DUMMYFUNCTION("""COMPUTED_VALUE"""),"Waiver") -> Waiver | D12: =IFERROR(__xludf.DUMMYFUNCTION("""COMPUTED_VALUE"""),"- Acquired Vidal, Kimani LAC RB for $2.00 - Dropped Ridley, Calvin TEN WR") -> - Acquired Vidal, Kimani LAC RB for $2.00 - Dropped Ridley, Calvin TEN WR | E12: =IFERROR(__xludf.DUMMYFUNCTION("""COMPUTED_VALUE"""),"Wed Oct 7 11:00:00 a.m. ET 2026") -> Wed Oct 7 11:00:00 a.m. ET 2026 | F12: =iferror(datevalue(left(E12,10)&right(E12,5)),"") -> 46302 | G12: =iferror(value(mid(D12,find("$",D12)+1,4)),"") -> 2
A13: =IFERROR(__xludf.DUMMYFUNCTION("""COMPUTED_VALUE"""),11.0) -> 11 | B13: =IFERROR(__xludf.DUMMYFUNCTION("""COMPUTED_VALUE"""),"BattleBots") -> BattleBots | C13: =IFERROR(__xludf.DUMMYFUNCTION("""COMPUTED_VALUE"""),"Waiver") -> Waiver | D13: =IFERROR(__xludf.DUMMYFUNCTION("""COMPUTED_VALUE"""),"- Acquired Royals, Jalen KCC WR for $25.00 - Dropped Davis, Ray BUF RB") -> - Acquired Royals, Jalen KCC WR for $25.00 - Dropped Davis, Ray BUF RB | E13: =IFERROR(__xludf.DUMMYFUNCTION("""COMPUTED_VALUE"""),"Wed Oct 7 11:00:00 a.m. ET 2026") -> Wed Oct 7 11:00:00 a.m. ET 2026 | F13: =iferror(datevalue(left(E13,10)&right(E13,5)),"") -> 46302 | G13: =iferror(value(mid(D13,find("$",D13)+1,4)),"") -> 25
A14: =IFERROR(__xludf.DUMMYFUNCTION("""COMPUTED_VALUE"""),12.0) -> 12 | B14: =IFERROR(__xludf.DUMMYFUNCTION("""COMPUTED_VALUE"""),"The Two Tones") -> The Two Tones | C14: =IFERROR(__xludf.DUMMYFUNCTION("""COMPUTED_VALUE"""),"Waiver") -> Waiver | D14: =IFERROR(__xludf.DUMMYFUNCTION("""COMPUTED_VALUE"""),"- Acquired Meyers, Dohnte CIN WR for $45.00 - Dropped Horn, Jimmy CLE WR") -> - Acquired Meyers, Dohnte CIN WR for $45.00 - Dropped Horn, Jimmy CLE WR | E14: =IFERROR(__xludf.DUMMYFUNCTION("""COMPUTED_VALUE"""),"Wed Oct 7 11:00:00 a.m. ET 2026") -> Wed Oct 7 11:00:00 a.m. ET 2026 | F14: =iferror(datevalue(left(E14,10)&right(E14,5)),"") -> 46302 | G14: =iferror(value(mid(D14,find("$",D14)+1,4)),"") -> 45
A15: =IFERROR(__xludf.DUMMYFUNCTION("""COMPUTED_VALUE"""),13.0) -> 13 | B15: =IFERROR(__xludf.DUMMYFUNCTION("""COMPUTED_VALUE"""),"BattleBots") -> BattleBots | C15: =IFERROR(__xludf.DUMMYFUNCTION("""COMPUTED_VALUE"""),"Waiver") -> Waiver | D15: =IFERROR(__xludf.DUMMYFUNCTION("""COMPUTED_VALUE"""),"- Acquired Johnson, Roschon CHI RB for $25.00 - Dropped Tremble, Tommy CAR TE") -> - Acquired Johnson, Roschon CHI RB for $25.00 - Dropped Tremble, Tommy CAR TE | E15: =IFERROR(__xludf.DUMMYFUNCTION("""COMPUTED_VALUE"""),"Fri Oct 2 11:00:00 a.m. ET 2026") -> Fri Oct 2 11:00:00 a.m. ET 2026 | F15: =iferror(datevalue(left(E15,10)&right(E15,5)),"") -> 46297 | G15: =iferror(value(mid(D15,find("$",D15)+1,4)),"") -> 25
A16: =IFERROR(__xludf.DUMMYFUNCTION("""COMPUTED_VALUE"""),14.0) -> 14 | B16: =IFERROR(__xludf.DUMMYFUNCTION("""COMPUTED_VALUE"""),"Peaky Fookin Blinders") -> Peaky Fookin Blinders | C16: =IFERROR(__xludf.DUMMYFUNCTION("""COMPUTED_VALUE"""),"Waiver") -> Waiver | D16: =IFERROR(__xludf.DUMMYFUNCTION("""COMPUTED_VALUE"""),"- Acquired Mumpfield, Konata LAR WR for $71.00 - Dropped Walker, Jahdae CHI WR") -> - Acquired Mumpfield, Konata LAR WR for $71.00 - Dropped Walker, Jahdae CHI WR | E16: =IFERROR(__xludf.DUMMYFUNCTION("""COMPUTED_VALUE"""),"Wed Sep 30 11:00:00 a.m. ET 2026") -> Wed Sep 30 11:00:00 a.m. ET 2026 | F16: =iferror(datevalue(left(E16,10)&right(E16,5)),"") -> 46295 | G16: =iferror(value(mid(D16,find("$",D16)+1,4)),"") -> 71
A17: =IFERROR(__xludf.DUMMYFUNCTION("""COMPUTED_VALUE"""),15.0) -> 15 | B17: =IFERROR(__xludf.DUMMYFUNCTION("""COMPUTED_VALUE"""),"Orcan Terror") -> Orcan Terror | C17: =IFERROR(__xludf.DUMMYFUNCTION("""COMPUTED_VALUE"""),"Waiver") -> Waiver | D17: =IFERROR(__xludf.DUMMYFUNCTION("""COMPUTED_VALUE"""),"- Acquired Wayne, Jared MIA WR for $0.00 - Dropped Metchie, John CAR WR") -> - Acquired Wayne, Jared MIA WR for $0.00 - Dropped Metchie, John CAR WR | E17: =IFERROR(__xludf.DUMMYFUNCTION("""COMPUTED_VALUE"""),"Fri Sep 25 11:00:00 a.m. ET 2026") -> Fri Sep 25 11:00:00 a.m. ET 2026 | F17: =iferror(datevalue(left(E17,10)&right(E17,5)),"") -> 46290 | G17: =iferror(value(mid(D17,find("$",D17)+1,4)),"") -> 0
A18: =IFERROR(__xludf.DUMMYFUNCTION("""COMPUTED_VALUE"""),16.0) -> 16 | B18: =IFERROR(__xludf.DUMMYFUNCTION("""COMPUTED_VALUE"""),"Ted Lasso") -> Ted Lasso | C18: =IFERROR(__xludf.DUMMYFUNCTION("""COMPUTED_VALUE"""),"Waiver") -> Waiver | D18: =IFERROR(__xludf.DUMMYFUNCTION("""COMPUTED_VALUE"""),"- Acquired Knox, Dawson BUF TE for $0.00") -> - Acquired Knox, Dawson BUF TE for $0.00 | E18: =IFERROR(__xludf.DUMMYFUNCTION("""COMPUTED_VALUE"""),"Wed Sep 23 11:00:00 a.m. ET 2026") -> Wed Sep 23 11:00:00 a.m. ET 2026 | F18: =iferror(datevalue(left(E18,10)&right(E18,5)),"") -> 46288 | G18: =iferror(value(mid(D18,find("$",D18)+1,4)),"") -> 0
A19: =IFERROR(__xludf.DUMMYFUNCTION("""COMPUTED_VALUE"""),17.0) -> 17 | B19: =IFERROR(__xludf.DUMMYFUNCTION("""COMPUTED_VALUE"""),"Springfield Isotopes") -> Springfield Isotopes | C19: =IFERROR(__xludf.DUMMYFUNCTION("""COMPUTED_VALUE"""),"Waiver") -> Waiver | D19: =IFERROR(__xludf.DUMMYFUNCTION("""COMPUTED_VALUE"""),"- Acquired Winston, Jameis NYG QB for $4.00 - Dropped Demercado, Emari DAL RB") -> - Acquired Winston, Jameis NYG QB for $4.00 - Dropped Demercado, Emari DAL RB | E19: =IFERROR(__xludf.DUMMYFUNCTION("""COMPUTED_VALUE"""),"Wed Sep 23 11:00:00 a.m. ET 2026") -> Wed Sep 23 11:00:00 a.m. ET 2026 | F19: =iferror(datevalue(left(E19,10)&right(E19,5)),"") -> 46288 | G19: =iferror(value(mid(D19,find("$",D19)+1,4)),"") -> 4
A20: =IFERROR(__xludf.DUMMYFUNCTION("""COMPUTED_VALUE"""),18.0) -> 18 | B20: =IFERROR(__xludf.DUMMYFUNCTION("""COMPUTED_VALUE"""),"Shankly's Ghost") -> Shankly's Ghost | C20: =IFERROR(__xludf.DUMMYFUNCTION("""COMPUTED_VALUE"""),"Waiver") -> Waiver | D20: =IFERROR(__xludf.DUMMYFUNCTION("""COMPUTED_VALUE"""),"- Acquired Ertz, Zach PHI TE for $21.00 - Dropped Dotson, Jahan ATL WR") -> - Acquired Ertz, Zach PHI TE for $21.00 - Dropped Dotson, Jahan ATL WR | E20: =IFERROR(__xludf.DUMMYFUNCTION("""COMPUTED_VALUE"""),"Wed Sep 23 11:00:00 a.m. ET 2026") -> Wed Sep 23 11:00:00 a.m. ET 2026 | F20: =iferror(datevalue(left(E20,10)&right(E20,5)),"") -> 46288 | G20: =iferror(value(mid(D20,find("$",D20)+1,4)),"") -> 21
A21: =IFERROR(__xludf.DUMMYFUNCTION("""COMPUTED_VALUE"""),19.0) -> 19 | B21: =IFERROR(__xludf.DUMMYFUNCTION("""COMPUTED_VALUE"""),"BattleBots") -> BattleBots | C21: =IFERROR(__xludf.DUMMYFUNCTION("""COMPUTED_VALUE"""),"Waiver") -> Waiver | D21: =IFERROR(__xludf.DUMMYFUNCTION("""COMPUTED_VALUE"""),"- Acquired Keenum, Case CHI QB for $25.00") -> - Acquired Keenum, Case CHI QB for $25.00 | E21: =IFERROR(__xludf.DUMMYFUNCTION("""COMPUTED_VALUE"""),"Wed Sep 23 11:00:00 a.m. ET 2026") -> Wed Sep 23 11:00:00 a.m. ET 2026 | F21: =iferror(datevalue(left(E21,10)&right(E21,5)),"") -> 46288 | G21: =iferror(value(mid(D21,find("$",D21)+1,4)),"") -> 25
A22: =IFERROR(__xludf.DUMMYFUNCTION("""COMPUTED_VALUE"""),20.0) -> 20 | B22: =IFERROR(__xludf.DUMMYFUNCTION("""COMPUTED_VALUE"""),"Peaky Fookin Blinders") -> Peaky Fookin Blinders | C22: =IFERROR(__xludf.DUMMYFUNCTION("""COMPUTED_VALUE"""),"Waiver") -> Waiver | D22: =IFERROR(__xludf.DUMMYFUNCTION("""COMPUTED_VALUE"""),"- Acquired Wilson, Emanuel SEA RB for $323.00 - Dropped Davis, Isaiah NYJ RB") -> - Acquired Wilson, Emanuel SEA RB for $323.00 - Dropped Davis, Isaiah NYJ RB | E22: =IFERROR(__xludf.DUMMYFUNCTION("""COMPUTED_VALUE"""),"Wed Sep 23 11:00:00 a.m. ET 2026") -> Wed Sep 23 11:00:00 a.m. ET 2026 | F22: =iferror(datevalue(left(E22,10)&right(E22,5)),"") -> 46288 | G22: =iferror(value(mid(D22,find("$",D22)+1,4)),"") -> 323
A23: =IFERROR(__xludf.DUMMYFUNCTION("""COMPUTED_VALUE"""),21.0) -> 21 | B23: =IFERROR(__xludf.DUMMYFUNCTION("""COMPUTED_VALUE"""),"Shankly's Ghost") -> Shankly's Ghost | C23: =IFERROR(__xludf.DUMMYFUNCTION("""COMPUTED_VALUE"""),"Waiver") -> Waiver | D23: =IFERROR(__xludf.DUMMYFUNCTION("""COMPUTED_VALUE"""),"- Acquired Wentz, Carson MIN QB for $21.00") -> - Acquired Wentz, Carson MIN QB for $21.00 | E23: =IFERROR(__xludf.DUMMYFUNCTION("""COMPUTED_VALUE"""),"Wed Sep 16 11:00:00 a.m. ET 2026") -> Wed Sep 16 11:00:00 a.m. ET 2026 | F23: =iferror(datevalue(left(E23,10)&right(E23,5)),"") -> 46281 | G23: =iferror(value(mid(D23,find("$",D23)+1,4)),"") -> 21
A24: =IFERROR(__xludf.DUMMYFUNCTION("""COMPUTED_VALUE"""),22.0) -> 22 | B24: =IFERROR(__xludf.DUMMYFUNCTION("""COMPUTED_VALUE"""),"2 Roops, 1 Silva") -> 2 Roops, 1 Silva | C24: =IFERROR(__xludf.DUMMYFUNCTION("""COMPUTED_VALUE"""),"Waiver") -> Waiver | D24: =IFERROR(__xludf.DUMMYFUNCTION("""COMPUTED_VALUE"""),"- Acquired Robinson, Demarcus SFO WR for $25.00") -> - Acquired Robinson, Demarcus SFO WR for $25.00 | E24: =IFERROR(__xludf.DUMMYFUNCTION("""COMPUTED_VALUE"""),"Wed Sep 16 11:00:00 a.m. ET 2026") -> Wed Sep 16 11:00:00 a.m. ET 2026 | F24: =iferror(datevalue(left(E24,10)&right(E24,5)),"") -> 46281 | G24: =iferror(value(mid(D24,find("$",D24)+1,4)),"") -> 25
A25: =IFERROR(__xludf.DUMMYFUNCTION("""COMPUTED_VALUE"""),23.0) -> 23 | B25: =IFERROR(__xludf.DUMMYFUNCTION("""COMPUTED_VALUE"""),"Orcan Terror") -> Orcan Terror | C25: =IFERROR(__xludf.DUMMYFUNCTION("""COMPUTED_VALUE"""),"Waiver") -> Waiver | D25: =IFERROR(__xludf.DUMMYFUNCTION("""COMPUTED_VALUE"""),"- Acquired Bourne, Kendrick ARI WR for $27.00") -> - Acquired Bourne, Kendrick ARI WR for $27.00 | E25: =IFERROR(__xludf.DUMMYFUNCTION("""COMPUTED_VALUE"""),"Wed Sep 16 11:00:00 a.m. ET 2026") -> Wed Sep 16 11:00:00 a.m. ET 2026 | F25: =iferror(datevalue(left(E25,10)&right(E25,5)),"") -> 46281 | G25: =iferror(value(mid(D25,find("$",D25)+1,4)),"") -> 27
A26: =IFERROR(__xludf.DUMMYFUNCTION("""COMPUTED_VALUE"""),24.0) -> 24 | B26: =IFERROR(__xludf.DUMMYFUNCTION("""COMPUTED_VALUE"""),"2 Roops, 1 Silva") -> 2 Roops, 1 Silva | C26: =IFERROR(__xludf.DUMMYFUNCTION("""COMPUTED_VALUE"""),"Waiver") -> Waiver | D26: =IFERROR(__xludf.DUMMYFUNCTION("""COMPUTED_VALUE"""),"- Acquired Raymond, Kalif CHI WR for $50.00") -> - Acquired Raymond, Kalif CHI WR for $50.00 | E26: =IFERROR(__xludf.DUMMYFUNCTION("""COMPUTED_VALUE"""),"Wed Sep 16 11:00:00 a.m. ET 2026") -> Wed Sep 16 11:00:00 a.m. ET 2026 | F26: =iferror(datevalue(left(E26,10)&right(E26,5)),"") -> 46281 | G26: =iferror(value(mid(D26,find("$",D26)+1,4)),"") -> 50
A27: =IFERROR(__xludf.DUMMYFUNCTION("""COMPUTED_VALUE"""),25.0) -> 25 | B27: =IFERROR(__xludf.DUMMYFUNCTION("""COMPUTED_VALUE"""),"2 Roops, 1 Silva") -> 2 Roops, 1 Silva | C27: =IFERROR(__xludf.DUMMYFUNCTION("""COMPUTED_VALUE"""),"Waiver") -> Waiver | D27: =IFERROR(__xludf.DUMMYFUNCTION("""COMPUTED_VALUE"""),"- Acquired Wilson, Roman PIT WR for $70.00 - Dropped Atwell, Tutu LAR WR") -> - Acquired Wilson, Roman PIT WR for $70.00 - Dropped Atwell, Tutu LAR WR | E27: =IFERROR(__xludf.DUMMYFUNCTION("""COMPUTED_VALUE"""),"Wed Sep 16 11:00:00 a.m. ET 2026") -> Wed Sep 16 11:00:00 a.m. ET 2026 | F27: =iferror(datevalue(left(E27,10)&right(E27,5)),"") -> 46281 | G27: =iferror(value(mid(D27,find("$",D27)+1,4)),"") -> 70
A28: =IFERROR(__xludf.DUMMYFUNCTION("""COMPUTED_VALUE"""),26.0) -> 26 | B28: =IFERROR(__xludf.DUMMYFUNCTION("""COMPUTED_VALUE"""),"The Meaty Ogres") -> The Meaty Ogres | C28: =IFERROR(__xludf.DUMMYFUNCTION("""COMPUTED_VALUE"""),"Waiver") -> Waiver | D28: =IFERROR(__xludf.DUMMYFUNCTION("""COMPUTED_VALUE"""),"- Acquired Lock, Drew SEA QB for $107.00") -> - Acquired Lock, Drew SEA QB for $107.00 | E28: =IFERROR(__xludf.DUMMYFUNCTION("""COMPUTED_VALUE"""),"Wed Sep 16 11:00:00 a.m. ET 2026") -> Wed Sep 16 11:00:00 a.m. ET 2026 | F28: =iferror(datevalue(left(E28,10)&right(E28,5)),"") -> 46281 | G28: =iferror(value(mid(D28,find("$",D28)+1,4)),"") -> 107
A29: =IFERROR(__xludf.DUMMYFUNCTION("""COMPUTED_VALUE"""),27.0) -> 27 | B29: =IFERROR(__xludf.DUMMYFUNCTION("""COMPUTED_VALUE"""),"BattleBots") -> BattleBots | C29: =IFERROR(__xludf.DUMMYFUNCTION("""COMPUTED_VALUE"""),"Waiver") -> Waiver | D29: =IFERROR(__xludf.DUMMYFUNCTION("""COMPUTED_VALUE"""),"- Acquired Ayomanor, Elic TEN WR for $1.00") -> - Acquired Ayomanor, Elic TEN WR for $1.00 | E29: =IFERROR(__xludf.DUMMYFUNCTION("""COMPUTED_VALUE"""),"Wed Sep 9 11:00:00 a.m. ET 2026") -> Wed Sep 9 11:00:00 a.m. ET 2026 | F29: =iferror(datevalue(left(E29,10)&right(E29,5)),"") -> 46274 | G29: =iferror(value(mid(D29,find("$",D29)+1,4)),"") -> 1
A30: =IFERROR(__xludf.DUMMYFUNCTION("""COMPUTED_VALUE"""),28.0) -> 28 | B30: =IFERROR(__xludf.DUMMYFUNCTION("""COMPUTED_VALUE"""),"The Meaty Ogres") -> The Meaty Ogres | C30: =IFERROR(__xludf.DUMMYFUNCTION("""COMPUTED_VALUE"""),"Waiver") -> Waiver | D30: =IFERROR(__xludf.DUMMYFUNCTION("""COMPUTED_VALUE"""),"- Acquired Tucker, Sean TBB RB for $34.00") -> - Acquired Tucker, Sean TBB RB for $34.00 | E30: =IFERROR(__xludf.DUMMYFUNCTION("""COMPUTED_VALUE"""),"Wed Sep 9 11:00:00 a.m. ET 2026") -> Wed Sep 9 11:00:00 a.m. ET 2026 | F30: =iferror(datevalue(left(E30,10)&right(E30,5)),"") -> 46274 | G30: =iferror(value(mid(D30,find("$",D30)+1,4)),"") -> 34
A31: =IFERROR(__xludf.DUMMYFUNCTION("""COMPUTED_VALUE"""),29.0) -> 29 | B31: =IFERROR(__xludf.DUMMYFUNCTION("""COMPUTED_VALUE"""),"Shankly's Ghost") -> Shankly's Ghost | C31: =IFERROR(__xludf.DUMMYFUNCTION("""COMPUTED_VALUE"""),"Waiver") -> Waiver | D31: =IFERROR(__xludf.DUMMYFUNCTION("""COMPUTED_VALUE"""),"- Acquired Flournoy, Ryan DAL WR for $51.00") -> - Acquired Flournoy, Ryan DAL WR for $51.00 | E31: =IFERROR(__xludf.DUMMYFUNCTION("""COMPUTED_VALUE"""),"Wed Sep 9 11:00:00 a.m. ET 2026") -> Wed Sep 9 11:00:00 a.m. ET 2026 | F31: =iferror(datevalue(left(E31,10)&right(E31,5)),"") -> 46274 | G31: =iferror(value(mid(D31,find("$",D31)+1,4)),"") -> 51
A32: =IFERROR(__xludf.DUMMYFUNCTION("""COMPUTED_VALUE"""),30.0) -> 30 | B32: =IFERROR(__xludf.DUMMYFUNCTION("""COMPUTED_VALUE"""),"The Meaty Ogres") -> The Meaty Ogres | C32: =IFERROR(__xludf.DUMMYFUNCTION("""COMPUTED_VALUE"""),"Waiver") -> Waiver | D32: =IFERROR(__xludf.DUMMYFUNCTION("""COMPUTED_VALUE"""),"- Acquired Kolar, Charlie LAC TE for $93.00") -> - Acquired Kolar, Charlie LAC TE for $93.00 | E32: =IFERROR(__xludf.DUMMYFUNCTION("""COMPUTED_VALUE"""),"Wed Sep 9 11:00:00 a.m. ET 2026") -> Wed Sep 9 11:00:00 a.m. ET 2026 | F32: =iferror(datevalue(left(E32,10)&right(E32,5)),"") -> 46274 | G32: =iferror(value(mid(D32,find("$",D32)+1,4)),"") -> 93
F33: =iferror(datevalue(left(E33,10)&right(E33,5)),"") | G33: =iferror(value(mid(D33,find("$",D33)+1,4)),"")
F34: =iferror(datevalue(left(E34,10)&right(E34,5)),"") | G34: =iferror(value(mid(D34,find("$",D34)+1,4)),"")
F35: =iferror(datevalue(left(E35,10)&right(E35,5)),"") | G35: =iferror(value(mid(D35,find("$",D35)+1,4)),"")
F36: =iferror(datevalue(left(E36,10)&right(E36,5)),"") | G36: =iferror(value(mid(D36,find("$",D36)+1,4)),"")
F37: =iferror(datevalue(left(E37,10)&right(E37,5)),"") | G37: =iferror(value(mid(D37,find("$",D37)+1,4)),"")
F38: =iferror(datevalue(left(E38,10)&right(E38,5)),"") | G38: =iferror(value(mid(D38,find("$",D38)+1,4)),"")
F39: =iferror(datevalue(left(E39,10)&right(E39,5)),"") | G39: =iferror(value(mid(D39,find("$",D39)+1,4)),"")
F40: =iferror(datevalue(left(E40,10)&right(E40,5)),"") | G40: =iferror(value(mid(D40,find("$",D40)+1,4)),"")
F41: =iferror(datevalue(left(E41,10)&right(E41,5)),"") | G41: =iferror(value(mid(D41,find("$",D41)+1,4)),"")
F42: =iferror(datevalue(left(E42,10)&right(E42,5)),"") | G42: =iferror(value(mid(D42,find("$",D42)+1,4)),"")
F43: =iferror(datevalue(left(E43,10)&right(E43,5)),"") | G43: =iferror(value(mid(D43,find("$",D43)+1,4)),"")
F44: =iferror(datevalue(left(E44,10)&right(E44,5)),"") | G44: =iferror(value(mid(D44,find("$",D44)+1,4)),"")
... F998: =iferror(datevalue(left(E998,10)&right(E998,5)),"") | G998: =iferror(value(mid(D998,find("$",D998)+1,4)),"")

Sheet Notes
A1: Conditional Trades to Resolve
A2: BB has rights to swap 2026 5th round picks with PFB | E2: Done on 8/29

Sheet TokenAwards
A1: Entries for Wheel | B1: Team | C1: Tokens Given (Assuming min 50%) | D1: Entry Verification | E1: Odds for #1 | F1: Actual Draw Slot | G1: Prize Selected | I1: Available Awards
B2: The Wild Cards | C2: =Tracker!D2/2 -> 5.5 | D2: =countif($A:$A,B2) -> 0 | E2: =C2/sum(C:C) -> 0.052380952 | I2: 2026 Draft Pick 1.13
B3: Hamsterdam | C3: =Tracker!E2/2 -> 6.5 | D3: =countif($A:$A,B3) -> 0 | E3: =C3/sum(C:C) -> 0.061904762 | I3: 2027 Draft Pick 2.13
B4: Shankly's Ghost | C4: =Tracker!F2/2 -> 1.5 | D4: =countif($A:$A,B4) -> 0 | E4: =C4/sum(C:C) -> 0.014285714 | I4: 2026 Draft Pick 2.14
B5: 2 Roops, 1 Silva | C5: =Tracker!G2/2 -> 6 | D5: =countif($A:$A,B5) -> 0 | E5: =C5/sum(C:C) -> 0.057142857 | I5: 2027 Draft Pick 3.13
B6: Orcan Terror | C6: =Tracker!H2/2 -> 9 | D6: =countif($A:$A,B6) -> 0 | E6: =C6/sum(C:C) -> 0.085714286 | I6: 2026 Draft Pick 3.14
B7: The Meaty Ogres | C7: =Tracker!I2/2 -> 8 | D7: =countif($A:$A,B7) -> 0 | E7: =C7/sum(C:C) -> 0.076190476 | I7: 2026 Draft Pick 4th Rd - Draft pick forfeiture from Q2 Upper division relegation
B8: Ted Lasso | C8: =Tracker!J2/2 -> 1.5 | D8: =countif($A:$A,B8) -> 0 | E8: =C8/sum(C:C) -> 0.014285714 | I8: 2026 Draft Pick 4th Rd - Draft pick forfeiture from Q2 Middle division relegation
B9: Peaky Fookin Blinders | C9: =Tracker!K2/2 -> 0 | D9: =countif($A:$A,B9) -> 0 | E9: =C9/sum(C:C) -> 0 | I9: 2026 Draft Pick 3rd Rd - Draft pick forfeiture from Q3 Upper division relegation
B10: Springfield Isotopes | C10: =Tracker!L2/2 -> 10.5 | D10: =countif($A:$A,B10) -> 0 | E10: =C10/sum(C:C) -> 0.1 | I10: 2026 Draft Pick 3rd Rd - Draft pick forfeiture from Q3 Middle division relegation
B11: Battlebots | C11: =Tracker!M2/2 -> 43 | D11: =countif($A:$A,B11) -> 0 | E11: =C11/sum(C:C) -> 0.40952381 | I11: 50
B12: The Two Tones | C12: =Tracker!N2/2 -> 6 | D12: =countif($A:$A,B12) -> 0 | E12: =C12/sum(C:C) -> 0.057142857 | I12: Refund of Committed Tokens Back to Team
B13: Norsemen | C13: =Tracker!O2/2 -> 7.5 | D13: =countif($A:$A,B13) -> 0 | E13: =C13/sum(C:C) -> 0.071428571 | I13: 10 Tokens

Sheet RisersFalls
A1: Top 10 Risers
A2: =IFERROR(__xludf.DUMMYFUNCTION("sort(filter({PlayerValues!B2:B3222,PlayerValues!R2:R3222},PlayerValues!R2:R3222>large(PlayerValues!R2:R3222,11)),2,false)"),"#N/A") -> #N/A
A13: Top 10 Fallers
A14: =IFERROR(__xludf.DUMMYFUNCTION("sort(filter({PlayerValues!B2:B3222,PlayerValues!R2:R3222},PlayerValues!R2:R3222<small(PlayerValues!R2:R3222,11)),2,true)"),"Robinson, Bijan") -> Robinson, Bijan | B14: =IFERROR(__xludf.DUMMYFUNCTION("""COMPUTED_VALUE"""),-9998.0) -> -9998
A15: =IFERROR(__xludf.DUMMYFUNCTION("""COMPUTED_VALUE"""),"Gibbs, Jahmyr") -> Gibbs, Jahmyr | B15: =IFERROR(__xludf.DUMMYFUNCTION("""COMPUTED_VALUE"""),-9998.0) -> -9998
A16: =IFERROR(__xludf.DUMMYFUNCTION("""COMPUTED_VALUE"""),"Allen, Josh") -> Allen, Josh | B16: =IFERROR(__xludf.DUMMYFUNCTION("""COMPUTED_VALUE"""),-9993.0) -> -9993
A17: =IFERROR(__xludf.DUMMYFUNCTION("""COMPUTED_VALUE"""),"Chase, Ja'Marr") -> Chase, Ja'Marr | B17: =IFERROR(__xludf.DUMMYFUNCTION("""COMPUTED_VALUE"""),-9977.0) -> -9977
A18: =IFERROR(__xludf.DUMMYFUNCTION("""COMPUTED_VALUE"""),"Smith-Njigba, Jaxon") -> Smith-Njigba, Jaxon | B18: =IFERROR(__xludf.DUMMYFUNCTION("""COMPUTED_VALUE"""),-9195.0) -> -9195
A19: =IFERROR(__xludf.DUMMYFUNCTION("""COMPUTED_VALUE"""),"Bowers, Brock") -> Bowers, Brock | B19: =IFERROR(__xludf.DUMMYFUNCTION("""COMPUTED_VALUE"""),-9139.0) -> -9139
A20: =IFERROR(__xludf.DUMMYFUNCTION("""COMPUTED_VALUE"""),"Maye, Drake") -> Maye, Drake | B20: =IFERROR(__xludf.DUMMYFUNCTION("""COMPUTED_VALUE"""),-8897.0) -> -8897
A21: =IFERROR(__xludf.DUMMYFUNCTION("""COMPUTED_VALUE"""),"Nacua, Puka") -> Nacua, Puka | B21: =IFERROR(__xludf.DUMMYFUNCTION("""COMPUTED_VALUE"""),-8580.0) -> -8580
A22: =IFERROR(__xludf.DUMMYFUNCTION("""COMPUTED_VALUE"""),"St. Brown, Amon-Ra") -> St. Brown, Amon-Ra | B22: =IFERROR(__xludf.DUMMYFUNCTION("""COMPUTED_VALUE"""),-8188.0) -> -8188
A23: =IFERROR(__xludf.DUMMYFUNCTION("""COMPUTED_VALUE"""),"McBride, Trey") -> McBride, Trey | B23: =IFERROR(__xludf.DUMMYFUNCTION("""COMPUTED_VALUE"""),-8090.0) -> -8090

Sheet PlayerValues
A1: =IFERROR(__xludf.DUMMYFUNCTION("importrange(""https://docs.google.com/spreadsheets/d/1Sq384NvzuOA5vLi-wT_7CYoq3hD-kgu--fETQsusM8A"",""Current!A:D"")"),"#REF!") -> #REF! | E1: First Name Last | F1: 46023 | G1: =if(today()>=date(2026,month(F1)+1,1),date(2026,month(F1)+1,1),) -> 46054 | H1: =if(today()>=date(2026,month(G1)+1,1),date(2026,month(G1)+1,1),) -> 46082 | I1: =if(today()>=date(2026,month(H1)+1,1),date(2026,month(H1)+1,1),) -> 46113 | J1: =if(today()>=date(2026,month(I1)+1,1),date(2026,month(I1)+1,1),) -> 46143 | K1: =if(today()>=date(2026,month(J1)+1,1),date(2026,month(J1)+1,1),) -> 46174 | L1: =if(today()>=date(2026,month(K1)+1,1),date(2026,month(K1)+1,1),) -> 46204 | M1: =if(today()>=date(2026,month(L1)+1,1),date(2026,month(L1)+1,1),) -> 46235 | N1: =if(today()>=date(2026,month(M1)+1,1),date(2026,month(M1)+1,1),) -> 46266 | ... Q1: =if(today()>=date(2026,month(P1)+1,1),date(2026,month(P1)+1,1),) | R1: 1 Month Rise/Fall
A2: =IFERROR(__xludf.DUMMYFUNCTION("""COMPUTED_VALUE"""),151.0) -> 151 | B2: =IFERROR(__xludf.DUMMYFUNCTION("""COMPUTED_VALUE"""),"Bills, Buffalo") -> Bills, Buffalo | C2: =IFERROR(__xludf.DUMMYFUNCTION("""COMPUTED_VALUE"""),"TMWR") -> TMWR | D2: =IFERROR(__xludf.DUMMYFUNCTION("""COMPUTED_VALUE"""),"BUF") -> BUF | E2: =mid(B2,find(",",B2)+2,30)&" "&left(B2,find(",",B2)-1) -> Buffalo Bills | F2: =IF(isblank(F$1),,IF(isblank($A2),,IFERROR(vlookup($A2,indirect("'TVC-"&text(month(F$1),"00")&"'!$A:$D"),4,false),1))) -> 1 | G2: =IF(isblank(G$1),,IF(isblank($A2),,IFERROR(vlookup($A2,indirect("'TVC-"&text(month(G$1),"00")&"'!$A:$D"),4,false),1))) -> 1 | H2: =IF(isblank(H$1),,IFERROR(vlookup($A2,indirect("'TVC-"&text(month(H$1),"00")&"'!$A:$D"),4,false),1)) -> 1 | I2: =IF(isblank(I$1),,IFERROR(vlookup($A2,indirect("'TVC-"&text(month(I$1),"00")&"'!$A:$D"),4,false),1)) -> 1 | J2: =IF(isblank(J$1),,IFERROR(vlookup($A2,indirect("'TVC-"&text(month(J$1),"00")&"'!$A:$D"),4,false),1)) -> 1 | K2: =IF(isblank(K$1),,IFERROR(vlookup($A2,indirect("'TVC-"&text(month(K$1),"00")&"'!$A:$D"),4,false),1)) -> 1 | L2: =IF(isblank(L$1),,IFERROR(vlookup($A2,indirect("'TVC-"&text(month(L$1),"00")&"'!$A:$D"),4,false),1)) -> 1 | M2: =IF(isblank(M$1),,IFERROR(vlookup($A2,indirect("'TVC-"&text(month(M$1),"00")&"'!$A:$D"),4,false),1)) -> 1 | N2: =IF(isblank(N$1),,IFERROR(vlookup($A2,indirect("'TVC-"&text(month(N$1),"00")&"'!$A:$D"),4,false),1)) -> 1 | O2: =IF(isblank(O$1),,IFERROR(vlookup($A2,indirect("'TVC-"&text(month(O$1),"00")&"'!$A:$D"),4,false),1)) -> 1 | ... Q2: =IF(isblank(Q$1),,IFERROR(vlookup($A2,indirect("'TVC-"&text(month(Q$1),"00")&"'!$A:$D"),4,false),1)) | R2: =index(A2:Q2,,month(today())+5)-index(A2:Q2,,month(today())+4) -> 0
A3: =IFERROR(__xludf.DUMMYFUNCTION("""COMPUTED_VALUE"""),152.0) -> 152 | B3: =IFERROR(__xludf.DUMMYFUNCTION("""COMPUTED_VALUE"""),"Colts, Indianapolis") -> Colts, Indianapolis | C3: =IFERROR(__xludf.DUMMYFUNCTION("""COMPUTED_VALUE"""),"TMWR") -> TMWR | D3: =IFERROR(__xludf.DUMMYFUNCTION("""COMPUTED_VALUE"""),"IND") -> IND | E3: =mid(B3,find(",",B3)+2,30)&" "&left(B3,find(",",B3)-1) -> Indianapolis Colts | F3: =IF(isblank(F$1),,IF(isblank($A3),,IFERROR(vlookup($A3,indirect("'TVC-"&text(month(F$1),"00")&"'!$A:$D"),4,false),1))) -> 1 | G3: =IF(isblank(G$1),,IF(isblank($A3),,IFERROR(vlookup($A3,indirect("'TVC-"&text(month(G$1),"00")&"'!$A:$D"),4,false),1))) -> 1 | H3: =IF(isblank(H$1),,IFERROR(vlookup($A3,indirect("'TVC-"&text(month(H$1),"00")&"'!$A:$D"),4,false),1)) -> 1 | I3: =IF(isblank(I$1),,IFERROR(vlookup($A3,indirect("'TVC-"&text(month(I$1),"00")&"'!$A:$D"),4,false),1)) -> 1 | J3: =IF(isblank(J$1),,IFERROR(vlookup($A3,indirect("'TVC-"&text(month(J$1),"00")&"'!$A:$D"),4,false),1)) -> 1 | K3: =IF(isblank(K$1),,IFERROR(vlookup($A3,indirect("'TVC-"&text(month(K$1),"00")&"'!$A:$D"),4,false),1)) -> 1 | L3: =IF(isblank(L$1),,IFERROR(vlookup($A3,indirect("'TVC-"&text(month(L$1),"00")&"'!$A:$D"),4,false),1)) -> 1 | M3: =IF(isblank(M$1),,IFERROR(vlookup($A3,indirect("'TVC-"&text(month(M$1),"00")&"'!$A:$D"),4,false),1)) -> 1 | N3: =IF(isblank(N$1),,IFERROR(vlookup($A3,indirect("'TVC-"&text(month(N$1),"00")&"'!$A:$D"),4,false),1)) -> 1 | O3: =IF(isblank(O$1),,IFERROR(vlookup($A3,indirect("'TVC-"&text(month(O$1),"00")&"'!$A:$D"),4,false),1)) -> 1 | ... Q3: =IF(isblank(Q$1),,IFERROR(vlookup($A3,indirect("'TVC-"&text(month(Q$1),"00")&"'!$A:$D"),4,false),1)) | R3: =index(A3:Q3,,month(today())+5)-index(A3:Q3,,month(today())+4) -> 0
A4: =IFERROR(__xludf.DUMMYFUNCTION("""COMPUTED_VALUE"""),153.0) -> 153 | B4: =IFERROR(__xludf.DUMMYFUNCTION("""COMPUTED_VALUE"""),"Dolphins, Miami") -> Dolphins, Miami | C4: =IFERROR(__xludf.DUMMYFUNCTION("""COMPUTED_VALUE"""),"TMWR") -> TMWR | D4: =IFERROR(__xludf.DUMMYFUNCTION("""COMPUTED_VALUE"""),"MIA") -> MIA | E4: =mid(B4,find(",",B4)+2,30)&" "&left(B4,find(",",B4)-1) -> Miami Dolphins | F4: =IF(isblank(F$1),,IF(isblank($A4),,IFERROR(vlookup($A4,indirect("'TVC-"&text(month(F$1),"00")&"'!$A:$D"),4,false),1))) -> 1 | G4: =IF(isblank(G$1),,IF(isblank($A4),,IFERROR(vlookup($A4,indirect("'TVC-"&text(month(G$1),"00")&"'!$A:$D"),4,false),1))) -> 1 | H4: =IF(isblank(H$1),,IFERROR(vlookup($A4,indirect("'TVC-"&text(month(H$1),"00")&"'!$A:$D"),4,false),1)) -> 1 | I4: =IF(isblank(I$1),,IFERROR(vlookup($A4,indirect("'TVC-"&text(month(I$1),"00")&"'!$A:$D"),4,false),1)) -> 1 | J4: =IF(isblank(J$1),,IFERROR(vlookup($A4,indirect("'TVC-"&text(month(J$1),"00")&"'!$A:$D"),4,false),1)) -> 1 | K4: =IF(isblank(K$1),,IFERROR(vlookup($A4,indirect("'TVC-"&text(month(K$1),"00")&"'!$A:$D"),4,false),1)) -> 1 | L4: =IF(isblank(L$1),,IFERROR(vlookup($A4,indirect("'TVC-"&text(month(L$1),"00")&"'!$A:$D"),4,false),1)) -> 1 | M4: =IF(isblank(M$1),,IFERROR(vlookup($A4,indirect("'TVC-"&text(month(M$1),"00")&"'!$A:$D"),4,false),1)) -> 1 | N4: =IF(isblank(N$1),,IFERROR(vlookup($A4,indirect("'TVC-"&text(month(N$1),"00")&"'!$A:$D"),4,false),1)) -> 1 | O4: =IF(isblank(O$1),,IFERROR(vlookup($A4,indirect("'TVC-"&text(month(O$1),"00")&"'!$A:$D"),4,false),1)) -> 1 | ... Q4: =IF(isblank(Q$1),,IFERROR(vlookup($A4,indirect("'TVC-"&text(month(Q$1),"00")&"'!$A:$D"),4,false),1)) | R4: =index(A4:Q4,,month(today())+5)-index(A4:Q4,,month(today())+4) -> 0
A5: =IFERROR(__xludf.DUMMYFUNCTION("""COMPUTED_VALUE"""),154.0) -> 154 | B5: =IFERROR(__xludf.DUMMYFUNCTION("""COMPUTED_VALUE"""),"Patriots, New England") -> Patriots, New England | C5: =IFERROR(__xludf.DUMMYFUNCTION("""COMPUTED_VALUE"""),"TMWR") -> TMWR | D5: =IFERROR(__xludf.DUMMYFUNCTION("""COMPUTED_VALUE"""),"NEP") -> NEP | E5: =mid(B5,find(",",B5)+2,30)&" "&left(B5,find(",",B5)-1) -> New England Patriots | F5: =IF(isblank(F$1),,IF(isblank($A5),,IFERROR(vlookup($A5,indirect("'TVC-"&text(month(F$1),"00")&"'!$A:$D"),4,false),1))) -> 1 | G5: =IF(isblank(G$1),,IF(isblank($A5),,IFERROR(vlookup($A5,indirect("'TVC-"&text(month(G$1),"00")&"'!$A:$D"),4,false),1))) -> 1 | H5: =IF(isblank(H$1),,IFERROR(vlookup($A5,indirect("'TVC-"&text(month(H$1),"00")&"'!$A:$D"),4,false),1)) -> 1 | I5: =IF(isblank(I$1),,IFERROR(vlookup($A5,indirect("'TVC-"&text(month(I$1),"00")&"'!$A:$D"),4,false),1)) -> 1 | J5: =IF(isblank(J$1),,IFERROR(vlookup($A5,indirect("'TVC-"&text(month(J$1),"00")&"'!$A:$D"),4,false),1)) -> 1 | K5: =IF(isblank(K$1),,IFERROR(vlookup($A5,indirect("'TVC-"&text(month(K$1),"00")&"'!$A:$D"),4,false),1)) -> 1 | L5: =IF(isblank(L$1),,IFERROR(vlookup($A5,indirect("'TVC-"&text(month(L$1),"00")&"'!$A:$D"),4,false),1)) -> 1 | M5: =IF(isblank(M$1),,IFERROR(vlookup($A5,indirect("'TVC-"&text(month(M$1),"00")&"'!$A:$D"),4,false),1)) -> 1 | N5: =IF(isblank(N$1),,IFERROR(vlookup($A5,indirect("'TVC-"&text(month(N$1),"00")&"'!$A:$D"),4,false),1)) -> 1 | O5: =IF(isblank(O$1),,IFERROR(vlookup($A5,indirect("'TVC-"&text(month(O$1),"00")&"'!$A:$D"),4,false),1)) -> 1 | ... Q5: =IF(isblank(Q$1),,IFERROR(vlookup($A5,indirect("'TVC-"&text(month(Q$1),"00")&"'!$A:$D"),4,false),1)) | R5: =index(A5:Q5,,month(today())+5)-index(A5:Q5,,month(today())+4) -> 0
A6: =IFERROR(__xludf.DUMMYFUNCTION("""COMPUTED_VALUE"""),155.0) -> 155 | B6: =IFERROR(__xludf.DUMMYFUNCTION("""COMPUTED_VALUE"""),"Jets, New York") -> Jets, New York | C6: =IFERROR(__xludf.DUMMYFUNCTION("""COMPUTED_VALUE"""),"TMWR") -> TMWR | D6: =IFERROR(__xludf.DUMMYFUNCTION("""COMPUTED_VALUE"""),"NYJ") -> NYJ | E6: =mid(B6,find(",",B6)+2,30)&" "&left(B6,find(",",B6)-1) -> New York Jets | F6: =IF(isblank(F$1),,IF(isblank($A6),,IFERROR(vlookup($A6,indirect("'TVC-"&text(month(F$1),"00")&"'!$A:$D"),4,false),1))) -> 1 | G6: =IF(isblank(G$1),,IF(isblank($A6),,IFERROR(vlookup($A6,indirect("'TVC-"&text(month(G$1),"00")&"'!$A:$D"),4,false),1))) -> 1 | H6: =IF(isblank(H$1),,IFERROR(vlookup($A6,indirect("'TVC-"&text(month(H$1),"00")&"'!$A:$D"),4,false),1)) -> 1 | I6: =IF(isblank(I$1),,IFERROR(vlookup($A6,indirect("'TVC-"&text(month(I$1),"00")&"'!$A:$D"),4,false),1)) -> 1 | J6: =IF(isblank(J$1),,IFERROR(vlookup($A6,indirect("'TVC-"&text(month(J$1),"00")&"'!$A:$D"),4,false),1)) -> 1 | K6: =IF(isblank(K$1),,IFERROR(vlookup($A6,indirect("'TVC-"&text(month(K$1),"00")&"'!$A:$D"),4,false),1)) -> 1 | L6: =IF(isblank(L$1),,IFERROR(vlookup($A6,indirect("'TVC-"&text(month(L$1),"00")&"'!$A:$D"),4,false),1)) -> 1 | M6: =IF(isblank(M$1),,IFERROR(vlookup($A6,indirect("'TVC-"&text(month(M$1),"00")&"'!$A:$D"),4,false),1)) -> 1 | N6: =IF(isblank(N$1),,IFERROR(vlookup($A6,indirect("'TVC-"&text(month(N$1),"00")&"'!$A:$D"),4,false),1)) -> 1 | O6: =IF(isblank(O$1),,IFERROR(vlookup($A6,indirect("'TVC-"&text(month(O$1),"00")&"'!$A:$D"),4,false),1)) -> 1 | ... Q6: =IF(isblank(Q$1),,IFERROR(vlookup($A6,indirect("'TVC-"&text(month(Q$1),"00")&"'!$A:$D"),4,false),1)) | R6: =index(A6:Q6,,month(today())+5)-index(A6:Q6,,month(today())+4) -> 0
A7: =IFERROR(__xludf.DUMMYFUNCTION("""COMPUTED_VALUE"""),156.0) -> 156 | B7: =IFERROR(__xludf.DUMMYFUNCTION("""COMPUTED_VALUE"""),"Bengals, Cincinnati") -> Bengals, Cincinnati | C7: =IFERROR(__xludf.DUMMYFUNCTION("""COMPUTED_VALUE"""),"TMWR") -> TMWR | D7: =IFERROR(__xludf.DUMMYFUNCTION("""COMPUTED_VALUE"""),"CIN") -> CIN | E7: =mid(B7,find(",",B7)+2,30)&" "&left(B7,find(",",B7)-1) -> Cincinnati Bengals | F7: =IF(isblank(F$1),,IF(isblank($A7),,IFERROR(vlookup($A7,indirect("'TVC-"&text(month(F$1),"00")&"'!$A:$D"),4,false),1))) -> 1 | G7: =IF(isblank(G$1),,IF(isblank($A7),,IFERROR(vlookup($A7,indirect("'TVC-"&text(month(G$1),"00")&"'!$A:$D"),4,false),1))) -> 1 | H7: =IF(isblank(H$1),,IFERROR(vlookup($A7,indirect("'TVC-"&text(month(H$1),"00")&"'!$A:$D"),4,false),1)) -> 1 | I7: =IF(isblank(I$1),,IFERROR(vlookup($A7,indirect("'TVC-"&text(month(I$1),"00")&"'!$A:$D"),4,false),1)) -> 1 | J7: =IF(isblank(J$1),,IFERROR(vlookup($A7,indirect("'TVC-"&text(month(J$1),"00")&"'!$A:$D"),4,false),1)) -> 1 | K7: =IF(isblank(K$1),,IFERROR(vlookup($A7,indirect("'TVC-"&text(month(K$1),"00")&"'!$A:$D"),4,false),1)) -> 1 | L7: =IF(isblank(L$1),,IFERROR(vlookup($A7,indirect("'TVC-"&text(month(L$1),"00")&"'!$A:$D"),4,false),1)) -> 1 | M7: =IF(isblank(M$1),,IFERROR(vlookup($A7,indirect("'TVC-"&text(month(M$1),"00")&"'!$A:$D"),4,false),1)) -> 1 | N7: =IF(isblank(N$1),,IFERROR(vlookup($A7,indirect("'TVC-"&text(month(N$1),"00")&"'!$A:$D"),4,false),1)) -> 1 | O7: =IF(isblank(O$1),,IFERROR(vlookup($A7,indirect("'TVC-"&text(month(O$1),"00")&"'!$A:$D"),4,false),1)) -> 1 | ... Q7: =IF(isblank(Q$1),,IFERROR(vlookup($A7,indirect("'TVC-"&text(month(Q$1),"00")&"'!$A:$D"),4,false),1)) | R7: =index(A7:Q7,,month(today())+5)-index(A7:Q7,,month(today())+4) -> 0
A8: =IFERROR(__xludf.DUMMYFUNCTION("""COMPUTED_VALUE"""),157.0) -> 157 | B8: =IFERROR(__xludf.DUMMYFUNCTION("""COMPUTED_VALUE"""),"Browns, Cleveland") -> Browns, Cleveland | C8: =IFERROR(__xludf.DUMMYFUNCTION("""COMPUTED_VALUE"""),"TMWR") -> TMWR | D8: =IFERROR(__xludf.DUMMYFUNCTION("""COMPUTED_VALUE"""),"CLE") -> CLE | E8: =mid(B8,find(",",B8)+2,30)&" "&left(B8,find(",",B8)-1) -> Cleveland Browns | F8: =IF(isblank(F$1),,IF(isblank($A8),,IFERROR(vlookup($A8,indirect("'TVC-"&text(month(F$1),"00")&"'!$A:$D"),4,false),1))) -> 1 | G8: =IF(isblank(G$1),,IF(isblank($A8),,IFERROR(vlookup($A8,indirect("'TVC-"&text(month(G$1),"00")&"'!$A:$D"),4,false),1))) -> 1 | H8: =IF(isblank(H$1),,IFERROR(vlookup($A8,indirect("'TVC-"&text(month(H$1),"00")&"'!$A:$D"),4,false),1)) -> 1 | I8: =IF(isblank(I$1),,IFERROR(vlookup($A8,indirect("'TVC-"&text(month(I$1),"00")&"'!$A:$D"),4,false),1)) -> 1 | J8: =IF(isblank(J$1),,IFERROR(vlookup($A8,indirect("'TVC-"&text(month(J$1),"00")&"'!$A:$D"),4,false),1)) -> 1 | K8: =IF(isblank(K$1),,IFERROR(vlookup($A8,indirect("'TVC-"&text(month(K$1),"00")&"'!$A:$D"),4,false),1)) -> 1 | L8: =IF(isblank(L$1),,IFERROR(vlookup($A8,indirect("'TVC-"&text(month(L$1),"00")&"'!$A:$D"),4,false),1)) -> 1 | M8: =IF(isblank(M$1),,IFERROR(vlookup($A8,indirect("'TVC-"&text(month(M$1),"00")&"'!$A:$D"),4,false),1)) -> 1 | N8: =IF(isblank(N$1),,IFERROR(vlookup($A8,indirect("'TVC-"&text(month(N$1),"00")&"'!$A:$D"),4,false),1)) -> 1 | O8: =IF(isblank(O$1),,IFERROR(vlookup($A8,indirect("'TVC-"&text(month(O$1),"00")&"'!$A:$D"),4,false),1)) -> 1 | ... Q8: =IF(isblank(Q$1),,IFERROR(vlookup($A8,indirect("'TVC-"&text(month(Q$1),"00")&"'!$A:$D"),4,false),1)) | R8: =index(A8:Q8,,month(today())+5)-index(A8:Q8,,month(today())+4) -> 0
A9: =IFERROR(__xludf.DUMMYFUNCTION("""COMPUTED_VALUE"""),158.0) -> 158 | B9: =IFERROR(__xludf.DUMMYFUNCTION("""COMPUTED_VALUE"""),"Titans, Tennessee") -> Titans, Tennessee | C9: =IFERROR(__xludf.DUMMYFUNCTION("""COMPUTED_VALUE"""),"TMWR") -> TMWR | D9: =IFERROR(__xludf.DUMMYFUNCTION("""COMPUTED_VALUE"""),"TEN") -> TEN | E9: =mid(B9,find(",",B9)+2,30)&" "&left(B9,find(",",B9)-1) -> Tennessee Titans | F9: =IF(isblank(F$1),,IF(isblank($A9),,IFERROR(vlookup($A9,indirect("'TVC-"&text(month(F$1),"00")&"'!$A:$D"),4,false),1))) -> 1 | G9: =IF(isblank(G$1),,IF(isblank($A9),,IFERROR(vlookup($A9,indirect("'TVC-"&text(month(G$1),"00")&"'!$A:$D"),4,false),1))) -> 1 | H9: =IF(isblank(H$1),,IFERROR(vlookup($A9,indirect("'TVC-"&text(month(H$1),"00")&"'!$A:$D"),4,false),1)) -> 1 | I9: =IF(isblank(I$1),,IFERROR(vlookup($A9,indirect("'TVC-"&text(month(I$1),"00")&"'!$A:$D"),4,false),1)) -> 1 | J9: =IF(isblank(J$1),,IFERROR(vlookup($A9,indirect("'TVC-"&text(month(J$1),"00")&"'!$A:$D"),4,false),1)) -> 1 | K9: =IF(isblank(K$1),,IFERROR(vlookup($A9,indirect("'TVC-"&text(month(K$1),"00")&"'!$A:$D"),4,false),1)) -> 1 | L9: =IF(isblank(L$1),,IFERROR(vlookup($A9,indirect("'TVC-"&text(month(L$1),"00")&"'!$A:$D"),4,false),1)) -> 1 | M9: =IF(isblank(M$1),,IFERROR(vlookup($A9,indirect("'TVC-"&text(month(M$1),"00")&"'!$A:$D"),4,false),1)) -> 1 | N9: =IF(isblank(N$1),,IFERROR(vlookup($A9,indirect("'TVC-"&text(month(N$1),"00")&"'!$A:$D"),4,false),1)) -> 1 | O9: =IF(isblank(O$1),,IFERROR(vlookup($A9,indirect("'TVC-"&text(month(O$1),"00")&"'!$A:$D"),4,false),1)) -> 1 | ... Q9: =IF(isblank(Q$1),,IFERROR(vlookup($A9,indirect("'TVC-"&text(month(Q$1),"00")&"'!$A:$D"),4,false),1)) | R9: =index(A9:Q9,,month(today())+5)-index(A9:Q9,,month(today())+4) -> 0
A10: =IFERROR(__xludf.DUMMYFUNCTION("""COMPUTED_VALUE"""),159.0) -> 159 | B10: =IFERROR(__xludf.DUMMYFUNCTION("""COMPUTED_VALUE"""),"Jaguars, Jacksonville") -> Jaguars, Jacksonville | C10: =IFERROR(__xludf.DUMMYFUNCTION("""COMPUTED_VALUE"""),"TMWR") -> TMWR | D10: =IFERROR(__xludf.DUMMYFUNCTION("""COMPUTED_VALUE"""),"JAC") -> JAC | E10: =mid(B10,find(",",B10)+2,30)&" "&left(B10,find(",",B10)-1) -> Jacksonville Jaguars | F10: =IF(isblank(F$1),,IF(isblank($A10),,IFERROR(vlookup($A10,indirect("'TVC-"&text(month(F$1),"00")&"'!$A:$D"),4,false),1))) -> 1 | G10: =IF(isblank(G$1),,IF(isblank($A10),,IFERROR(vlookup($A10,indirect("'TVC-"&text(month(G$1),"00")&"'!$A:$D"),4,false),1))) -> 1 | H10: =IF(isblank(H$1),,IFERROR(vlookup($A10,indirect("'TVC-"&text(month(H$1),"00")&"'!$A:$D"),4,false),1)) -> 1 | I10: =IF(isblank(I$1),,IFERROR(vlookup($A10,indirect("'TVC-"&text(month(I$1),"00")&"'!$A:$D"),4,false),1)) -> 1 | J10: =IF(isblank(J$1),,IFERROR(vlookup($A10,indirect("'TVC-"&text(month(J$1),"00")&"'!$A:$D"),4,false),1)) -> 1 | K10: =IF(isblank(K$1),,IFERROR(vlookup($A10,indirect("'TVC-"&text(month(K$1),"00")&"'!$A:$D"),4,false),1)) -> 1 | L10: =IF(isblank(L$1),,IFERROR(vlookup($A10,indirect("'TVC-"&text(month(L$1),"00")&"'!$A:$D"),4,false),1)) -> 1 | M10: =IF(isblank(M$1),,IFERROR(vlookup($A10,indirect("'TVC-"&text(month(M$1),"00")&"'!$A:$D"),4,false),1)) -> 1 | N10: =IF(isblank(N$1),,IFERROR(vlookup($A10,indirect("'TVC-"&text(month(N$1),"00")&"'!$A:$D"),4,false),1)) -> 1 | O10: =IF(isblank(O$1),,IFERROR(vlookup($A10,indirect("'TVC-"&text(month(O$1),"00")&"'!$A:$D"),4,false),1)) -> 1 | ... Q10: =IF(isblank(Q$1),,IFERROR(vlookup($A10,indirect("'TVC-"&text(month(Q$1),"00")&"'!$A:$D"),4,false),1)) | R10: =index(A10:Q10,,month(today())+5)-index(A10:Q10,,month(today())+4) -> 0
A11: =IFERROR(__xludf.DUMMYFUNCTION("""COMPUTED_VALUE"""),160.0) -> 160 | B11: =IFERROR(__xludf.DUMMYFUNCTION("""COMPUTED_VALUE"""),"Steelers, Pittsburgh") -> Steelers, Pittsburgh | C11: =IFERROR(__xludf.DUMMYFUNCTION("""COMPUTED_VALUE"""),"TMWR") -> TMWR | D11: =IFERROR(__xludf.DUMMYFUNCTION("""COMPUTED_VALUE"""),"PIT") -> PIT | E11: =mid(B11,find(",",B11)+2,30)&" "&left(B11,find(",",B11)-1) -> Pittsburgh Steelers | F11: =IF(isblank(F$1),,IF(isblank($A11),,IFERROR(vlookup($A11,indirect("'TVC-"&text(month(F$1),"00")&"'!$A:$D"),4,false),1))) -> 1 | G11: =IF(isblank(G$1),,IF(isblank($A11),,IFERROR(vlookup($A11,indirect("'TVC-"&text(month(G$1),"00")&"'!$A:$D"),4,false),1))) -> 1 | H11: =IF(isblank(H$1),,IFERROR(vlookup($A11,indirect("'TVC-"&text(month(H$1),"00")&"'!$A:$D"),4,false),1)) -> 1 | I11: =IF(isblank(I$1),,IFERROR(vlookup($A11,indirect("'TVC-"&text(month(I$1),"00")&"'!$A:$D"),4,false),1)) -> 1 | J11: =IF(isblank(J$1),,IFERROR(vlookup($A11,indirect("'TVC-"&text(month(J$1),"00")&"'!$A:$D"),4,false),1)) -> 1 | K11: =IF(isblank(K$1),,IFERROR(vlookup($A11,indirect("'TVC-"&text(month(K$1),"00")&"'!$A:$D"),4,false),1)) -> 1 | L11: =IF(isblank(L$1),,IFERROR(vlookup($A11,indirect("'TVC-"&text(month(L$1),"00")&"'!$A:$D"),4,false),1)) -> 1 | M11: =IF(isblank(M$1),,IFERROR(vlookup($A11,indirect("'TVC-"&text(month(M$1),"00")&"'!$A:$D"),4,false),1)) -> 1 | N11: =IF(isblank(N$1),,IFERROR(vlookup($A11,indirect("'TVC-"&text(month(N$1),"00")&"'!$A:$D"),4,false),1)) -> 1 | O11: =IF(isblank(O$1),,IFERROR(vlookup($A11,indirect("'TVC-"&text(month(O$1),"00")&"'!$A:$D"),4,false),1)) -> 1 | ... Q11: =IF(isblank(Q$1),,IFERROR(vlookup($A11,indirect("'TVC-"&text(month(Q$1),"00")&"'!$A:$D"),4,false),1)) | R11: =index(A11:Q11,,month(today())+5)-index(A11:Q11,,month(today())+4) -> 0
A12: =IFERROR(__xludf.DUMMYFUNCTION("""COMPUTED_VALUE"""),161.0) -> 161 | B12: =IFERROR(__xludf.DUMMYFUNCTION("""COMPUTED_VALUE"""),"Broncos, Denver") -> Broncos, Denver | C12: =IFERROR(__xludf.DUMMYFUNCTION("""COMPUTED_VALUE"""),"TMWR") -> TMWR | D12: =IFERROR(__xludf.DUMMYFUNCTION("""COMPUTED_VALUE"""),"DEN") -> DEN | E12: =mid(B12,find(",",B12)+2,30)&" "&left(B12,find(",",B12)-1) -> Denver Broncos | F12: =IF(isblank(F$1),,IF(isblank($A12),,IFERROR(vlookup($A12,indirect("'TVC-"&text(month(F$1),"00")&"'!$A:$D"),4,false),1))) -> 1 | G12: =IF(isblank(G$1),,IF(isblank($A12),,IFERROR(vlookup($A12,indirect("'TVC-"&text(month(G$1),"00")&"'!$A:$D"),4,false),1))) -> 1 | H12: =IF(isblank(H$1),,IFERROR(vlookup($A12,indirect("'TVC-"&text(month(H$1),"00")&"'!$A:$D"),4,false),1)) -> 1 | I12: =IF(isblank(I$1),,IFERROR(vlookup($A12,indirect("'TVC-"&text(month(I$1),"00")&"'!$A:$D"),4,false),1)) -> 1 | J12: =IF(isblank(J$1),,IFERROR(vlookup($A12,indirect("'TVC-"&text(month(J$1),"00")&"'!$A:$D"),4,false),1)) -> 1 | K12: =IF(isblank(K$1),,IFERROR(vlookup($A12,indirect("'TVC-"&text(month(K$1),"00")&"'!$A:$D"),4,false),1)) -> 1 | L12: =IF(isblank(L$1),,IFERROR(vlookup($A12,indirect("'TVC-"&text(month(L$1),"00")&"'!$A:$D"),4,false),1)) -> 1 | M12: =IF(isblank(M$1),,IFERROR(vlookup($A12,indirect("'TVC-"&text(month(M$1),"00")&"'!$A:$D"),4,false),1)) -> 1 | N12: =IF(isblank(N$1),,IFERROR(vlookup($A12,indirect("'TVC-"&text(month(N$1),"00")&"'!$A:$D"),4,false),1)) -> 1 | O12: =IF(isblank(O$1),,IFERROR(vlookup($A12,indirect("'TVC-"&text(month(O$1),"00")&"'!$A:$D"),4,false),1)) -> 1 | ... Q12: =IF(isblank(Q$1),,IFERROR(vlookup($A12,indirect("'TVC-"&text(month(Q$1),"00")&"'!$A:$D"),4,false),1)) | R12: =index(A12:Q12,,month(today())+5)-index(A12:Q12,,month(today())+4) -> 0
A13: =IFERROR(__xludf.DUMMYFUNCTION("""COMPUTED_VALUE"""),162.0) -> 162 | B13: =IFERROR(__xludf.DUMMYFUNCTION("""COMPUTED_VALUE"""),"Chiefs, Kansas City") -> Chiefs, Kansas City | C13: =IFERROR(__xludf.DUMMYFUNCTION("""COMPUTED_VALUE"""),"TMWR") -> TMWR | D13: =IFERROR(__xludf.DUMMYFUNCTION("""COMPUTED_VALUE"""),"KCC") -> KCC | E13: =mid(B13,find(",",B13)+2,30)&" "&left(B13,find(",",B13)-1) -> Kansas City Chiefs | F13: =IF(isblank(F$1),,IF(isblank($A13),,IFERROR(vlookup($A13,indirect("'TVC-"&text(month(F$1),"00")&"'!$A:$D"),4,false),1))) -> 1 | G13: =IF(isblank(G$1),,IF(isblank($A13),,IFERROR(vlookup($A13,indirect("'TVC-"&text(month(G$1),"00")&"'!$A:$D"),4,false),1))) -> 1 | H13: =IF(isblank(H$1),,IFERROR(vlookup($A13,indirect("'TVC-"&text(month(H$1),"00")&"'!$A:$D"),4,false),1)) -> 1 | I13: =IF(isblank(I$1),,IFERROR(vlookup($A13,indirect("'TVC-"&text(month(I$1),"00")&"'!$A:$D"),4,false),1)) -> 1 | J13: =IF(isblank(J$1),,IFERROR(vlookup($A13,indirect("'TVC-"&text(month(J$1),"00")&"'!$A:$D"),4,false),1)) -> 1 | K13: =IF(isblank(K$1),,IFERROR(vlookup($A13,indirect("'TVC-"&text(month(K$1),"00")&"'!$A:$D"),4,false),1)) -> 1 | L13: =IF(isblank(L$1),,IFERROR(vlookup($A13,indirect("'TVC-"&text(month(L$1),"00")&"'!$A:$D"),4,false),1)) -> 1 | M13: =IF(isblank(M$1),,IFERROR(vlookup($A13,indirect("'TVC-"&text(month(M$1),"00")&"'!$A:$D"),4,false),1)) -> 1 | N13: =IF(isblank(N$1),,IFERROR(vlookup($A13,indirect("'TVC-"&text(month(N$1),"00")&"'!$A:$D"),4,false),1)) -> 1 | O13: =IF(isblank(O$1),,IFERROR(vlookup($A13,indirect("'TVC-"&text(month(O$1),"00")&"'!$A:$D"),4,false),1)) -> 1 | ... Q13: =IF(isblank(Q$1),,IFERROR(vlookup($A13,indirect("'TVC-"&text(month(Q$1),"00")&"'!$A:$D"),4,false),1)) | R13: =index(A13:Q13,,month(today())+5)-index(A13:Q13,,month(today())+4) -> 0
A14: =IFERROR(__xludf.DUMMYFUNCTION("""COMPUTED_VALUE"""),163.0) -> 163 | B14: =IFERROR(__xludf.DUMMYFUNCTION("""COMPUTED_VALUE"""),"Raiders, Las Vegas") -> Raiders, Las Vegas | C14: =IFERROR(__xludf.DUMMYFUNCTION("""COMPUTED_VALUE"""),"TMWR") -> TMWR | D14: =IFERROR(__xludf.DUMMYFUNCTION("""COMPUTED_VALUE"""),"LVR") -> LVR | E14: =mid(B14,find(",",B14)+2,30)&" "&left(B14,find(",",B14)-1) -> Las Vegas Raiders | F14: =IF(isblank(F$1),,IF(isblank($A14),,IFERROR(vlookup($A14,indirect("'TVC-"&text(month(F$1),"00")&"'!$A:$D"),4,false),1))) -> 1 | G14: =IF(isblank(G$1),,IF(isblank($A14),,IFERROR(vlookup($A14,indirect("'TVC-"&text(month(G$1),"00")&"'!$A:$D"),4,false),1))) -> 1 | H14: =IF(isblank(H$1),,IFERROR(vlookup($A14,indirect("'TVC-"&text(month(H$1),"00")&"'!$A:$D"),4,false),1)) -> 1 | I14: =IF(isblank(I$1),,IFERROR(vlookup($A14,indirect("'TVC-"&text(month(I$1),"00")&"'!$A:$D"),4,false),1)) -> 1 | J14: =IF(isblank(J$1),,IFERROR(vlookup($A14,indirect("'TVC-"&text(month(J$1),"00")&"'!$A:$D"),4,false),1)) -> 1 | K14: =IF(isblank(K$1),,IFERROR(vlookup($A14,indirect("'TVC-"&text(month(K$1),"00")&"'!$A:$D"),4,false),1)) -> 1 | L14: =IF(isblank(L$1),,IFERROR(vlookup($A14,indirect("'TVC-"&text(month(L$1),"00")&"'!$A:$D"),4,false),1)) -> 1 | M14: =IF(isblank(M$1),,IFERROR(vlookup($A14,indirect("'TVC-"&text(month(M$1),"00")&"'!$A:$D"),4,false),1)) -> 1 | N14: =IF(isblank(N$1),,IFERROR(vlookup($A14,indirect("'TVC-"&text(month(N$1),"00")&"'!$A:$D"),4,false),1)) -> 1 | O14: =IF(isblank(O$1),,IFERROR(vlookup($A14,indirect("'TVC-"&text(month(O$1),"00")&"'!$A:$D"),4,false),1)) -> 1 | ... Q14: =IF(isblank(Q$1),,IFERROR(vlookup($A14,indirect("'TVC-"&text(month(Q$1),"00")&"'!$A:$D"),4,false),1)) | R14: =index(A14:Q14,,month(today())+5)-index(A14:Q14,,month(today())+4) -> 0
A15: =IFERROR(__xludf.DUMMYFUNCTION("""COMPUTED_VALUE"""),164.0) -> 164 | B15: =IFERROR(__xludf.DUMMYFUNCTION("""COMPUTED_VALUE"""),"Chargers, Los Angeles") -> Chargers, Los Angeles | C15: =IFERROR(__xludf.DUMMYFUNCTION("""COMPUTED_VALUE"""),"TMWR") -> TMWR | D15: =IFERROR(__xludf.DUMMYFUNCTION("""COMPUTED_VALUE"""),"LAC") -> LAC | E15: =mid(B15,find(",",B15)+2,30)&" "&left(B15,find(",",B15)-1) -> Los Angeles Chargers | F15: =IF(isblank(F$1),,IF(isblank($A15),,IFERROR(vlookup($A15,indirect("'TVC-"&text(month(F$1),"00")&"'!$A:$D"),4,false),1))) -> 1 | G15: =IF(isblank(G$1),,IF(isblank($A15),,IFERROR(vlookup($A15,indirect("'TVC-"&text(month(G$1),"00")&"'!$A:$D"),4,false),1))) -> 1 | H15: =IF(isblank(H$1),,IFERROR(vlookup($A15,indirect("'TVC-"&text(month(H$1),"00")&"'!$A:$D"),4,false),1)) -> 1 | I15: =IF(isblank(I$1),,IFERROR(vlookup($A15,indirect("'TVC-"&text(month(I$1),"00")&"'!$A:$D"),4,false),1)) -> 1 | J15: =IF(isblank(J$1),,IFERROR(vlookup($A15,indirect("'TVC-"&text(month(J$1),"00")&"'!$A:$D"),4,false),1)) -> 1 | K15: =IF(isblank(K$1),,IFERROR(vlookup($A15,indirect("'TVC-"&text(month(K$1),"00")&"'!$A:$D"),4,false),1)) -> 1 | L15: =IF(isblank(L$1),,IFERROR(vlookup($A15,indirect("'TVC-"&text(month(L$1),"00")&"'!$A:$D"),4,false),1)) -> 1 | M15: =IF(isblank(M$1),,IFERROR(vlookup($A15,indirect("'TVC-"&text(month(M$1),"00")&"'!$A:$D"),4,false),1)) -> 1 | N15: =IF(isblank(N$1),,IFERROR(vlookup($A15,indirect("'TVC-"&text(month(N$1),"00")&"'!$A:$D"),4,false),1)) -> 1 | O15: =IF(isblank(O$1),,IFERROR(vlookup($A15,indirect("'TVC-"&text(month(O$1),"00")&"'!$A:$D"),4,false),1)) -> 1 | ... Q15: =IF(isblank(Q$1),,IFERROR(vlookup($A15,indirect("'TVC-"&text(month(Q$1),"00")&"'!$A:$D"),4,false),1)) | R15: =index(A15:Q15,,month(today())+5)-index(A15:Q15,,month(today())+4) -> 0
A16: =IFERROR(__xludf.DUMMYFUNCTION("""COMPUTED_VALUE"""),165.0) -> 165 | B16: =IFERROR(__xludf.DUMMYFUNCTION("""COMPUTED_VALUE"""),"Seahawks, Seattle") -> Seahawks, Seattle | C16: =IFERROR(__xludf.DUMMYFUNCTION("""COMPUTED_VALUE"""),"TMWR") -> TMWR | D16: =IFERROR(__xludf.DUMMYFUNCTION("""COMPUTED_VALUE"""),"SEA") -> SEA | E16: =mid(B16,find(",",B16)+2,30)&" "&left(B16,find(",",B16)-1) -> Seattle Seahawks | F16: =IF(isblank(F$1),,IF(isblank($A16),,IFERROR(vlookup($A16,indirect("'TVC-"&text(month(F$1),"00")&"'!$A:$D"),4,false),1))) -> 1 | G16: =IF(isblank(G$1),,IF(isblank($A16),,IFERROR(vlookup($A16,indirect("'TVC-"&text(month(G$1),"00")&"'!$A:$D"),4,false),1))) -> 1 | H16: =IF(isblank(H$1),,IFERROR(vlookup($A16,indirect("'TVC-"&text(month(H$1),"00")&"'!$A:$D"),4,false),1)) -> 1 | I16: =IF(isblank(I$1),,IFERROR(vlookup($A16,indirect("'TVC-"&text(month(I$1),"00")&"'!$A:$D"),4,false),1)) -> 1 | J16: =IF(isblank(J$1),,IFERROR(vlookup($A16,indirect("'TVC-"&text(month(J$1),"00")&"'!$A:$D"),4,false),1)) -> 1 | K16: =IF(isblank(K$1),,IFERROR(vlookup($A16,indirect("'TVC-"&text(month(K$1),"00")&"'!$A:$D"),4,false),1)) -> 1 | L16: =IF(isblank(L$1),,IFERROR(vlookup($A16,indirect("'TVC-"&text(month(L$1),"00")&"'!$A:$D"),4,false),1)) -> 1 | M16: =IF(isblank(M$1),,IFERROR(vlookup($A16,indirect("'TVC-"&text(month(M$1),"00")&"'!$A:$D"),4,false),1)) -> 1 | N16: =IF(isblank(N$1),,IFERROR(vlookup($A16,indirect("'TVC-"&text(month(N$1),"00")&"'!$A:$D"),4,false),1)) -> 1 | O16: =IF(isblank(O$1),,IFERROR(vlookup($A16,indirect("'TVC-"&text(month(O$1),"00")&"'!$A:$D"),4,false),1)) -> 1 | ... Q16: =IF(isblank(Q$1),,IFERROR(vlookup($A16,indirect("'TVC-"&text(month(Q$1),"00")&"'!$A:$D"),4,false),1)) | R16: =index(A16:Q16,,month(today())+5)-index(A16:Q16,,month(today())+4) -> 0
A17: =IFERROR(__xludf.DUMMYFUNCTION("""COMPUTED_VALUE"""),166.0) -> 166 | B17: =IFERROR(__xludf.DUMMYFUNCTION("""COMPUTED_VALUE"""),"Cowboys, Dallas") -> Cowboys, Dallas | C17: =IFERROR(__xludf.DUMMYFUNCTION("""COMPUTED_VALUE"""),"TMWR") -> TMWR | D17: =IFERROR(__xludf.DUMMYFUNCTION("""COMPUTED_VALUE"""),"DAL") -> DAL | E17: =mid(B17,find(",",B17)+2,30)&" "&left(B17,find(",",B17)-1) -> Dallas Cowboys | F17: =IF(isblank(F$1),,IF(isblank($A17),,IFERROR(vlookup($A17,indirect("'TVC-"&text(month(F$1),"00")&"'!$A:$D"),4,false),1))) -> 1 | G17: =IF(isblank(G$1),,IF(isblank($A17),,IFERROR(vlookup($A17,indirect("'TVC-"&text(month(G$1),"00")&"'!$A:$D"),4,false),1))) -> 1 | H17: =IF(isblank(H$1),,IFERROR(vlookup($A17,indirect("'TVC-"&text(month(H$1),"00")&"'!$A:$D"),4,false),1)) -> 1 | I17: =IF(isblank(I$1),,IFERROR(vlookup($A17,indirect("'TVC-"&text(month(I$1),"00")&"'!$A:$D"),4,false),1)) -> 1 | J17: =IF(isblank(J$1),,IFERROR(vlookup($A17,indirect("'TVC-"&text(month(J$1),"00")&"'!$A:$D"),4,false),1)) -> 1 | K17: =IF(isblank(K$1),,IFERROR(vlookup($A17,indirect("'TVC-"&text(month(K$1),"00")&"'!$A:$D"),4,false),1)) -> 1 | L17: =IF(isblank(L$1),,IFERROR(vlookup($A17,indirect("'TVC-"&text(month(L$1),"00")&"'!$A:$D"),4,false),1)) -> 1 | M17: =IF(isblank(M$1),,IFERROR(vlookup($A17,indirect("'TVC-"&text(month(M$1),"00")&"'!$A:$D"),4,false),1)) -> 1 | N17: =IF(isblank(N$1),,IFERROR(vlookup($A17,indirect("'TVC-"&text(month(N$1),"00")&"'!$A:$D"),4,false),1)) -> 1 | O17: =IF(isblank(O$1),,IFERROR(vlookup($A17,indirect("'TVC-"&text(month(O$1),"00")&"'!$A:$D"),4,false),1)) -> 1 | ... Q17: =IF(isblank(Q$1),,IFERROR(vlookup($A17,indirect("'TVC-"&text(month(Q$1),"00")&"'!$A:$D"),4,false),1)) | R17: =index(A17:Q17,,month(today())+5)-index(A17:Q17,,month(today())+4) -> 0
A18: =IFERROR(__xludf.DUMMYFUNCTION("""COMPUTED_VALUE"""),167.0) -> 167 | B18: =IFERROR(__xludf.DUMMYFUNCTION("""COMPUTED_VALUE"""),"Giants, New York") -> Giants, New York | C18: =IFERROR(__xludf.DUMMYFUNCTION("""COMPUTED_VALUE"""),"TMWR") -> TMWR | D18: =IFERROR(__xludf.DUMMYFUNCTION("""COMPUTED_VALUE"""),"NYG") -> NYG | E18: =mid(B18,find(",",B18)+2,30)&" "&left(B18,find(",",B18)-1) -> New York Giants | F18: =IF(isblank(F$1),,IF(isblank($A18),,IFERROR(vlookup($A18,indirect("'TVC-"&text(month(F$1),"00")&"'!$A:$D"),4,false),1))) -> 1 | G18: =IF(isblank(G$1),,IF(isblank($A18),,IFERROR(vlookup($A18,indirect("'TVC-"&text(month(G$1),"00")&"'!$A:$D"),4,false),1))) -> 1 | H18: =IF(isblank(H$1),,IFERROR(vlookup($A18,indirect("'TVC-"&text(month(H$1),"00")&"'!$A:$D"),4,false),1)) -> 1 | I18: =IF(isblank(I$1),,IFERROR(vlookup($A18,indirect("'TVC-"&text(month(I$1),"00")&"'!$A:$D"),4,false),1)) -> 1 | J18: =IF(isblank(J$1),,IFERROR(vlookup($A18,indirect("'TVC-"&text(month(J$1),"00")&"'!$A:$D"),4,false),1)) -> 1 | K18: =IF(isblank(K$1),,IFERROR(vlookup($A18,indirect("'TVC-"&text(month(K$1),"00")&"'!$A:$D"),4,false),1)) -> 1 | L18: =IF(isblank(L$1),,IFERROR(vlookup($A18,indirect("'TVC-"&text(month(L$1),"00")&"'!$A:$D"),4,false),1)) -> 1 | M18: =IF(isblank(M$1),,IFERROR(vlookup($A18,indirect("'TVC-"&text(month(M$1),"00")&"'!$A:$D"),4,false),1)) -> 1 | N18: =IF(isblank(N$1),,IFERROR(vlookup($A18,indirect("'TVC-"&text(month(N$1),"00")&"'!$A:$D"),4,false),1)) -> 1 | O18: =IF(isblank(O$1),,IFERROR(vlookup($A18,indirect("'TVC-"&text(month(O$1),"00")&"'!$A:$D"),4,false),1)) -> 1 | ... Q18: =IF(isblank(Q$1),,IFERROR(vlookup($A18,indirect("'TVC-"&text(month(Q$1),"00")&"'!$A:$D"),4,false),1)) | R18: =index(A18:Q18,,month(today())+5)-index(A18:Q18,,month(today())+4) -> 0
A19: =IFERROR(__xludf.DUMMYFUNCTION("""COMPUTED_VALUE"""),168.0) -> 168 | B19: =IFERROR(__xludf.DUMMYFUNCTION("""COMPUTED_VALUE"""),"Eagles, Philadelphia") -> Eagles, Philadelphia | C19: =IFERROR(__xludf.DUMMYFUNCTION("""COMPUTED_VALUE"""),"TMWR") -> TMWR | D19: =IFERROR(__xludf.DUMMYFUNCTION("""COMPUTED_VALUE"""),"PHI") -> PHI | E19: =mid(B19,find(",",B19)+2,30)&" "&left(B19,find(",",B19)-1) -> Philadelphia Eagles | F19: =IF(isblank(F$1),,IF(isblank($A19),,IFERROR(vlookup($A19,indirect("'TVC-"&text(month(F$1),"00")&"'!$A:$D"),4,false),1))) -> 1 | G19: =IF(isblank(G$1),,IF(isblank($A19),,IFERROR(vlookup($A19,indirect("'TVC-"&text(month(G$1),"00")&"'!$A:$D"),4,false),1))) -> 1 | H19: =IF(isblank(H$1),,IFERROR(vlookup($A19,indirect("'TVC-"&text(month(H$1),"00")&"'!$A:$D"),4,false),1)) -> 1 | I19: =IF(isblank(I$1),,IFERROR(vlookup($A19,indirect("'TVC-"&text(month(I$1),"00")&"'!$A:$D"),4,false),1)) -> 1 | J19: =IF(isblank(J$1),,IFERROR(vlookup($A19,indirect("'TVC-"&text(month(J$1),"00")&"'!$A:$D"),4,false),1)) -> 1 | K19: =IF(isblank(K$1),,IFERROR(vlookup($A19,indirect("'TVC-"&text(month(K$1),"00")&"'!$A:$D"),4,false),1)) -> 1 | L19: =IF(isblank(L$1),,IFERROR(vlookup($A19,indirect("'TVC-"&text(month(L$1),"00")&"'!$A:$D"),4,false),1)) -> 1 | M19: =IF(isblank(M$1),,IFERROR(vlookup($A19,indirect("'TVC-"&text(month(M$1),"00")&"'!$A:$D"),4,false),1)) -> 1 | N19: =IF(isblank(N$1),,IFERROR(vlookup($A19,indirect("'TVC-"&text(month(N$1),"00")&"'!$A:$D"),4,false),1)) -> 1 | O19: =IF(isblank(O$1),,IFERROR(vlookup($A19,indirect("'TVC-"&text(month(O$1),"00")&"'!$A:$D"),4,false),1)) -> 1 | ... Q19: =IF(isblank(Q$1),,IFERROR(vlookup($A19,indirect("'TVC-"&text(month(Q$1),"00")&"'!$A:$D"),4,false),1)) | R19: =index(A19:Q19,,month(today())+5)-index(A19:Q19,,month(today())+4) -> 0
A20: =IFERROR(__xludf.DUMMYFUNCTION("""COMPUTED_VALUE"""),169.0) -> 169 | B20: =IFERROR(__xludf.DUMMYFUNCTION("""COMPUTED_VALUE"""),"Cardinals, Arizona") -> Cardinals, Arizona | C20: =IFERROR(__xludf.DUMMYFUNCTION("""COMPUTED_VALUE"""),"TMWR") -> TMWR | D20: =IFERROR(__xludf.DUMMYFUNCTION("""COMPUTED_VALUE"""),"ARI") -> ARI | E20: =mid(B20,find(",",B20)+2,30)&" "&left(B20,find(",",B20)-1) -> Arizona Cardinals | F20: =IF(isblank(F$1),,IF(isblank($A20),,IFERROR(vlookup($A20,indirect("'TVC-"&text(month(F$1),"00")&"'!$A:$D"),4,false),1))) -> 1 | G20: =IF(isblank(G$1),,IF(isblank($A20),,IFERROR(vlookup($A20,indirect("'TVC-"&text(month(G$1),"00")&"'!$A:$D"),4,false),1))) -> 1 | H20: =IF(isblank(H$1),,IFERROR(vlookup($A20,indirect("'TVC-"&text(month(H$1),"00")&"'!$A:$D"),4,false),1)) -> 1 | I20: =IF(isblank(I$1),,IFERROR(vlookup($A20,indirect("'TVC-"&text(month(I$1),"00")&"'!$A:$D"),4,false),1)) -> 1 | J20: =IF(isblank(J$1),,IFERROR(vlookup($A20,indirect("'TVC-"&text(month(J$1),"00")&"'!$A:$D"),4,false),1)) -> 1 | K20: =IF(isblank(K$1),,IFERROR(vlookup($A20,indirect("'TVC-"&text(month(K$1),"00")&"'!$A:$D"),4,false),1)) -> 1 | L20: =IF(isblank(L$1),,IFERROR(vlookup($A20,indirect("'TVC-"&text(month(L$1),"00")&"'!$A:$D"),4,false),1)) -> 1 | M20: =IF(isblank(M$1),,IFERROR(vlookup($A20,indirect("'TVC-"&text(month(M$1),"00")&"'!$A:$D"),4,false),1)) -> 1 | N20: =IF(isblank(N$1),,IFERROR(vlookup($A20,indirect("'TVC-"&text(month(N$1),"00")&"'!$A:$D"),4,false),1)) -> 1 | O20: =IF(isblank(O$1),,IFERROR(vlookup($A20,indirect("'TVC-"&text(month(O$1),"00")&"'!$A:$D"),4,false),1)) -> 1 | ... Q20: =IF(isblank(Q$1),,IFERROR(vlookup($A20,indirect("'TVC-"&text(month(Q$1),"00")&"'!$A:$D"),4,false),1)) | R20: =index(A20:Q20,,month(today())+5)-index(A20:Q20,,month(today())+4) -> 0
A21: =IFERROR(__xludf.DUMMYFUNCTION("""COMPUTED_VALUE"""),170.0) -> 170 | B21: =IFERROR(__xludf.DUMMYFUNCTION("""COMPUTED_VALUE"""),"Commanders, Washington") -> Commanders, Washington | C21: =IFERROR(__xludf.DUMMYFUNCTION("""COMPUTED_VALUE"""),"TMWR") -> TMWR | D21: =IFERROR(__xludf.DUMMYFUNCTION("""COMPUTED_VALUE"""),"WAS") -> WAS | E21: =mid(B21,find(",",B21)+2,30)&" "&left(B21,find(",",B21)-1) -> Washington Commanders | F21: =IF(isblank(F$1),,IF(isblank($A21),,IFERROR(vlookup($A21,indirect("'TVC-"&text(month(F$1),"00")&"'!$A:$D"),4,false),1))) -> 1 | G21: =IF(isblank(G$1),,IF(isblank($A21),,IFERROR(vlookup($A21,indirect("'TVC-"&text(month(G$1),"00")&"'!$A:$D"),4,false),1))) -> 1 | H21: =IF(isblank(H$1),,IFERROR(vlookup($A21,indirect("'TVC-"&text(month(H$1),"00")&"'!$A:$D"),4,false),1)) -> 1 | I21: =IF(isblank(I$1),,IFERROR(vlookup($A21,indirect("'TVC-"&text(month(I$1),"00")&"'!$A:$D"),4,false),1)) -> 1 | J21: =IF(isblank(J$1),,IFERROR(vlookup($A21,indirect("'TVC-"&text(month(J$1),"00")&"'!$A:$D"),4,false),1)) -> 1 | K21: =IF(isblank(K$1),,IFERROR(vlookup($A21,indirect("'TVC-"&text(month(K$1),"00")&"'!$A:$D"),4,false),1)) -> 1 | L21: =IF(isblank(L$1),,IFERROR(vlookup($A21,indirect("'TVC-"&text(month(L$1),"00")&"'!$A:$D"),4,false),1)) -> 1 | M21: =IF(isblank(M$1),,IFERROR(vlookup($A21,indirect("'TVC-"&text(month(M$1),"00")&"'!$A:$D"),4,false),1)) -> 1 | N21: =IF(isblank(N$1),,IFERROR(vlookup($A21,indirect("'TVC-"&text(month(N$1),"00")&"'!$A:$D"),4,false),1)) -> 1 | O21: =IF(isblank(O$1),,IFERROR(vlookup($A21,indirect("'TVC-"&text(month(O$1),"00")&"'!$A:$D"),4,false),1)) -> 1 | ... Q21: =IF(isblank(Q$1),,IFERROR(vlookup($A21,indirect("'TVC-"&text(month(Q$1),"00")&"'!$A:$D"),4,false),1)) | R21: =index(A21:Q21,,month(today())+5)-index(A21:Q21,,month(today())+4) -> 0
A22: =IFERROR(__xludf.DUMMYFUNCTION("""COMPUTED_VALUE"""),171.0) -> 171 | B22: =IFERROR(__xludf.DUMMYFUNCTION("""COMPUTED_VALUE"""),"Bears, Chicago") -> Bears, Chicago | C22: =IFERROR(__xludf.DUMMYFUNCTION("""COMPUTED_VALUE"""),"TMWR") -> TMWR | D22: =IFERROR(__xludf.DUMMYFUNCTION("""COMPUTED_VALUE"""),"CHI") -> CHI | E22: =mid(B22,find(",",B22)+2,30)&" "&left(B22,find(",",B22)-1) -> Chicago Bears | F22: =IF(isblank(F$1),,IF(isblank($A22),,IFERROR(vlookup($A22,indirect("'TVC-"&text(month(F$1),"00")&"'!$A:$D"),4,false),1))) -> 1 | G22: =IF(isblank(G$1),,IF(isblank($A22),,IFERROR(vlookup($A22,indirect("'TVC-"&text(month(G$1),"00")&"'!$A:$D"),4,false),1))) -> 1 | H22: =IF(isblank(H$1),,IFERROR(vlookup($A22,indirect("'TVC-"&text(month(H$1),"00")&"'!$A:$D"),4,false),1)) -> 1 | I22: =IF(isblank(I$1),,IFERROR(vlookup($A22,indirect("'TVC-"&text(month(I$1),"00")&"'!$A:$D"),4,false),1)) -> 1 | J22: =IF(isblank(J$1),,IFERROR(vlookup($A22,indirect("'TVC-"&text(month(J$1),"00")&"'!$A:$D"),4,false),1)) -> 1 | K22: =IF(isblank(K$1),,IFERROR(vlookup($A22,indirect("'TVC-"&text(month(K$1),"00")&"'!$A:$D"),4,false),1)) -> 1 | L22: =IF(isblank(L$1),,IFERROR(vlookup($A22,indirect("'TVC-"&text(month(L$1),"00")&"'!$A:$D"),4,false),1)) -> 1 | M22: =IF(isblank(M$1),,IFERROR(vlookup($A22,indirect("'TVC-"&text(month(M$1),"00")&"'!$A:$D"),4,false),1)) -> 1 | N22: =IF(isblank(N$1),,IFERROR(vlookup($A22,indirect("'TVC-"&text(month(N$1),"00")&"'!$A:$D"),4,false),1)) -> 1 | O22: =IF(isblank(O$1),,IFERROR(vlookup($A22,indirect("'TVC-"&text(month(O$1),"00")&"'!$A:$D"),4,false),1)) -> 1 | ... Q22: =IF(isblank(Q$1),,IFERROR(vlookup($A22,indirect("'TVC-"&text(month(Q$1),"00")&"'!$A:$D"),4,false),1)) | R22: =index(A22:Q22,,month(today())+5)-index(A22:Q22,,month(today())+4) -> 0
A23: =IFERROR(__xludf.DUMMYFUNCTION("""COMPUTED_VALUE"""),172.0) -> 172 | B23: =IFERROR(__xludf.DUMMYFUNCTION("""COMPUTED_VALUE"""),"Lions, Detroit") -> Lions, Detroit | C23: =IFERROR(__xludf.DUMMYFUNCTION("""COMPUTED_VALUE"""),"TMWR") -> TMWR | D23: =IFERROR(__xludf.DUMMYFUNCTION("""COMPUTED_VALUE"""),"DET") -> DET | E23: =mid(B23,find(",",B23)+2,30)&" "&left(B23,find(",",B23)-1) -> Detroit Lions | F23: =IF(isblank(F$1),,IF(isblank($A23),,IFERROR(vlookup($A23,indirect("'TVC-"&text(month(F$1),"00")&"'!$A:$D"),4,false),1))) -> 1 | G23: =IF(isblank(G$1),,IF(isblank($A23),,IFERROR(vlookup($A23,indirect("'TVC-"&text(month(G$1),"00")&"'!$A:$D"),4,false),1))) -> 1 | H23: =IF(isblank(H$1),,IFERROR(vlookup($A23,indirect("'TVC-"&text(month(H$1),"00")&"'!$A:$D"),4,false),1)) -> 1 | I23: =IF(isblank(I$1),,IFERROR(vlookup($A23,indirect("'TVC-"&text(month(I$1),"00")&"'!$A:$D"),4,false),1)) -> 1 | J23: =IF(isblank(J$1),,IFERROR(vlookup($A23,indirect("'TVC-"&text(month(J$1),"00")&"'!$A:$D"),4,false),1)) -> 1 | K23: =IF(isblank(K$1),,IFERROR(vlookup($A23,indirect("'TVC-"&text(month(K$1),"00")&"'!$A:$D"),4,false),1)) -> 1 | L23: =IF(isblank(L$1),,IFERROR(vlookup($A23,indirect("'TVC-"&text(month(L$1),"00")&"'!$A:$D"),4,false),1)) -> 1 | M23: =IF(isblank(M$1),,IFERROR(vlookup($A23,indirect("'TVC-"&text(month(M$1),"00")&"'!$A:$D"),4,false),1)) -> 1 | N23: =IF(isblank(N$1),,IFERROR(vlookup($A23,indirect("'TVC-"&text(month(N$1),"00")&"'!$A:$D"),4,false),1)) -> 1 | O23: =IF(isblank(O$1),,IFERROR(vlookup($A23,indirect("'TVC-"&text(month(O$1),"00")&"'!$A:$D"),4,false),1)) -> 1 | ... Q23: =IF(isblank(Q$1),,IFERROR(vlookup($A23,indirect("'TVC-"&text(month(Q$1),"00")&"'!$A:$D"),4,false),1)) | R23: =index(A23:Q23,,month(today())+5)-index(A23:Q23,,month(today())+4) -> 0
A24: =IFERROR(__xludf.DUMMYFUNCTION("""COMPUTED_VALUE"""),173.0) -> 173 | B24: =IFERROR(__xludf.DUMMYFUNCTION("""COMPUTED_VALUE"""),"Packers, Green Bay") -> Packers, Green Bay | C24: =IFERROR(__xludf.DUMMYFUNCTION("""COMPUTED_VALUE"""),"TMWR") -> TMWR | D24: =IFERROR(__xludf.DUMMYFUNCTION("""COMPUTED_VALUE"""),"GBP") -> GBP | E24: =mid(B24,find(",",B24)+2,30)&" "&left(B24,find(",",B24)-1) -> Green Bay Packers | F24: =IF(isblank(F$1),,IF(isblank($A24),,IFERROR(vlookup($A24,indirect("'TVC-"&text(month(F$1),"00")&"'!$A:$D"),4,false),1))) -> 1 | G24: =IF(isblank(G$1),,IF(isblank($A24),,IFERROR(vlookup($A24,indirect("'TVC-"&text(month(G$1),"00")&"'!$A:$D"),4,false),1))) -> 1 | H24: =IF(isblank(H$1),,IFERROR(vlookup($A24,indirect("'TVC-"&text(month(H$1),"00")&"'!$A:$D"),4,false),1)) -> 1 | I24: =IF(isblank(I$1),,IFERROR(vlookup($A24,indirect("'TVC-"&text(month(I$1),"00")&"'!$A:$D"),4,false),1)) -> 1 | J24: =IF(isblank(J$1),,IFERROR(vlookup($A24,indirect("'TVC-"&text(month(J$1),"00")&"'!$A:$D"),4,false),1)) -> 1 | K24: =IF(isblank(K$1),,IFERROR(vlookup($A24,indirect("'TVC-"&text(month(K$1),"00")&"'!$A:$D"),4,false),1)) -> 1 | L24: =IF(isblank(L$1),,IFERROR(vlookup($A24,indirect("'TVC-"&text(month(L$1),"00")&"'!$A:$D"),4,false),1)) -> 1 | M24: =IF(isblank(M$1),,IFERROR(vlookup($A24,indirect("'TVC-"&text(month(M$1),"00")&"'!$A:$D"),4,false),1)) -> 1 | N24: =IF(isblank(N$1),,IFERROR(vlookup($A24,indirect("'TVC-"&text(month(N$1),"00")&"'!$A:$D"),4,false),1)) -> 1 | O24: =IF(isblank(O$1),,IFERROR(vlookup($A24,indirect("'TVC-"&text(month(O$1),"00")&"'!$A:$D"),4,false),1)) -> 1 | ... Q24: =IF(isblank(Q$1),,IFERROR(vlookup($A24,indirect("'TVC-"&text(month(Q$1),"00")&"'!$A:$D"),4,false),1)) | R24: =index(A24:Q24,,month(today())+5)-index(A24:Q24,,month(today())+4) -> 0
A25: =IFERROR(__xludf.DUMMYFUNCTION("""COMPUTED_VALUE"""),174.0) -> 174 | B25: =IFERROR(__xludf.DUMMYFUNCTION("""COMPUTED_VALUE"""),"Vikings, Minnesota") -> Vikings, Minnesota | C25: =IFERROR(__xludf.DUMMYFUNCTION("""COMPUTED_VALUE"""),"TMWR") -> TMWR | D25: =IFERROR(__xludf.DUMMYFUNCTION("""COMPUTED_VALUE"""),"MIN") -> MIN | E25: =mid(B25,find(",",B25)+2,30)&" "&left(B25,find(",",B25)-1) -> Minnesota Vikings | F25: =IF(isblank(F$1),,IF(isblank($A25),,IFERROR(vlookup($A25,indirect("'TVC-"&text(month(F$1),"00")&"'!$A:$D"),4,false),1))) -> 1 | G25: =IF(isblank(G$1),,IF(isblank($A25),,IFERROR(vlookup($A25,indirect("'TVC-"&text(month(G$1),"00")&"'!$A:$D"),4,false),1))) -> 1 | H25: =IF(isblank(H$1),,IFERROR(vlookup($A25,indirect("'TVC-"&text(month(H$1),"00")&"'!$A:$D"),4,false),1)) -> 1 | I25: =IF(isblank(I$1),,IFERROR(vlookup($A25,indirect("'TVC-"&text(month(I$1),"00")&"'!$A:$D"),4,false),1)) -> 1 | J25: =IF(isblank(J$1),,IFERROR(vlookup($A25,indirect("'TVC-"&text(month(J$1),"00")&"'!$A:$D"),4,false),1)) -> 1 | K25: =IF(isblank(K$1),,IFERROR(vlookup($A25,indirect("'TVC-"&text(month(K$1),"00")&"'!$A:$D"),4,false),1)) -> 1 | L25: =IF(isblank(L$1),,IFERROR(vlookup($A25,indirect("'TVC-"&text(month(L$1),"00")&"'!$A:$D"),4,false),1)) -> 1 | M25: =IF(isblank(M$1),,IFERROR(vlookup($A25,indirect("'TVC-"&text(month(M$1),"00")&"'!$A:$D"),4,false),1)) -> 1 | N25: =IF(isblank(N$1),,IFERROR(vlookup($A25,indirect("'TVC-"&text(month(N$1),"00")&"'!$A:$D"),4,false),1)) -> 1 | O25: =IF(isblank(O$1),,IFERROR(vlookup($A25,indirect("'TVC-"&text(month(O$1),"00")&"'!$A:$D"),4,false),1)) -> 1 | ... Q25: =IF(isblank(Q$1),,IFERROR(vlookup($A25,indirect("'TVC-"&text(month(Q$1),"00")&"'!$A:$D"),4,false),1)) | R25: =index(A25:Q25,,month(today())+5)-index(A25:Q25,,month(today())+4) -> 0
A26: =IFERROR(__xludf.DUMMYFUNCTION("""COMPUTED_VALUE"""),175.0) -> 175 | B26: =IFERROR(__xludf.DUMMYFUNCTION("""COMPUTED_VALUE"""),"Buccaneers, Tampa Bay") -> Buccaneers, Tampa Bay | C26: =IFERROR(__xludf.DUMMYFUNCTION("""COMPUTED_VALUE"""),"TMWR") -> TMWR | D26: =IFERROR(__xludf.DUMMYFUNCTION("""COMPUTED_VALUE"""),"TBB") -> TBB | E26: =mid(B26,find(",",B26)+2,30)&" "&left(B26,find(",",B26)-1) -> Tampa Bay Buccaneers | F26: =IF(isblank(F$1),,IF(isblank($A26),,IFERROR(vlookup($A26,indirect("'TVC-"&text(month(F$1),"00")&"'!$A:$D"),4,false),1))) -> 1 | G26: =IF(isblank(G$1),,IF(isblank($A26),,IFERROR(vlookup($A26,indirect("'TVC-"&text(month(G$1),"00")&"'!$A:$D"),4,false),1))) -> 1 | H26: =IF(isblank(H$1),,IFERROR(vlookup($A26,indirect("'TVC-"&text(month(H$1),"00")&"'!$A:$D"),4,false),1)) -> 1 | I26: =IF(isblank(I$1),,IFERROR(vlookup($A26,indirect("'TVC-"&text(month(I$1),"00")&"'!$A:$D"),4,false),1)) -> 1 | J26: =IF(isblank(J$1),,IFERROR(vlookup($A26,indirect("'TVC-"&text(month(J$1),"00")&"'!$A:$D"),4,false),1)) -> 1 | K26: =IF(isblank(K$1),,IFERROR(vlookup($A26,indirect("'TVC-"&text(month(K$1),"00")&"'!$A:$D"),4,false),1)) -> 1 | L26: =IF(isblank(L$1),,IFERROR(vlookup($A26,indirect("'TVC-"&text(month(L$1),"00")&"'!$A:$D"),4,false),1)) -> 1 | M26: =IF(isblank(M$1),,IFERROR(vlookup($A26,indirect("'TVC-"&text(month(M$1),"00")&"'!$A:$D"),4,false),1)) -> 1 | N26: =IF(isblank(N$1),,IFERROR(vlookup($A26,indirect("'TVC-"&text(month(N$1),"00")&"'!$A:$D"),4,false),1)) -> 1 | O26: =IF(isblank(O$1),,IFERROR(vlookup($A26,indirect("'TVC-"&text(month(O$1),"00")&"'!$A:$D"),4,false),1)) -> 1 | ... Q26: =IF(isblank(Q$1),,IFERROR(vlookup($A26,indirect("'TVC-"&text(month(Q$1),"00")&"'!$A:$D"),4,false),1)) | R26: =index(A26:Q26,,month(today())+5)-index(A26:Q26,,month(today())+4) -> 0
A27: =IFERROR(__xludf.DUMMYFUNCTION("""COMPUTED_VALUE"""),176.0) -> 176 | B27: =IFERROR(__xludf.DUMMYFUNCTION("""COMPUTED_VALUE"""),"Falcons, Atlanta") -> Falcons, Atlanta | C27: =IFERROR(__xludf.DUMMYFUNCTION("""COMPUTED_VALUE"""),"TMWR") -> TMWR | D27: =IFERROR(__xludf.DUMMYFUNCTION("""COMPUTED_VALUE"""),"ATL") -> ATL | E27: =mid(B27,find(",",B27)+2,30)&" "&left(B27,find(",",B27)-1) -> Atlanta Falcons | F27: =IF(isblank(F$1),,IF(isblank($A27),,IFERROR(vlookup($A27,indirect("'TVC-"&text(month(F$1),"00")&"'!$A:$D"),4,false),1))) -> 1 | G27: =IF(isblank(G$1),,IF(isblank($A27),,IFERROR(vlookup($A27,indirect("'TVC-"&text(month(G$1),"00")&"'!$A:$D"),4,false),1))) -> 1 | H27: =IF(isblank(H$1),,IFERROR(vlookup($A27,indirect("'TVC-"&text(month(H$1),"00")&"'!$A:$D"),4,false),1)) -> 1 | I27: =IF(isblank(I$1),,IFERROR(vlookup($A27,indirect("'TVC-"&text(month(I$1),"00")&"'!$A:$D"),4,false),1)) -> 1 | J27: =IF(isblank(J$1),,IFERROR(vlookup($A27,indirect("'TVC-"&text(month(J$1),"00")&"'!$A:$D"),4,false),1)) -> 1 | K27: =IF(isblank(K$1),,IFERROR(vlookup($A27,indirect("'TVC-"&text(month(K$1),"00")&"'!$A:$D"),4,false),1)) -> 1 | L27: =IF(isblank(L$1),,IFERROR(vlookup($A27,indirect("'TVC-"&text(month(L$1),"00")&"'!$A:$D"),4,false),1)) -> 1 | M27: =IF(isblank(M$1),,IFERROR(vlookup($A27,indirect("'TVC-"&text(month(M$1),"00")&"'!$A:$D"),4,false),1)) -> 1 | N27: =IF(isblank(N$1),,IFERROR(vlookup($A27,indirect("'TVC-"&text(month(N$1),"00")&"'!$A:$D"),4,false),1)) -> 1 | O27: =IF(isblank(O$1),,IFERROR(vlookup($A27,indirect("'TVC-"&text(month(O$1),"00")&"'!$A:$D"),4,false),1)) -> 1 | ... Q27: =IF(isblank(Q$1),,IFERROR(vlookup($A27,indirect("'TVC-"&text(month(Q$1),"00")&"'!$A:$D"),4,false),1)) | R27: =index(A27:Q27,,month(today())+5)-index(A27:Q27,,month(today())+4) -> 0
A28: =IFERROR(__xludf.DUMMYFUNCTION("""COMPUTED_VALUE"""),177.0) -> 177 | B28: =IFERROR(__xludf.DUMMYFUNCTION("""COMPUTED_VALUE"""),"Panthers, Carolina") -> Panthers, Carolina | C28: =IFERROR(__xludf.DUMMYFUNCTION("""COMPUTED_VALUE"""),"TMWR") -> TMWR | D28: =IFERROR(__xludf.DUMMYFUNCTION("""COMPUTED_VALUE"""),"CAR") -> CAR | E28: =mid(B28,find(",",B28)+2,30)&" "&left(B28,find(",",B28)-1) -> Carolina Panthers | F28: =IF(isblank(F$1),,IF(isblank($A28),,IFERROR(vlookup($A28,indirect("'TVC-"&text(month(F$1),"00")&"'!$A:$D"),4,false),1))) -> 1 | G28: =IF(isblank(G$1),,IF(isblank($A28),,IFERROR(vlookup($A28,indirect("'TVC-"&text(month(G$1),"00")&"'!$A:$D"),4,false),1))) -> 1 | H28: =IF(isblank(H$1),,IFERROR(vlookup($A28,indirect("'TVC-"&text(month(H$1),"00")&"'!$A:$D"),4,false),1)) -> 1 | I28: =IF(isblank(I$1),,IFERROR(vlookup($A28,indirect("'TVC-"&text(month(I$1),"00")&"'!$A:$D"),4,false),1)) -> 1 | J28: =IF(isblank(J$1),,IFERROR(vlookup($A28,indirect("'TVC-"&text(month(J$1),"00")&"'!$A:$D"),4,false),1)) -> 1 | K28: =IF(isblank(K$1),,IFERROR(vlookup($A28,indirect("'TVC-"&text(month(K$1),"00")&"'!$A:$D"),4,false),1)) -> 1 | L28: =IF(isblank(L$1),,IFERROR(vlookup($A28,indirect("'TVC-"&text(month(L$1),"00")&"'!$A:$D"),4,false),1)) -> 1 | M28: =IF(isblank(M$1),,IFERROR(vlookup($A28,indirect("'TVC-"&text(month(M$1),"00")&"'!$A:$D"),4,false),1)) -> 1 | N28: =IF(isblank(N$1),,IFERROR(vlookup($A28,indirect("'TVC-"&text(month(N$1),"00")&"'!$A:$D"),4,false),1)) -> 1 | O28: =IF(isblank(O$1),,IFERROR(vlookup($A28,indirect("'TVC-"&text(month(O$1),"00")&"'!$A:$D"),4,false),1)) -> 1 | ... Q28: =IF(isblank(Q$1),,IFERROR(vlookup($A28,indirect("'TVC-"&text(month(Q$1),"00")&"'!$A:$D"),4,false),1)) | R28: =index(A28:Q28,,month(today())+5)-index(A28:Q28,,month(today())+4) -> 0
A29: =IFERROR(__xludf.DUMMYFUNCTION("""COMPUTED_VALUE"""),178.0) -> 178 | B29: =IFERROR(__xludf.DUMMYFUNCTION("""COMPUTED_VALUE"""),"Rams, Los Angeles") -> Rams, Los Angeles | C29: =IFERROR(__xludf.DUMMYFUNCTION("""COMPUTED_VALUE"""),"TMWR") -> TMWR | D29: =IFERROR(__xludf.DUMMYFUNCTION("""COMPUTED_VALUE"""),"LAR") -> LAR | E29: =mid(B29,find(",",B29)+2,30)&" "&left(B29,find(",",B29)-1) -> Los Angeles Rams | F29: =IF(isblank(F$1),,IF(isblank($A29),,IFERROR(vlookup($A29,indirect("'TVC-"&text(month(F$1),"00")&"'!$A:$D"),4,false),1))) -> 1 | G29: =IF(isblank(G$1),,IF(isblank($A29),,IFERROR(vlookup($A29,indirect("'TVC-"&text(month(G$1),"00")&"'!$A:$D"),4,false),1))) -> 1 | H29: =IF(isblank(H$1),,IFERROR(vlookup($A29,indirect("'TVC-"&text(month(H$1),"00")&"'!$A:$D"),4,false),1)) -> 1 | I29: =IF(isblank(I$1),,IFERROR(vlookup($A29,indirect("'TVC-"&text(month(I$1),"00")&"'!$A:$D"),4,false),1)) -> 1 | J29: =IF(isblank(J$1),,IFERROR(vlookup($A29,indirect("'TVC-"&text(month(J$1),"00")&"'!$A:$D"),4,false),1)) -> 1 | K29: =IF(isblank(K$1),,IFERROR(vlookup($A29,indirect("'TVC-"&text(month(K$1),"00")&"'!$A:$D"),4,false),1)) -> 1 | L29: =IF(isblank(L$1),,IFERROR(vlookup($A29,indirect("'TVC-"&text(month(L$1),"00")&"'!$A:$D"),4,false),1)) -> 1 | M29: =IF(isblank(M$1),,IFERROR(vlookup($A29,indirect("'TVC-"&text(month(M$1),"00")&"'!$A:$D"),4,false),1)) -> 1 | N29: =IF(isblank(N$1),,IFERROR(vlookup($A29,indirect("'TVC-"&text(month(N$1),"00")&"'!$A:$D"),4,false),1)) -> 1 | O29: =IF(isblank(O$1),,IFERROR(vlookup($A29,indirect("'TVC-"&text(month(O$1),"00")&"'!$A:$D"),4,false),1)) -> 1 | ... Q29: =IF(isblank(Q$1),,IFERROR(vlookup($A29,indirect("'TVC-"&text(month(Q$1),"00")&"'!$A:$D"),4,false),1)) | R29: =index(A29:Q29,,month(today())+5)-index(A29:Q29,,month(today())+4) -> 0
A30: =IFERROR(__xludf.DUMMYFUNCTION("""COMPUTED_VALUE"""),179.0) -> 179 | B30: =IFERROR(__xludf.DUMMYFUNCTION("""COMPUTED_VALUE"""),"Saints, New Orleans") -> Saints, New Orleans | C30: =IFERROR(__xludf.DUMMYFUNCTION("""COMPUTED_VALUE"""),"TMWR") -> TMWR | D30: =IFERROR(__xludf.DUMMYFUNCTION("""COMPUTED_VALUE"""),"NOS") -> NOS | E30: =mid(B30,find(",",B30)+2,30)&" "&left(B30,find(",",B30)-1) -> New Orleans Saints | F30: =IF(isblank(F$1),,IF(isblank($A30),,IFERROR(vlookup($A30,indirect("'TVC-"&text(month(F$1),"00")&"'!$A:$D"),4,false),1))) -> 1 | G30: =IF(isblank(G$1),,IF(isblank($A30),,IFERROR(vlookup($A30,indirect("'TVC-"&text(month(G$1),"00")&"'!$A:$D"),4,false),1))) -> 1 | H30: =IF(isblank(H$1),,IFERROR(vlookup($A30,indirect("'TVC-"&text(month(H$1),"00")&"'!$A:$D"),4,false),1)) -> 1 | I30: =IF(isblank(I$1),,IFERROR(vlookup($A30,indirect("'TVC-"&text(month(I$1),"00")&"'!$A:$D"),4,false),1)) -> 1 | J30: =IF(isblank(J$1),,IFERROR(vlookup($A30,indirect("'TVC-"&text(month(J$1),"00")&"'!$A:$D"),4,false),1)) -> 1 | K30: =IF(isblank(K$1),,IFERROR(vlookup($A30,indirect("'TVC-"&text(month(K$1),"00")&"'!$A:$D"),4,false),1)) -> 1 | L30: =IF(isblank(L$1),,IFERROR(vlookup($A30,indirect("'TVC-"&text(month(L$1),"00")&"'!$A:$D"),4,false),1)) -> 1 | M30: =IF(isblank(M$1),,IFERROR(vlookup($A30,indirect("'TVC-"&text(month(M$1),"00")&"'!$A:$D"),4,false),1)) -> 1 | N30: =IF(isblank(N$1),,IFERROR(vlookup($A30,indirect("'TVC-"&text(month(N$1),"00")&"'!$A:$D"),4,false),1)) -> 1 | O30: =IF(isblank(O$1),,IFERROR(vlookup($A30,indirect("'TVC-"&text(month(O$1),"00")&"'!$A:$D"),4,false),1)) -> 1 | ... Q30: =IF(isblank(Q$1),,IFERROR(vlookup($A30,indirect("'TVC-"&text(month(Q$1),"00")&"'!$A:$D"),4,false),1)) | R30: =index(A30:Q30,,month(today())+5)-index(A30:Q30,,month(today())+4) -> 0
A31: =IFERROR(__xludf.DUMMYFUNCTION("""COMPUTED_VALUE"""),180.0) -> 180 | B31: =IFERROR(__xludf.DUMMYFUNCTION("""COMPUTED_VALUE"""),"49ers, San Francisco") -> 49ers, San Francisco | C31: =IFERROR(__xludf.DUMMYFUNCTION("""COMPUTED_VALUE"""),"TMWR") -> TMWR | D31: =IFERROR(__xludf.DUMMYFUNCTION("""COMPUTED_VALUE"""),"SFO") -> SFO | E31: =mid(B31,find(",",B31)+2,30)&" "&left(B31,find(",",B31)-1) -> San Francisco 49ers | F31: =IF(isblank(F$1),,IF(isblank($A31),,IFERROR(vlookup($A31,indirect("'TVC-"&text(month(F$1),"00")&"'!$A:$D"),4,false),1))) -> 1 | G31: =IF(isblank(G$1),,IF(isblank($A31),,IFERROR(vlookup($A31,indirect("'TVC-"&text(month(G$1),"00")&"'!$A:$D"),4,false),1))) -> 1 | H31: =IF(isblank(H$1),,IFERROR(vlookup($A31,indirect("'TVC-"&text(month(H$1),"00")&"'!$A:$D"),4,false),1)) -> 1 | I31: =IF(isblank(I$1),,IFERROR(vlookup($A31,indirect("'TVC-"&text(month(I$1),"00")&"'!$A:$D"),4,false),1)) -> 1 | J31: =IF(isblank(J$1),,IFERROR(vlookup($A31,indirect("'TVC-"&text(month(J$1),"00")&"'!$A:$D"),4,false),1)) -> 1 | K31: =IF(isblank(K$1),,IFERROR(vlookup($A31,indirect("'TVC-"&text(month(K$1),"00")&"'!$A:$D"),4,false),1)) -> 1 | L31: =IF(isblank(L$1),,IFERROR(vlookup($A31,indirect("'TVC-"&text(month(L$1),"00")&"'!$A:$D"),4,false),1)) -> 1 | M31: =IF(isblank(M$1),,IFERROR(vlookup($A31,indirect("'TVC-"&text(month(M$1),"00")&"'!$A:$D"),4,false),1)) -> 1 | N31: =IF(isblank(N$1),,IFERROR(vlookup($A31,indirect("'TVC-"&text(month(N$1),"00")&"'!$A:$D"),4,false),1)) -> 1 | O31: =IF(isblank(O$1),,IFERROR(vlookup($A31,indirect("'TVC-"&text(month(O$1),"00")&"'!$A:$D"),4,false),1)) -> 1 | ... Q31: =IF(isblank(Q$1),,IFERROR(vlookup($A31,indirect("'TVC-"&text(month(Q$1),"00")&"'!$A:$D"),4,false),1)) | R31: =index(A31:Q31,,month(today())+5)-index(A31:Q31,,month(today())+4) -> 0
A32: =IFERROR(__xludf.DUMMYFUNCTION("""COMPUTED_VALUE"""),181.0) -> 181 | B32: =IFERROR(__xludf.DUMMYFUNCTION("""COMPUTED_VALUE"""),"Ravens, Baltimore") -> Ravens, Baltimore | C32: =IFERROR(__xludf.DUMMYFUNCTION("""COMPUTED_VALUE"""),"TMWR") -> TMWR | D32: =IFERROR(__xludf.DUMMYFUNCTION("""COMPUTED_VALUE"""),"BAL") -> BAL | E32: =mid(B32,find(",",B32)+2,30)&" "&left(B32,find(",",B32)-1) -> Baltimore Ravens | F32: =IF(isblank(F$1),,IF(isblank($A32),,IFERROR(vlookup($A32,indirect("'TVC-"&text(month(F$1),"00")&"'!$A:$D"),4,false),1))) -> 1 | G32: =IF(isblank(G$1),,IF(isblank($A32),,IFERROR(vlookup($A32,indirect("'TVC-"&text(month(G$1),"00")&"'!$A:$D"),4,false),1))) -> 1 | H32: =IF(isblank(H$1),,IFERROR(vlookup($A32,indirect("'TVC-"&text(month(H$1),"00")&"'!$A:$D"),4,false),1)) -> 1 | I32: =IF(isblank(I$1),,IFERROR(vlookup($A32,indirect("'TVC-"&text(month(I$1),"00")&"'!$A:$D"),4,false),1)) -> 1 | J32: =IF(isblank(J$1),,IFERROR(vlookup($A32,indirect("'TVC-"&text(month(J$1),"00")&"'!$A:$D"),4,false),1)) -> 1 | K32: =IF(isblank(K$1),,IFERROR(vlookup($A32,indirect("'TVC-"&text(month(K$1),"00")&"'!$A:$D"),4,false),1)) -> 1 | L32: =IF(isblank(L$1),,IFERROR(vlookup($A32,indirect("'TVC-"&text(month(L$1),"00")&"'!$A:$D"),4,false),1)) -> 1 | M32: =IF(isblank(M$1),,IFERROR(vlookup($A32,indirect("'TVC-"&text(month(M$1),"00")&"'!$A:$D"),4,false),1)) -> 1 | N32: =IF(isblank(N$1),,IFERROR(vlookup($A32,indirect("'TVC-"&text(month(N$1),"00")&"'!$A:$D"),4,false),1)) -> 1 | O32: =IF(isblank(O$1),,IFERROR(vlookup($A32,indirect("'TVC-"&text(month(O$1),"00")&"'!$A:$D"),4,false),1)) -> 1 | ... Q32: =IF(isblank(Q$1),,IFERROR(vlookup($A32,indirect("'TVC-"&text(month(Q$1),"00")&"'!$A:$D"),4,false),1)) | R32: =index(A32:Q32,,month(today())+5)-index(A32:Q32,,month(today())+4) -> 0
A33: =IFERROR(__xludf.DUMMYFUNCTION("""COMPUTED_VALUE"""),182.0) -> 182 | B33: =IFERROR(__xludf.DUMMYFUNCTION("""COMPUTED_VALUE"""),"Texans, Houston") -> Texans, Houston | C33: =IFERROR(__xludf.DUMMYFUNCTION("""COMPUTED_VALUE"""),"TMWR") -> TMWR | D33: =IFERROR(__xludf.DUMMYFUNCTION("""COMPUTED_VALUE"""),"HOU") -> HOU | E33: =mid(B33,find(",",B33)+2,30)&" "&left(B33,find(",",B33)-1) -> Houston Texans | F33: =IF(isblank(F$1),,IF(isblank($A33),,IFERROR(vlookup($A33,indirect("'TVC-"&text(month(F$1),"00")&"'!$A:$D"),4,false),1))) -> 1 | G33: =IF(isblank(G$1),,IF(isblank($A33),,IFERROR(vlookup($A33,indirect("'TVC-"&text(month(G$1),"00")&"'!$A:$D"),4,false),1))) -> 1 | H33: =IF(isblank(H$1),,IFERROR(vlookup($A33,indirect("'TVC-"&text(month(H$1),"00")&"'!$A:$D"),4,false),1)) -> 1 | I33: =IF(isblank(I$1),,IFERROR(vlookup($A33,indirect("'TVC-"&text(month(I$1),"00")&"'!$A:$D"),4,false),1)) -> 1 | J33: =IF(isblank(J$1),,IFERROR(vlookup($A33,indirect("'TVC-"&text(month(J$1),"00")&"'!$A:$D"),4,false),1)) -> 1 | K33: =IF(isblank(K$1),,IFERROR(vlookup($A33,indirect("'TVC-"&text(month(K$1),"00")&"'!$A:$D"),4,false),1)) -> 1 | L33: =IF(isblank(L$1),,IFERROR(vlookup($A33,indirect("'TVC-"&text(month(L$1),"00")&"'!$A:$D"),4,false),1)) -> 1 | M33: =IF(isblank(M$1),,IFERROR(vlookup($A33,indirect("'TVC-"&text(month(M$1),"00")&"'!$A:$D"),4,false),1)) -> 1 | N33: =IF(isblank(N$1),,IFERROR(vlookup($A33,indirect("'TVC-"&text(month(N$1),"00")&"'!$A:$D"),4,false),1)) -> 1 | O33: =IF(isblank(O$1),,IFERROR(vlookup($A33,indirect("'TVC-"&text(month(O$1),"00")&"'!$A:$D"),4,false),1)) -> 1 | ... Q33: =IF(isblank(Q$1),,IFERROR(vlookup($A33,indirect("'TVC-"&text(month(Q$1),"00")&"'!$A:$D"),4,false),1)) | R33: =index(A33:Q33,,month(today())+5)-index(A33:Q33,,month(today())+4) -> 0
A34: =IFERROR(__xludf.DUMMYFUNCTION("""COMPUTED_VALUE"""),201.0) -> 201 | B34: =IFERROR(__xludf.DUMMYFUNCTION("""COMPUTED_VALUE"""),"Bills, Buffalo") -> Bills, Buffalo | C34: =IFERROR(__xludf.DUMMYFUNCTION("""COMPUTED_VALUE"""),"TMRB") -> TMRB | D34: =IFERROR(__xludf.DUMMYFUNCTION("""COMPUTED_VALUE"""),"BUF") -> BUF | E34: =mid(B34,find(",",B34)+2,30)&" "&left(B34,find(",",B34)-1) -> Buffalo Bills | F34: =IF(isblank(F$1),,IF(isblank($A34),,IFERROR(vlookup($A34,indirect("'TVC-"&text(month(F$1),"00")&"'!$A:$D"),4,false),1))) -> 1 | G34: =IF(isblank(G$1),,IF(isblank($A34),,IFERROR(vlookup($A34,indirect("'TVC-"&text(month(G$1),"00")&"'!$A:$D"),4,false),1))) -> 1 | H34: =IF(isblank(H$1),,IFERROR(vlookup($A34,indirect("'TVC-"&text(month(H$1),"00")&"'!$A:$D"),4,false),1)) -> 1 | I34: =IF(isblank(I$1),,IFERROR(vlookup($A34,indirect("'TVC-"&text(month(I$1),"00")&"'!$A:$D"),4,false),1)) -> 1 | J34: =IF(isblank(J$1),,IFERROR(vlookup($A34,indirect("'TVC-"&text(month(J$1),"00")&"'!$A:$D"),4,false),1)) -> 1 | K34: =IF(isblank(K$1),,IFERROR(vlookup($A34,indirect("'TVC-"&text(month(K$1),"00")&"'!$A:$D"),4,false),1)) -> 1 | L34: =IF(isblank(L$1),,IFERROR(vlookup($A34,indirect("'TVC-"&text(month(L$1),"00")&"'!$A:$D"),4,false),1)) -> 1 | M34: =IF(isblank(M$1),,IFERROR(vlookup($A34,indirect("'TVC-"&text(month(M$1),"00")&"'!$A:$D"),4,false),1)) -> 1 | N34: =IF(isblank(N$1),,IFERROR(vlookup($A34,indirect("'TVC-"&text(month(N$1),"00")&"'!$A:$D"),4,false),1)) -> 1 | O34: =IF(isblank(O$1),,IFERROR(vlookup($A34,indirect("'TVC-"&text(month(O$1),"00")&"'!$A:$D"),4,false),1)) -> 1 | ... Q34: =IF(isblank(Q$1),,IFERROR(vlookup($A34,indirect("'TVC-"&text(month(Q$1),"00")&"'!$A:$D"),4,false),1)) | R34: =index(A34:Q34,,month(today())+5)-index(A34:Q34,,month(today())+4) -> 0
A35: =IFERROR(__xludf.DUMMYFUNCTION("""COMPUTED_VALUE"""),202.0) -> 202 | B35: =IFERROR(__xludf.DUMMYFUNCTION("""COMPUTED_VALUE"""),"Colts, Indianapolis") -> Colts, Indianapolis | C35: =IFERROR(__xludf.DUMMYFUNCTION("""COMPUTED_VALUE"""),"TMRB") -> TMRB | D35: =IFERROR(__xludf.DUMMYFUNCTION("""COMPUTED_VALUE"""),"IND") -> IND | E35: =mid(B35,find(",",B35)+2,30)&" "&left(B35,find(",",B35)-1) -> Indianapolis Colts | F35: =IF(isblank(F$1),,IF(isblank($A35),,IFERROR(vlookup($A35,indirect("'TVC-"&text(month(F$1),"00")&"'!$A:$D"),4,false),1))) -> 1 | G35: =IF(isblank(G$1),,IF(isblank($A35),,IFERROR(vlookup($A35,indirect("'TVC-"&text(month(G$1),"00")&"'!$A:$D"),4,false),1))) -> 1 | H35: =IF(isblank(H$1),,IFERROR(vlookup($A35,indirect("'TVC-"&text(month(H$1),"00")&"'!$A:$D"),4,false),1)) -> 1 | I35: =IF(isblank(I$1),,IFERROR(vlookup($A35,indirect("'TVC-"&text(month(I$1),"00")&"'!$A:$D"),4,false),1)) -> 1 | J35: =IF(isblank(J$1),,IFERROR(vlookup($A35,indirect("'TVC-"&text(month(J$1),"00")&"'!$A:$D"),4,false),1)) -> 1 | K35: =IF(isblank(K$1),,IFERROR(vlookup($A35,indirect("'TVC-"&text(month(K$1),"00")&"'!$A:$D"),4,false),1)) -> 1 | L35: =IF(isblank(L$1),,IFERROR(vlookup($A35,indirect("'TVC-"&text(month(L$1),"00")&"'!$A:$D"),4,false),1)) -> 1 | M35: =IF(isblank(M$1),,IFERROR(vlookup($A35,indirect("'TVC-"&text(month(M$1),"00")&"'!$A:$D"),4,false),1)) -> 1 | N35: =IF(isblank(N$1),,IFERROR(vlookup($A35,indirect("'TVC-"&text(month(N$1),"00")&"'!$A:$D"),4,false),1)) -> 1 | O35: =IF(isblank(O$1),,IFERROR(vlookup($A35,indirect("'TVC-"&text(month(O$1),"00")&"'!$A:$D"),4,false),1)) -> 1 | ... Q35: =IF(isblank(Q$1),,IFERROR(vlookup($A35,indirect("'TVC-"&text(month(Q$1),"00")&"'!$A:$D"),4,false),1)) | R35: =index(A35:Q35,,month(today())+5)-index(A35:Q35,,month(today())+4) -> 0
A36: =IFERROR(__xludf.DUMMYFUNCTION("""COMPUTED_VALUE"""),203.0) -> 203 | B36: =IFERROR(__xludf.DUMMYFUNCTION("""COMPUTED_VALUE"""),"Dolphins, Miami") -> Dolphins, Miami | C36: =IFERROR(__xludf.DUMMYFUNCTION("""COMPUTED_VALUE"""),"TMRB") -> TMRB | D36: =IFERROR(__xludf.DUMMYFUNCTION("""COMPUTED_VALUE"""),"MIA") -> MIA | E36: =mid(B36,find(",",B36)+2,30)&" "&left(B36,find(",",B36)-1) -> Miami Dolphins | F36: =IF(isblank(F$1),,IF(isblank($A36),,IFERROR(vlookup($A36,indirect("'TVC-"&text(month(F$1),"00")&"'!$A:$D"),4,false),1))) -> 1 | G36: =IF(isblank(G$1),,IF(isblank($A36),,IFERROR(vlookup($A36,indirect("'TVC-"&text(month(G$1),"00")&"'!$A:$D"),4,false),1))) -> 1 | H36: =IF(isblank(H$1),,IFERROR(vlookup($A36,indirect("'TVC-"&text(month(H$1),"00")&"'!$A:$D"),4,false),1)) -> 1 | I36: =IF(isblank(I$1),,IFERROR(vlookup($A36,indirect("'TVC-"&text(month(I$1),"00")&"'!$A:$D"),4,false),1)) -> 1 | J36: =IF(isblank(J$1),,IFERROR(vlookup($A36,indirect("'TVC-"&text(month(J$1),"00")&"'!$A:$D"),4,false),1)) -> 1 | K36: =IF(isblank(K$1),,IFERROR(vlookup($A36,indirect("'TVC-"&text(month(K$1),"00")&"'!$A:$D"),4,false),1)) -> 1 | L36: =IF(isblank(L$1),,IFERROR(vlookup($A36,indirect("'TVC-"&text(month(L$1),"00")&"'!$A:$D"),4,false),1)) -> 1 | M36: =IF(isblank(M$1),,IFERROR(vlookup($A36,indirect("'TVC-"&text(month(M$1),"00")&"'!$A:$D"),4,false),1)) -> 1 | N36: =IF(isblank(N$1),,IFERROR(vlookup($A36,indirect("'TVC-"&text(month(N$1),"00")&"'!$A:$D"),4,false),1)) -> 1 | O36: =IF(isblank(O$1),,IFERROR(vlookup($A36,indirect("'TVC-"&text(month(O$1),"00")&"'!$A:$D"),4,false),1)) -> 1 | ... Q36: =IF(isblank(Q$1),,IFERROR(vlookup($A36,indirect("'TVC-"&text(month(Q$1),"00")&"'!$A:$D"),4,false),1)) | R36: =index(A36:Q36,,month(today())+5)-index(A36:Q36,,month(today())+4) -> 0
A37: =IFERROR(__xludf.DUMMYFUNCTION("""COMPUTED_VALUE"""),204.0) -> 204 | B37: =IFERROR(__xludf.DUMMYFUNCTION("""COMPUTED_VALUE"""),"Patriots, New England") -> Patriots, New England | C37: =IFERROR(__xludf.DUMMYFUNCTION("""COMPUTED_VALUE"""),"TMRB") -> TMRB | D37: =IFERROR(__xludf.DUMMYFUNCTION("""COMPUTED_VALUE"""),"NEP") -> NEP | E37: =mid(B37,find(",",B37)+2,30)&" "&left(B37,find(",",B37)-1) -> New England Patriots | F37: =IF(isblank(F$1),,IF(isblank($A37),,IFERROR(vlookup($A37,indirect("'TVC-"&text(month(F$1),"00")&"'!$A:$D"),4,false),1))) -> 1 | G37: =IF(isblank(G$1),,IF(isblank($A37),,IFERROR(vlookup($A37,indirect("'TVC-"&text(month(G$1),"00")&"'!$A:$D"),4,false),1))) -> 1 | H37: =IF(isblank(H$1),,IFERROR(vlookup($A37,indirect("'TVC-"&text(month(H$1),"00")&"'!$A:$D"),4,false),1)) -> 1 | I37: =IF(isblank(I$1),,IFERROR(vlookup($A37,indirect("'TVC-"&text(month(I$1),"00")&"'!$A:$D"),4,false),1)) -> 1 | J37: =IF(isblank(J$1),,IFERROR(vlookup($A37,indirect("'TVC-"&text(month(J$1),"00")&"'!$A:$D"),4,false),1)) -> 1 | K37: =IF(isblank(K$1),,IFERROR(vlookup($A37,indirect("'TVC-"&text(month(K$1),"00")&"'!$A:$D"),4,false),1)) -> 1 | L37: =IF(isblank(L$1),,IFERROR(vlookup($A37,indirect("'TVC-"&text(month(L$1),"00")&"'!$A:$D"),4,false),1)) -> 1 | M37: =IF(isblank(M$1),,IFERROR(vlookup($A37,indirect("'TVC-"&text(month(M$1),"00")&"'!$A:$D"),4,false),1)) -> 1 | N37: =IF(isblank(N$1),,IFERROR(vlookup($A37,indirect("'TVC-"&text(month(N$1),"00")&"'!$A:$D"),4,false),1)) -> 1 | O37: =IF(isblank(O$1),,IFERROR(vlookup($A37,indirect("'TVC-"&text(month(O$1),"00")&"'!$A:$D"),4,false),1)) -> 1 | ... Q37: =IF(isblank(Q$1),,IFERROR(vlookup($A37,indirect("'TVC-"&text(month(Q$1),"00")&"'!$A:$D"),4,false),1)) | R37: =index(A37:Q37,,month(today())+5)-index(A37:Q37,,month(today())+4) -> 0
A38: =IFERROR(__xludf.DUMMYFUNCTION("""COMPUTED_VALUE"""),205.0) -> 205 | B38: =IFERROR(__xludf.DUMMYFUNCTION("""COMPUTED_VALUE"""),"Jets, New York") -> Jets, New York | C38: =IFERROR(__xludf.DUMMYFUNCTION("""COMPUTED_VALUE"""),"TMRB") -> TMRB | D38: =IFERROR(__xludf.DUMMYFUNCTION("""COMPUTED_VALUE"""),"NYJ") -> NYJ | E38: =mid(B38,find(",",B38)+2,30)&" "&left(B38,find(",",B38)-1) -> New York Jets | F38: =IF(isblank(F$1),,IF(isblank($A38),,IFERROR(vlookup($A38,indirect("'TVC-"&text(month(F$1),"00")&"'!$A:$D"),4,false),1))) -> 1 | G38: =IF(isblank(G$1),,IF(isblank($A38),,IFERROR(vlookup($A38,indirect("'TVC-"&text(month(G$1),"00")&"'!$A:$D"),4,false),1))) -> 1 | H38: =IF(isblank(H$1),,IFERROR(vlookup($A38,indirect("'TVC-"&text(month(H$1),"00")&"'!$A:$D"),4,false),1)) -> 1 | I38: =IF(isblank(I$1),,IFERROR(vlookup($A38,indirect("'TVC-"&text(month(I$1),"00")&"'!$A:$D"),4,false),1)) -> 1 | J38: =IF(isblank(J$1),,IFERROR(vlookup($A38,indirect("'TVC-"&text(month(J$1),"00")&"'!$A:$D"),4,false),1)) -> 1 | K38: =IF(isblank(K$1),,IFERROR(vlookup($A38,indirect("'TVC-"&text(month(K$1),"00")&"'!$A:$D"),4,false),1)) -> 1 | L38: =IF(isblank(L$1),,IFERROR(vlookup($A38,indirect("'TVC-"&text(month(L$1),"00")&"'!$A:$D"),4,false),1)) -> 1 | M38: =IF(isblank(M$1),,IFERROR(vlookup($A38,indirect("'TVC-"&text(month(M$1),"00")&"'!$A:$D"),4,false),1)) -> 1 | N38: =IF(isblank(N$1),,IFERROR(vlookup($A38,indirect("'TVC-"&text(month(N$1),"00")&"'!$A:$D"),4,false),1)) -> 1 | O38: =IF(isblank(O$1),,IFERROR(vlookup($A38,indirect("'TVC-"&text(month(O$1),"00")&"'!$A:$D"),4,false),1)) -> 1 | ... Q38: =IF(isblank(Q$1),,IFERROR(vlookup($A38,indirect("'TVC-"&text(month(Q$1),"00")&"'!$A:$D"),4,false),1)) | R38: =index(A38:Q38,,month(today())+5)-index(A38:Q38,,month(today())+4) -> 0
A39: =IFERROR(__xludf.DUMMYFUNCTION("""COMPUTED_VALUE"""),206.0) -> 206 | B39: =IFERROR(__xludf.DUMMYFUNCTION("""COMPUTED_VALUE"""),"Bengals, Cincinnati") -> Bengals, Cincinnati | C39: =IFERROR(__xludf.DUMMYFUNCTION("""COMPUTED_VALUE"""),"TMRB") -> TMRB | D39: =IFERROR(__xludf.DUMMYFUNCTION("""COMPUTED_VALUE"""),"CIN") -> CIN | E39: =mid(B39,find(",",B39)+2,30)&" "&left(B39,find(",",B39)-1) -> Cincinnati Bengals | F39: =IF(isblank(F$1),,IF(isblank($A39),,IFERROR(vlookup($A39,indirect("'TVC-"&text(month(F$1),"00")&"'!$A:$D"),4,false),1))) -> 1 | G39: =IF(isblank(G$1),,IF(isblank($A39),,IFERROR(vlookup($A39,indirect("'TVC-"&text(month(G$1),"00")&"'!$A:$D"),4,false),1))) -> 1 | H39: =IF(isblank(H$1),,IFERROR(vlookup($A39,indirect("'TVC-"&text(month(H$1),"00")&"'!$A:$D"),4,false),1)) -> 1 | I39: =IF(isblank(I$1),,IFERROR(vlookup($A39,indirect("'TVC-"&text(month(I$1),"00")&"'!$A:$D"),4,false),1)) -> 1 | J39: =IF(isblank(J$1),,IFERROR(vlookup($A39,indirect("'TVC-"&text(month(J$1),"00")&"'!$A:$D"),4,false),1)) -> 1 | K39: =IF(isblank(K$1),,IFERROR(vlookup($A39,indirect("'TVC-"&text(month(K$1),"00")&"'!$A:$D"),4,false),1)) -> 1 | L39: =IF(isblank(L$1),,IFERROR(vlookup($A39,indirect("'TVC-"&text(month(L$1),"00")&"'!$A:$D"),4,false),1)) -> 1 | M39: =IF(isblank(M$1),,IFERROR(vlookup($A39,indirect("'TVC-"&text(month(M$1),"00")&"'!$A:$D"),4,false),1)) -> 1 | N39: =IF(isblank(N$1),,IFERROR(vlookup($A39,indirect("'TVC-"&text(month(N$1),"00")&"'!$A:$D"),4,false),1)) -> 1 | O39: =IF(isblank(O$1),,IFERROR(vlookup($A39,indirect("'TVC-"&text(month(O$1),"00")&"'!$A:$D"),4,false),1)) -> 1 | ... Q39: =IF(isblank(Q$1),,IFERROR(vlookup($A39,indirect("'TVC-"&text(month(Q$1),"00")&"'!$A:$D"),4,false),1)) | R39: =index(A39:Q39,,month(today())+5)-index(A39:Q39,,month(today())+4) -> 0
A40: =IFERROR(__xludf.DUMMYFUNCTION("""COMPUTED_VALUE"""),207.0) -> 207 | B40: =IFERROR(__xludf.DUMMYFUNCTION("""COMPUTED_VALUE"""),"Browns, Cleveland") -> Browns, Cleveland | C40: =IFERROR(__xludf.DUMMYFUNCTION("""COMPUTED_VALUE"""),"TMRB") -> TMRB | D40: =IFERROR(__xludf.DUMMYFUNCTION("""COMPUTED_VALUE"""),"CLE") -> CLE | E40: =mid(B40,find(",",B40)+2,30)&" "&left(B40,find(",",B40)-1) -> Cleveland Browns | F40: =IF(isblank(F$1),,IF(isblank($A40),,IFERROR(vlookup($A40,indirect("'TVC-"&text(month(F$1),"00")&"'!$A:$D"),4,false),1))) -> 1 | G40: =IF(isblank(G$1),,IF(isblank($A40),,IFERROR(vlookup($A40,indirect("'TVC-"&text(month(G$1),"00")&"'!$A:$D"),4,false),1))) -> 1 | H40: =IF(isblank(H$1),,IFERROR(vlookup($A40,indirect("'TVC-"&text(month(H$1),"00")&"'!$A:$D"),4,false),1)) -> 1 | I40: =IF(isblank(I$1),,IFERROR(vlookup($A40,indirect("'TVC-"&text(month(I$1),"00")&"'!$A:$D"),4,false),1)) -> 1 | J40: =IF(isblank(J$1),,IFERROR(vlookup($A40,indirect("'TVC-"&text(month(J$1),"00")&"'!$A:$D"),4,false),1)) -> 1 | K40: =IF(isblank(K$1),,IFERROR(vlookup($A40,indirect("'TVC-"&text(month(K$1),"00")&"'!$A:$D"),4,false),1)) -> 1 | L40: =IF(isblank(L$1),,IFERROR(vlookup($A40,indirect("'TVC-"&text(month(L$1),"00")&"'!$A:$D"),4,false),1)) -> 1 | M40: =IF(isblank(M$1),,IFERROR(vlookup($A40,indirect("'TVC-"&text(month(M$1),"00")&"'!$A:$D"),4,false),1)) -> 1 | N40: =IF(isblank(N$1),,IFERROR(vlookup($A40,indirect("'TVC-"&text(month(N$1),"00")&"'!$A:$D"),4,false),1)) -> 1 | O40: =IF(isblank(O$1),,IFERROR(vlookup($A40,indirect("'TVC-"&text(month(O$1),"00")&"'!$A:$D"),4,false),1)) -> 1 | ... Q40: =IF(isblank(Q$1),,IFERROR(vlookup($A40,indirect("'TVC-"&text(month(Q$1),"00")&"'!$A:$D"),4,false),1)) | R40: =index(A40:Q40,,month(today())+5)-index(A40:Q40,,month(today())+4) -> 0
A41: =IFERROR(__xludf.DUMMYFUNCTION("""COMPUTED_VALUE"""),208.0) -> 208 | B41: =IFERROR(__xludf.DUMMYFUNCTION("""COMPUTED_VALUE"""),"Titans, Tennessee") -> Titans, Tennessee | C41: =IFERROR(__xludf.DUMMYFUNCTION("""COMPUTED_VALUE"""),"TMRB") -> TMRB | D41: =IFERROR(__xludf.DUMMYFUNCTION("""COMPUTED_VALUE"""),"TEN") -> TEN | E41: =mid(B41,find(",",B41)+2,30)&" "&left(B41,find(",",B41)-1) -> Tennessee Titans | F41: =IF(isblank(F$1),,IF(isblank($A41),,IFERROR(vlookup($A41,indirect("'TVC-"&text(month(F$1),"00")&"'!$A:$D"),4,false),1))) -> 1 | G41: =IF(isblank(G$1),,IF(isblank($A41),,IFERROR(vlookup($A41,indirect("'TVC-"&text(month(G$1),"00")&"'!$A:$D"),4,false),1))) -> 1 | H41: =IF(isblank(H$1),,IFERROR(vlookup($A41,indirect("'TVC-"&text(month(H$1),"00")&"'!$A:$D"),4,false),1)) -> 1 | I41: =IF(isblank(I$1),,IFERROR(vlookup($A41,indirect("'TVC-"&text(month(I$1),"00")&"'!$A:$D"),4,false),1)) -> 1 | J41: =IF(isblank(J$1),,IFERROR(vlookup($A41,indirect("'TVC-"&text(month(J$1),"00")&"'!$A:$D"),4,false),1)) -> 1 | K41: =IF(isblank(K$1),,IFERROR(vlookup($A41,indirect("'TVC-"&text(month(K$1),"00")&"'!$A:$D"),4,false),1)) -> 1 | L41: =IF(isblank(L$1),,IFERROR(vlookup($A41,indirect("'TVC-"&text(month(L$1),"00")&"'!$A:$D"),4,false),1)) -> 1 | M41: =IF(isblank(M$1),,IFERROR(vlookup($A41,indirect("'TVC-"&text(month(M$1),"00")&"'!$A:$D"),4,false),1)) -> 1 | N41: =IF(isblank(N$1),,IFERROR(vlookup($A41,indirect("'TVC-"&text(month(N$1),"00")&"'!$A:$D"),4,false),1)) -> 1 | O41: =IF(isblank(O$1),,IFERROR(vlookup($A41,indirect("'TVC-"&text(month(O$1),"00")&"'!$A:$D"),4,false),1)) -> 1 | ... Q41: =IF(isblank(Q$1),,IFERROR(vlookup($A41,indirect("'TVC-"&text(month(Q$1),"00")&"'!$A:$D"),4,false),1)) | R41: =index(A41:Q41,,month(today())+5)-index(A41:Q41,,month(today())+4) -> 0
A42: =IFERROR(__xludf.DUMMYFUNCTION("""COMPUTED_VALUE"""),209.0) -> 209 | B42: =IFERROR(__xludf.DUMMYFUNCTION("""COMPUTED_VALUE"""),"Jaguars, Jacksonville") -> Jaguars, Jacksonville | C42: =IFERROR(__xludf.DUMMYFUNCTION("""COMPUTED_VALUE"""),"TMRB") -> TMRB | D42: =IFERROR(__xludf.DUMMYFUNCTION("""COMPUTED_VALUE"""),"JAC") -> JAC | E42: =mid(B42,find(",",B42)+2,30)&" "&left(B42,find(",",B42)-1) -> Jacksonville Jaguars | F42: =IF(isblank(F$1),,IF(isblank($A42),,IFERROR(vlookup($A42,indirect("'TVC-"&text(month(F$1),"00")&"'!$A:$D"),4,false),1))) -> 1 | G42: =IF(isblank(G$1),,IF(isblank($A42),,IFERROR(vlookup($A42,indirect("'TVC-"&text(month(G$1),"00")&"'!$A:$D"),4,false),1))) -> 1 | H42: =IF(isblank(H$1),,IFERROR(vlookup($A42,indirect("'TVC-"&text(month(H$1),"00")&"'!$A:$D"),4,false),1)) -> 1 | I42: =IF(isblank(I$1),,IFERROR(vlookup($A42,indirect("'TVC-"&text(month(I$1),"00")&"'!$A:$D"),4,false),1)) -> 1 | J42: =IF(isblank(J$1),,IFERROR(vlookup($A42,indirect("'TVC-"&text(month(J$1),"00")&"'!$A:$D"),4,false),1)) -> 1 | K42: =IF(isblank(K$1),,IFERROR(vlookup($A42,indirect("'TVC-"&text(month(K$1),"00")&"'!$A:$D"),4,false),1)) -> 1 | L42: =IF(isblank(L$1),,IFERROR(vlookup($A42,indirect("'TVC-"&text(month(L$1),"00")&"'!$A:$D"),4,false),1)) -> 1 | M42: =IF(isblank(M$1),,IFERROR(vlookup($A42,indirect("'TVC-"&text(month(M$1),"00")&"'!$A:$D"),4,false),1)) -> 1 | N42: =IF(isblank(N$1),,IFERROR(vlookup($A42,indirect("'TVC-"&text(month(N$1),"00")&"'!$A:$D"),4,false),1)) -> 1 | O42: =IF(isblank(O$1),,IFERROR(vlookup($A42,indirect("'TVC-"&text(month(O$1),"00")&"'!$A:$D"),4,false),1)) -> 1 | ... Q42: =IF(isblank(Q$1),,IFERROR(vlookup($A42,indirect("'TVC-"&text(month(Q$1),"00")&"'!$A:$D"),4,false),1)) | R42: =index(A42:Q42,,month(today())+5)-index(A42:Q42,,month(today())+4) -> 0
A43: =IFERROR(__xludf.DUMMYFUNCTION("""COMPUTED_VALUE"""),210.0) -> 210 | B43: =IFERROR(__xludf.DUMMYFUNCTION("""COMPUTED_VALUE"""),"Steelers, Pittsburgh") -> Steelers, Pittsburgh | C43: =IFERROR(__xludf.DUMMYFUNCTION("""COMPUTED_VALUE"""),"TMRB") -> TMRB | D43: =IFERROR(__xludf.DUMMYFUNCTION("""COMPUTED_VALUE"""),"PIT") -> PIT | E43: =mid(B43,find(",",B43)+2,30)&" "&left(B43,find(",",B43)-1) -> Pittsburgh Steelers | F43: =IF(isblank(F$1),,IF(isblank($A43),,IFERROR(vlookup($A43,indirect("'TVC-"&text(month(F$1),"00")&"'!$A:$D"),4,false),1))) -> 1 | G43: =IF(isblank(G$1),,IF(isblank($A43),,IFERROR(vlookup($A43,indirect("'TVC-"&text(month(G$1),"00")&"'!$A:$D"),4,false),1))) -> 1 | H43: =IF(isblank(H$1),,IFERROR(vlookup($A43,indirect("'TVC-"&text(month(H$1),"00")&"'!$A:$D"),4,false),1)) -> 1 | I43: =IF(isblank(I$1),,IFERROR(vlookup($A43,indirect("'TVC-"&text(month(I$1),"00")&"'!$A:$D"),4,false),1)) -> 1 | J43: =IF(isblank(J$1),,IFERROR(vlookup($A43,indirect("'TVC-"&text(month(J$1),"00")&"'!$A:$D"),4,false),1)) -> 1 | K43: =IF(isblank(K$1),,IFERROR(vlookup($A43,indirect("'TVC-"&text(month(K$1),"00")&"'!$A:$D"),4,false),1)) -> 1 | L43: =IF(isblank(L$1),,IFERROR(vlookup($A43,indirect("'TVC-"&text(month(L$1),"00")&"'!$A:$D"),4,false),1)) -> 1 | M43: =IF(isblank(M$1),,IFERROR(vlookup($A43,indirect("'TVC-"&text(month(M$1),"00")&"'!$A:$D"),4,false),1)) -> 1 | N43: =IF(isblank(N$1),,IFERROR(vlookup($A43,indirect("'TVC-"&text(month(N$1),"00")&"'!$A:$D"),4,false),1)) -> 1 | O43: =IF(isblank(O$1),,IFERROR(vlookup($A43,indirect("'TVC-"&text(month(O$1),"00")&"'!$A:$D"),4,false),1)) -> 1 | ... Q43: =IF(isblank(Q$1),,IFERROR(vlookup($A43,indirect("'TVC-"&text(month(Q$1),"00")&"'!$A:$D"),4,false),1)) | R43: =index(A43:Q43,,month(today())+5)-index(A43:Q43,,month(today())+4) -> 0
A44: =IFERROR(__xludf.DUMMYFUNCTION("""COMPUTED_VALUE"""),211.0) -> 211 | B44: =IFERROR(__xludf.DUMMYFUNCTION("""COMPUTED_VALUE"""),"Broncos, Denver") -> Broncos, Denver | C44: =IFERROR(__xludf.DUMMYFUNCTION("""COMPUTED_VALUE"""),"TMRB") -> TMRB | D44: =IFERROR(__xludf.DUMMYFUNCTION("""COMPUTED_VALUE"""),"DEN") -> DEN | E44: =mid(B44,find(",",B44)+2,30)&" "&left(B44,find(",",B44)-1) -> Denver Broncos | F44: =IF(isblank(F$1),,IF(isblank($A44),,IFERROR(vlookup($A44,indirect("'TVC-"&text(month(F$1),"00")&"'!$A:$D"),4,false),1))) -> 1 | G44: =IF(isblank(G$1),,IF(isblank($A44),,IFERROR(vlookup($A44,indirect("'TVC-"&text(month(G$1),"00")&"'!$A:$D"),4,false),1))) -> 1 | H44: =IF(isblank(H$1),,IFERROR(vlookup($A44,indirect("'TVC-"&text(month(H$1),"00")&"'!$A:$D"),4,false),1)) -> 1 | I44: =IF(isblank(I$1),,IFERROR(vlookup($A44,indirect("'TVC-"&text(month(I$1),"00")&"'!$A:$D"),4,false),1)) -> 1 | J44: =IF(isblank(J$1),,IFERROR(vlookup($A44,indirect("'TVC-"&text(month(J$1),"00")&"'!$A:$D"),4,false),1)) -> 1 | K44: =IF(isblank(K$1),,IFERROR(vlookup($A44,indirect("'TVC-"&text(month(K$1),"00")&"'!$A:$D"),4,false),1)) -> 1 | L44: =IF(isblank(L$1),,IFERROR(vlookup($A44,indirect("'TVC-"&text(month(L$1),"00")&"'!$A:$D"),4,false),1)) -> 1 | M44: =IF(isblank(M$1),,IFERROR(vlookup($A44,indirect("'TVC-"&text(month(M$1),"00")&"'!$A:$D"),4,false),1)) -> 1 | N44: =IF(isblank(N$1),,IFERROR(vlookup($A44,indirect("'TVC-"&text(month(N$1),"00")&"'!$A:$D"),4,false),1)) -> 1 | O44: =IF(isblank(O$1),,IFERROR(vlookup($A44,indirect("'TVC-"&text(month(O$1),"00")&"'!$A:$D"),4,false),1)) -> 1 | ... Q44: =IF(isblank(Q$1),,IFERROR(vlookup($A44,indirect("'TVC-"&text(month(Q$1),"00")&"'!$A:$D"),4,false),1)) | R44: =index(A44:Q44,,month(today())+5)-index(A44:Q44,,month(today())+4) -> 0
A45: =IFERROR(__xludf.DUMMYFUNCTION("""COMPUTED_VALUE"""),212.0) -> 212 | B45: =IFERROR(__xludf.DUMMYFUNCTION("""COMPUTED_VALUE"""),"Chiefs, Kansas City") -> Chiefs, Kansas City | C45: =IFERROR(__xludf.DUMMYFUNCTION("""COMPUTED_VALUE"""),"TMRB") -> TMRB | D45: =IFERROR(__xludf.DUMMYFUNCTION("""COMPUTED_VALUE"""),"KCC") -> KCC | E45: =mid(B45,find(",",B45)+2,30)&" "&left(B45,find(",",B45)-1) -> Kansas City Chiefs | F45: =IF(isblank(F$1),,IF(isblank($A45),,IFERROR(vlookup($A45,indirect("'TVC-"&text(month(F$1),"00")&"'!$A:$D"),4,false),1))) -> 1 | G45: =IF(isblank(G$1),,IF(isblank($A45),,IFERROR(vlookup($A45,indirect("'TVC-"&text(month(G$1),"00")&"'!$A:$D"),4,false),1))) -> 1 | H45: =IF(isblank(H$1),,IFERROR(vlookup($A45,indirect("'TVC-"&text(month(H$1),"00")&"'!$A:$D"),4,false),1)) -> 1 | I45: =IF(isblank(I$1),,IFERROR(vlookup($A45,indirect("'TVC-"&text(month(I$1),"00")&"'!$A:$D"),4,false),1)) -> 1 | J45: =IF(isblank(J$1),,IFERROR(vlookup($A45,indirect("'TVC-"&text(month(J$1),"00")&"'!$A:$D"),4,false),1)) -> 1 | K45: =IF(isblank(K$1),,IFERROR(vlookup($A45,indirect("'TVC-"&text(month(K$1),"00")&"'!$A:$D"),4,false),1)) -> 1 | L45: =IF(isblank(L$1),,IFERROR(vlookup($A45,indirect("'TVC-"&text(month(L$1),"00")&"'!$A:$D"),4,false),1)) -> 1 | M45: =IF(isblank(M$1),,IFERROR(vlookup($A45,indirect("'TVC-"&text(month(M$1),"00")&"'!$A:$D"),4,false),1)) -> 1 | N45: =IF(isblank(N$1),,IFERROR(vlookup($A45,indirect("'TVC-"&text(month(N$1),"00")&"'!$A:$D"),4,false),1)) -> 1 | O45: =IF(isblank(O$1),,IFERROR(vlookup($A45,indirect("'TVC-"&text(month(O$1),"00")&"'!$A:$D"),4,false),1)) -> 1 | ... Q45: =IF(isblank(Q$1),,IFERROR(vlookup($A45,indirect("'TVC-"&text(month(Q$1),"00")&"'!$A:$D"),4,false),1)) | R45: =index(A45:Q45,,month(today())+5)-index(A45:Q45,,month(today())+4) -> 0
A46: =IFERROR(__xludf.DUMMYFUNCTION("""COMPUTED_VALUE"""),213.0) -> 213 | B46: =IFERROR(__xludf.DUMMYFUNCTION("""COMPUTED_VALUE"""),"Raiders, Las Vegas") -> Raiders, Las Vegas | C46: =IFERROR(__xludf.DUMMYFUNCTION("""COMPUTED_VALUE"""),"TMRB") -> TMRB | D46: =IFERROR(__xludf.DUMMYFUNCTION("""COMPUTED_VALUE"""),"LVR") -> LVR | E46: =mid(B46,find(",",B46)+2,30)&" "&left(B46,find(",",B46)-1) -> Las Vegas Raiders | F46: =IF(isblank(F$1),,IF(isblank($A46),,IFERROR(vlookup($A46,indirect("'TVC-"&text(month(F$1),"00")&"'!$A:$D"),4,false),1))) -> 1 | G46: =IF(isblank(G$1),,IF(isblank($A46),,IFERROR(vlookup($A46,indirect("'TVC-"&text(month(G$1),"00")&"'!$A:$D"),4,false),1))) -> 1 | H46: =IF(isblank(H$1),,IFERROR(vlookup($A46,indirect("'TVC-"&text(month(H$1),"00")&"'!$A:$D"),4,false),1)) -> 1 | I46: =IF(isblank(I$1),,IFERROR(vlookup($A46,indirect("'TVC-"&text(month(I$1),"00")&"'!$A:$D"),4,false),1)) -> 1 | J46: =IF(isblank(J$1),,IFERROR(vlookup($A46,indirect("'TVC-"&text(month(J$1),"00")&"'!$A:$D"),4,false),1)) -> 1 | K46: =IF(isblank(K$1),,IFERROR(vlookup($A46,indirect("'TVC-"&text(month(K$1),"00")&"'!$A:$D"),4,false),1)) -> 1 | L46: =IF(isblank(L$1),,IFERROR(vlookup($A46,indirect("'TVC-"&text(month(L$1),"00")&"'!$A:$D"),4,false),1)) -> 1 | M46: =IF(isblank(M$1),,IFERROR(vlookup($A46,indirect("'TVC-"&text(month(M$1),"00")&"'!$A:$D"),4,false),1)) -> 1 | N46: =IF(isblank(N$1),,IFERROR(vlookup($A46,indirect("'TVC-"&text(month(N$1),"00")&"'!$A:$D"),4,false),1)) -> 1 | O46: =IF(isblank(O$1),,IFERROR(vlookup($A46,indirect("'TVC-"&text(month(O$1),"00")&"'!$A:$D"),4,false),1)) -> 1 | ... Q46: =IF(isblank(Q$1),,IFERROR(vlookup($A46,indirect("'TVC-"&text(month(Q$1),"00")&"'!$A:$D"),4,false),1)) | R46: =index(A46:Q46,,month(today())+5)-index(A46:Q46,,month(today())+4) -> 0
A47: =IFERROR(__xludf.DUMMYFUNCTION("""COMPUTED_VALUE"""),214.0) -> 214 | B47: =IFERROR(__xludf.DUMMYFUNCTION("""COMPUTED_VALUE"""),"Chargers, Los Angeles") -> Chargers, Los Angeles | C47: =IFERROR(__xludf.DUMMYFUNCTION("""COMPUTED_VALUE"""),"TMRB") -> TMRB | D47: =IFERROR(__xludf.DUMMYFUNCTION("""COMPUTED_VALUE"""),"LAC") -> LAC | E47: =mid(B47,find(",",B47)+2,30)&" "&left(B47,find(",",B47)-1) -> Los Angeles Chargers | F47: =IF(isblank(F$1),,IF(isblank($A47),,IFERROR(vlookup($A47,indirect("'TVC-"&text(month(F$1),"00")&"'!$A:$D"),4,false),1))) -> 1 | G47: =IF(isblank(G$1),,IF(isblank($A47),,IFERROR(vlookup($A47,indirect("'TVC-"&text(month(G$1),"00")&"'!$A:$D"),4,false),1))) -> 1 | H47: =IF(isblank(H$1),,IFERROR(vlookup($A47,indirect("'TVC-"&text(month(H$1),"00")&"'!$A:$D"),4,false),1)) -> 1 | I47: =IF(isblank(I$1),,IFERROR(vlookup($A47,indirect("'TVC-"&text(month(I$1),"00")&"'!$A:$D"),4,false),1)) -> 1 | J47: =IF(isblank(J$1),,IFERROR(vlookup($A47,indirect("'TVC-"&text(month(J$1),"00")&"'!$A:$D"),4,false),1)) -> 1 | K47: =IF(isblank(K$1),,IFERROR(vlookup($A47,indirect("'TVC-"&text(month(K$1),"00")&"'!$A:$D"),4,false),1)) -> 1 | L47: =IF(isblank(L$1),,IFERROR(vlookup($A47,indirect("'TVC-"&text(month(L$1),"00")&"'!$A:$D"),4,false),1)) -> 1 | M47: =IF(isblank(M$1),,IFERROR(vlookup($A47,indirect("'TVC-"&text(month(M$1),"00")&"'!$A:$D"),4,false),1)) -> 1 | N47: =IF(isblank(N$1),,IFERROR(vlookup($A47,indirect("'TVC-"&text(month(N$1),"00")&"'!$A:$D"),4,false),1)) -> 1 | O47: =IF(isblank(O$1),,IFERROR(vlookup($A47,indirect("'TVC-"&text(month(O$1),"00")&"'!$A:$D"),4,false),1)) -> 1 | ... Q47: =IF(isblank(Q$1),,IFERROR(vlookup($A47,indirect("'TVC-"&text(month(Q$1),"00")&"'!$A:$D"),4,false),1)) | R47: =index(A47:Q47,,month(today())+5)-index(A47:Q47,,month(today())+4) -> 0
A48: =IFERROR(__xludf.DUMMYFUNCTION("""COMPUTED_VALUE"""),215.0) -> 215 | B48: =IFERROR(__xludf.DUMMYFUNCTION("""COMPUTED_VALUE"""),"Seahawks, Seattle") -> Seahawks, Seattle | C48: =IFERROR(__xludf.DUMMYFUNCTION("""COMPUTED_VALUE"""),"TMRB") -> TMRB | D48: =IFERROR(__xludf.DUMMYFUNCTION("""COMPUTED_VALUE"""),"SEA") -> SEA | E48: =mid(B48,find(",",B48)+2,30)&" "&left(B48,find(",",B48)-1) -> Seattle Seahawks | F48: =IF(isblank(F$1),,IF(isblank($A48),,IFERROR(vlookup($A48,indirect("'TVC-"&text(month(F$1),"00")&"'!$A:$D"),4,false),1))) -> 1 | G48: =IF(isblank(G$1),,IF(isblank($A48),,IFERROR(vlookup($A48,indirect("'TVC-"&text(month(G$1),"00")&"'!$A:$D"),4,false),1))) -> 1 | H48: =IF(isblank(H$1),,IFERROR(vlookup($A48,indirect("'TVC-"&text(month(H$1),"00")&"'!$A:$D"),4,false),1)) -> 1 | I48: =IF(isblank(I$1),,IFERROR(vlookup($A48,indirect("'TVC-"&text(month(I$1),"00")&"'!$A:$D"),4,false),1)) -> 1 | J48: =IF(isblank(J$1),,IFERROR(vlookup($A48,indirect("'TVC-"&text(month(J$1),"00")&"'!$A:$D"),4,false),1)) -> 1 | K48: =IF(isblank(K$1),,IFERROR(vlookup($A48,indirect("'TVC-"&text(month(K$1),"00")&"'!$A:$D"),4,false),1)) -> 1 | L48: =IF(isblank(L$1),,IFERROR(vlookup($A48,indirect("'TVC-"&text(month(L$1),"00")&"'!$A:$D"),4,false),1)) -> 1 | M48: =IF(isblank(M$1),,IFERROR(vlookup($A48,indirect("'TVC-"&text(month(M$1),"00")&"'!$A:$D"),4,false),1)) -> 1 | N48: =IF(isblank(N$1),,IFERROR(vlookup($A48,indirect("'TVC-"&text(month(N$1),"00")&"'!$A:$D"),4,false),1)) -> 1 | O48: =IF(isblank(O$1),,IFERROR(vlookup($A48,indirect("'TVC-"&text(month(O$1),"00")&"'!$A:$D"),4,false),1)) -> 1 | ... Q48: =IF(isblank(Q$1),,IFERROR(vlookup($A48,indirect("'TVC-"&text(month(Q$1),"00")&"'!$A:$D"),4,false),1)) | R48: =index(A48:Q48,,month(today())+5)-index(A48:Q48,,month(today())+4) -> 0
A49: =IFERROR(__xludf.DUMMYFUNCTION("""COMPUTED_VALUE"""),216.0) -> 216 | B49: =IFERROR(__xludf.DUMMYFUNCTION("""COMPUTED_VALUE"""),"Cowboys, Dallas") -> Cowboys, Dallas | C49: =IFERROR(__xludf.DUMMYFUNCTION("""COMPUTED_VALUE"""),"TMRB") -> TMRB | D49: =IFERROR(__xludf.DUMMYFUNCTION("""COMPUTED_VALUE"""),"DAL") -> DAL | E49: =mid(B49,find(",",B49)+2,30)&" "&left(B49,find(",",B49)-1) -> Dallas Cowboys | F49: =IF(isblank(F$1),,IF(isblank($A49),,IFERROR(vlookup($A49,indirect("'TVC-"&text(month(F$1),"00")&"'!$A:$D"),4,false),1))) -> 1 | G49: =IF(isblank(G$1),,IF(isblank($A49),,IFERROR(vlookup($A49,indirect("'TVC-"&text(month(G$1),"00")&"'!$A:$D"),4,false),1))) -> 1 | H49: =IF(isblank(H$1),,IFERROR(vlookup($A49,indirect("'TVC-"&text(month(H$1),"00")&"'!$A:$D"),4,false),1)) -> 1 | I49: =IF(isblank(I$1),,IFERROR(vlookup($A49,indirect("'TVC-"&text(month(I$1),"00")&"'!$A:$D"),4,false),1)) -> 1 | J49: =IF(isblank(J$1),,IFERROR(vlookup($A49,indirect("'TVC-"&text(month(J$1),"00")&"'!$A:$D"),4,false),1)) -> 1 | K49: =IF(isblank(K$1),,IFERROR(vlookup($A49,indirect("'TVC-"&text(month(K$1),"00")&"'!$A:$D"),4,false),1)) -> 1 | L49: =IF(isblank(L$1),,IFERROR(vlookup($A49,indirect("'TVC-"&text(month(L$1),"00")&"'!$A:$D"),4,false),1)) -> 1 | M49: =IF(isblank(M$1),,IFERROR(vlookup($A49,indirect("'TVC-"&text(month(M$1),"00")&"'!$A:$D"),4,false),1)) -> 1 | N49: =IF(isblank(N$1),,IFERROR(vlookup($A49,indirect("'TVC-"&text(month(N$1),"00")&"'!$A:$D"),4,false),1)) -> 1 | O49: =IF(isblank(O$1),,IFERROR(vlookup($A49,indirect("'TVC-"&text(month(O$1),"00")&"'!$A:$D"),4,false),1)) -> 1 | ... Q49: =IF(isblank(Q$1),,IFERROR(vlookup($A49,indirect("'TVC-"&text(month(Q$1),"00")&"'!$A:$D"),4,false),1)) | R49: =index(A49:Q49,,month(today())+5)-index(A49:Q49,,month(today())+4) -> 0
A50: =IFERROR(__xludf.DUMMYFUNCTION("""COMPUTED_VALUE"""),217.0) -> 217 | B50: =IFERROR(__xludf.DUMMYFUNCTION("""COMPUTED_VALUE"""),"Giants, New York") -> Giants, New York | C50: =IFERROR(__xludf.DUMMYFUNCTION("""COMPUTED_VALUE"""),"TMRB") -> TMRB | D50: =IFERROR(__xludf.DUMMYFUNCTION("""COMPUTED_VALUE"""),"NYG") -> NYG | E50: =mid(B50,find(",",B50)+2,30)&" "&left(B50,find(",",B50)-1) -> New York Giants | F50: =IF(isblank(F$1),,IF(isblank($A50),,IFERROR(vlookup($A50,indirect("'TVC-"&text(month(F$1),"00")&"'!$A:$D"),4,false),1))) -> 1 | G50: =IF(isblank(G$1),,IF(isblank($A50),,IFERROR(vlookup($A50,indirect("'TVC-"&text(month(G$1),"00")&"'!$A:$D"),4,false),1))) -> 1 | H50: =IF(isblank(H$1),,IFERROR(vlookup($A50,indirect("'TVC-"&text(month(H$1),"00")&"'!$A:$D"),4,false),1)) -> 1 | I50: =IF(isblank(I$1),,IFERROR(vlookup($A50,indirect("'TVC-"&text(month(I$1),"00")&"'!$A:$D"),4,false),1)) -> 1 | J50: =IF(isblank(J$1),,IFERROR(vlookup($A50,indirect("'TVC-"&text(month(J$1),"00")&"'!$A:$D"),4,false),1)) -> 1 | K50: =IF(isblank(K$1),,IFERROR(vlookup($A50,indirect("'TVC-"&text(month(K$1),"00")&"'!$A:$D"),4,false),1)) -> 1 | L50: =IF(isblank(L$1),,IFERROR(vlookup($A50,indirect("'TVC-"&text(month(L$1),"00")&"'!$A:$D"),4,false),1)) -> 1 | M50: =IF(isblank(M$1),,IFERROR(vlookup($A50,indirect("'TVC-"&text(month(M$1),"00")&"'!$A:$D"),4,false),1)) -> 1 | N50: =IF(isblank(N$1),,IFERROR(vlookup($A50,indirect("'TVC-"&text(month(N$1),"00")&"'!$A:$D"),4,false),1)) -> 1 | O50: =IF(isblank(O$1),,IFERROR(vlookup($A50,indirect("'TVC-"&text(month(O$1),"00")&"'!$A:$D"),4,false),1)) -> 1 | ... Q50: =IF(isblank(Q$1),,IFERROR(vlookup($A50,indirect("'TVC-"&text(month(Q$1),"00")&"'!$A:$D"),4,false),1)) | R50: =index(A50:Q50,,month(today())+5)-index(A50:Q50,,month(today())+4) -> 0
A51: =IFERROR(__xludf.DUMMYFUNCTION("""COMPUTED_VALUE"""),218.0) -> 218 | B51: =IFERROR(__xludf.DUMMYFUNCTION("""COMPUTED_VALUE"""),"Eagles, Philadelphia") -> Eagles, Philadelphia | C51: =IFERROR(__xludf.DUMMYFUNCTION("""COMPUTED_VALUE"""),"TMRB") -> TMRB | D51: =IFERROR(__xludf.DUMMYFUNCTION("""COMPUTED_VALUE"""),"PHI") -> PHI | E51: =mid(B51,find(",",B51)+2,30)&" "&left(B51,find(",",B51)-1) -> Philadelphia Eagles | F51: =IF(isblank(F$1),,IF(isblank($A51),,IFERROR(vlookup($A51,indirect("'TVC-"&text(month(F$1),"00")&"'!$A:$D"),4,false),1))) -> 1 | G51: =IF(isblank(G$1),,IF(isblank($A51),,IFERROR(vlookup($A51,indirect("'TVC-"&text(month(G$1),"00")&"'!$A:$D"),4,false),1))) -> 1 | H51: =IF(isblank(H$1),,IFERROR(vlookup($A51,indirect("'TVC-"&text(month(H$1),"00")&"'!$A:$D"),4,false),1)) -> 1 | I51: =IF(isblank(I$1),,IFERROR(vlookup($A51,indirect("'TVC-"&text(month(I$1),"00")&"'!$A:$D"),4,false),1)) -> 1 | J51: =IF(isblank(J$1),,IFERROR(vlookup($A51,indirect("'TVC-"&text(month(J$1),"00")&"'!$A:$D"),4,false),1)) -> 1 | K51: =IF(isblank(K$1),,IFERROR(vlookup($A51,indirect("'TVC-"&text(month(K$1),"00")&"'!$A:$D"),4,false),1)) -> 1 | L51: =IF(isblank(L$1),,IFERROR(vlookup($A51,indirect("'TVC-"&text(month(L$1),"00")&"'!$A:$D"),4,false),1)) -> 1 | M51: =IF(isblank(M$1),,IFERROR(vlookup($A51,indirect("'TVC-"&text(month(M$1),"00")&"'!$A:$D"),4,false),1)) -> 1 | N51: =IF(isblank(N$1),,IFERROR(vlookup($A51,indirect("'TVC-"&text(month(N$1),"00")&"'!$A:$D"),4,false),1)) -> 1 | O51: =IF(isblank(O$1),,IFERROR(vlookup($A51,indirect("'TVC-"&text(month(O$1),"00")&"'!$A:$D"),4,false),1)) -> 1 | ... Q51: =IF(isblank(Q$1),,IFERROR(vlookup($A51,indirect("'TVC-"&text(month(Q$1),"00")&"'!$A:$D"),4,false),1)) | R51: =index(A51:Q51,,month(today())+5)-index(A51:Q51,,month(today())+4) -> 0
A52: =IFERROR(__xludf.DUMMYFUNCTION("""COMPUTED_VALUE"""),219.0) -> 219 | B52: =IFERROR(__xludf.DUMMYFUNCTION("""COMPUTED_VALUE"""),"Cardinals, Arizona") -> Cardinals, Arizona | C52: =IFERROR(__xludf.DUMMYFUNCTION("""COMPUTED_VALUE"""),"TMRB") -> TMRB | D52: =IFERROR(__xludf.DUMMYFUNCTION("""COMPUTED_VALUE"""),"ARI") -> ARI | E52: =mid(B52,find(",",B52)+2,30)&" "&left(B52,find(",",B52)-1) -> Arizona Cardinals | F52: =IF(isblank(F$1),,IF(isblank($A52),,IFERROR(vlookup($A52,indirect("'TVC-"&text(month(F$1),"00")&"'!$A:$D"),4,false),1))) -> 1 | G52: =IF(isblank(G$1),,IF(isblank($A52),,IFERROR(vlookup($A52,indirect("'TVC-"&text(month(G$1),"00")&"'!$A:$D"),4,false),1))) -> 1 | H52: =IF(isblank(H$1),,IFERROR(vlookup($A52,indirect("'TVC-"&text(month(H$1),"00")&"'!$A:$D"),4,false),1)) -> 1 | I52: =IF(isblank(I$1),,IFERROR(vlookup($A52,indirect("'TVC-"&text(month(I$1),"00")&"'!$A:$D"),4,false),1)) -> 1 | J52: =IF(isblank(J$1),,IFERROR(vlookup($A52,indirect("'TVC-"&text(month(J$1),"00")&"'!$A:$D"),4,false),1)) -> 1 | K52: =IF(isblank(K$1),,IFERROR(vlookup($A52,indirect("'TVC-"&text(month(K$1),"00")&"'!$A:$D"),4,false),1)) -> 1 | L52: =IF(isblank(L$1),,IFERROR(vlookup($A52,indirect("'TVC-"&text(month(L$1),"00")&"'!$A:$D"),4,false),1)) -> 1 | M52: =IF(isblank(M$1),,IFERROR(vlookup($A52,indirect("'TVC-"&text(month(M$1),"00")&"'!$A:$D"),4,false),1)) -> 1 | N52: =IF(isblank(N$1),,IFERROR(vlookup($A52,indirect("'TVC-"&text(month(N$1),"00")&"'!$A:$D"),4,false),1)) -> 1 | O52: =IF(isblank(O$1),,IFERROR(vlookup($A52,indirect("'TVC-"&text(month(O$1),"00")&"'!$A:$D"),4,false),1)) -> 1 | ... Q52: =IF(isblank(Q$1),,IFERROR(vlookup($A52,indirect("'TVC-"&text(month(Q$1),"00")&"'!$A:$D"),4,false),1)) | R52: =index(A52:Q52,,month(today())+5)-index(A52:Q52,,month(today())+4) -> 0
A53: =IFERROR(__xludf.DUMMYFUNCTION("""COMPUTED_VALUE"""),220.0) -> 220 | B53: =IFERROR(__xludf.DUMMYFUNCTION("""COMPUTED_VALUE"""),"Commanders, Washington") -> Commanders, Washington | C53: =IFERROR(__xludf.DUMMYFUNCTION("""COMPUTED_VALUE"""),"TMRB") -> TMRB | D53: =IFERROR(__xludf.DUMMYFUNCTION("""COMPUTED_VALUE"""),"WAS") -> WAS | E53: =mid(B53,find(",",B53)+2,30)&" "&left(B53,find(",",B53)-1) -> Washington Commanders | F53: =IF(isblank(F$1),,IF(isblank($A53),,IFERROR(vlookup($A53,indirect("'TVC-"&text(month(F$1),"00")&"'!$A:$D"),4,false),1))) -> 1 | G53: =IF(isblank(G$1),,IF(isblank($A53),,IFERROR(vlookup($A53,indirect("'TVC-"&text(month(G$1),"00")&"'!$A:$D"),4,false),1))) -> 1 | H53: =IF(isblank(H$1),,IFERROR(vlookup($A53,indirect("'TVC-"&text(month(H$1),"00")&"'!$A:$D"),4,false),1)) -> 1 | I53: =IF(isblank(I$1),,IFERROR(vlookup($A53,indirect("'TVC-"&text(month(I$1),"00")&"'!$A:$D"),4,false),1)) -> 1 | J53: =IF(isblank(J$1),,IFERROR(vlookup($A53,indirect("'TVC-"&text(month(J$1),"00")&"'!$A:$D"),4,false),1)) -> 1 | K53: =IF(isblank(K$1),,IFERROR(vlookup($A53,indirect("'TVC-"&text(month(K$1),"00")&"'!$A:$D"),4,false),1)) -> 1 | L53: =IF(isblank(L$1),,IFERROR(vlookup($A53,indirect("'TVC-"&text(month(L$1),"00")&"'!$A:$D"),4,false),1)) -> 1 | M53: =IF(isblank(M$1),,IFERROR(vlookup($A53,indirect("'TVC-"&text(month(M$1),"00")&"'!$A:$D"),4,false),1)) -> 1 | N53: =IF(isblank(N$1),,IFERROR(vlookup($A53,indirect("'TVC-"&text(month(N$1),"00")&"'!$A:$D"),4,false),1)) -> 1 | O53: =IF(isblank(O$1),,IFERROR(vlookup($A53,indirect("'TVC-"&text(month(O$1),"00")&"'!$A:$D"),4,false),1)) -> 1 | ... Q53: =IF(isblank(Q$1),,IFERROR(vlookup($A53,indirect("'TVC-"&text(month(Q$1),"00")&"'!$A:$D"),4,false),1)) | R53: =index(A53:Q53,,month(today())+5)-index(A53:Q53,,month(today())+4) -> 0
A54: =IFERROR(__xludf.DUMMYFUNCTION("""COMPUTED_VALUE"""),221.0) -> 221 | B54: =IFERROR(__xludf.DUMMYFUNCTION("""COMPUTED_VALUE"""),"Bears, Chicago") -> Bears, Chicago | C54: =IFERROR(__xludf.DUMMYFUNCTION("""COMPUTED_VALUE"""),"TMRB") -> TMRB | D54: =IFERROR(__xludf.DUMMYFUNCTION("""COMPUTED_VALUE"""),"CHI") -> CHI | E54: =mid(B54,find(",",B54)+2,30)&" "&left(B54,find(",",B54)-1) -> Chicago Bears | F54: =IF(isblank(F$1),,IF(isblank($A54),,IFERROR(vlookup($A54,indirect("'TVC-"&text(month(F$1),"00")&"'!$A:$D"),4,false),1))) -> 1 | G54: =IF(isblank(G$1),,IF(isblank($A54),,IFERROR(vlookup($A54,indirect("'TVC-"&text(month(G$1),"00")&"'!$A:$D"),4,false),1))) -> 1 | H54: =IF(isblank(H$1),,IFERROR(vlookup($A54,indirect("'TVC-"&text(month(H$1),"00")&"'!$A:$D"),4,false),1)) -> 1 | I54: =IF(isblank(I$1),,IFERROR(vlookup($A54,indirect("'TVC-"&text(month(I$1),"00")&"'!$A:$D"),4,false),1)) -> 1 | J54: =IF(isblank(J$1),,IFERROR(vlookup($A54,indirect("'TVC-"&text(month(J$1),"00")&"'!$A:$D"),4,false),1)) -> 1 | K54: =IF(isblank(K$1),,IFERROR(vlookup($A54,indirect("'TVC-"&text(month(K$1),"00")&"'!$A:$D"),4,false),1)) -> 1 | L54: =IF(isblank(L$1),,IFERROR(vlookup($A54,indirect("'TVC-"&text(month(L$1),"00")&"'!$A:$D"),4,false),1)) -> 1 | M54: =IF(isblank(M$1),,IFERROR(vlookup($A54,indirect("'TVC-"&text(month(M$1),"00")&"'!$A:$D"),4,false),1)) -> 1 | N54: =IF(isblank(N$1),,IFERROR(vlookup($A54,indirect("'TVC-"&text(month(N$1),"00")&"'!$A:$D"),4,false),1)) -> 1 | O54: =IF(isblank(O$1),,IFERROR(vlookup($A54,indirect("'TVC-"&text(month(O$1),"00")&"'!$A:$D"),4,false),1)) -> 1 | ... Q54: =IF(isblank(Q$1),,IFERROR(vlookup($A54,indirect("'TVC-"&text(month(Q$1),"00")&"'!$A:$D"),4,false),1)) | R54: =index(A54:Q54,,month(today())+5)-index(A54:Q54,,month(today())+4) -> 0
A55: =IFERROR(__xludf.DUMMYFUNCTION("""COMPUTED_VALUE"""),222.0) -> 222 | B55: =IFERROR(__xludf.DUMMYFUNCTION("""COMPUTED_VALUE"""),"Lions, Detroit") -> Lions, Detroit | C55: =IFERROR(__xludf.DUMMYFUNCTION("""COMPUTED_VALUE"""),"TMRB") -> TMRB | D55: =IFERROR(__xludf.DUMMYFUNCTION("""COMPUTED_VALUE"""),"DET") -> DET | E55: =mid(B55,find(",",B55)+2,30)&" "&left(B55,find(",",B55)-1) -> Detroit Lions | F55: =IF(isblank(F$1),,IF(isblank($A55),,IFERROR(vlookup($A55,indirect("'TVC-"&text(month(F$1),"00")&"'!$A:$D"),4,false),1))) -> 1 | G55: =IF(isblank(G$1),,IF(isblank($A55),,IFERROR(vlookup($A55,indirect("'TVC-"&text(month(G$1),"00")&"'!$A:$D"),4,false),1))) -> 1 | H55: =IF(isblank(H$1),,IFERROR(vlookup($A55,indirect("'TVC-"&text(month(H$1),"00")&"'!$A:$D"),4,false),1)) -> 1 | I55: =IF(isblank(I$1),,IFERROR(vlookup($A55,indirect("'TVC-"&text(month(I$1),"00")&"'!$A:$D"),4,false),1)) -> 1 | J55: =IF(isblank(J$1),,IFERROR(vlookup($A55,indirect("'TVC-"&text(month(J$1),"00")&"'!$A:$D"),4,false),1)) -> 1 | K55: =IF(isblank(K$1),,IFERROR(vlookup($A55,indirect("'TVC-"&text(month(K$1),"00")&"'!$A:$D"),4,false),1)) -> 1 | L55: =IF(isblank(L$1),,IFERROR(vlookup($A55,indirect("'TVC-"&text(month(L$1),"00")&"'!$A:$D"),4,false),1)) -> 1 | M55: =IF(isblank(M$1),,IFERROR(vlookup($A55,indirect("'TVC-"&text(month(M$1),"00")&"'!$A:$D"),4,false),1)) -> 1 | N55: =IF(isblank(N$1),,IFERROR(vlookup($A55,indirect("'TVC-"&text(month(N$1),"00")&"'!$A:$D"),4,false),1)) -> 1 | O55: =IF(isblank(O$1),,IFERROR(vlookup($A55,indirect("'TVC-"&text(month(O$1),"00")&"'!$A:$D"),4,false),1)) -> 1 | ... Q55: =IF(isblank(Q$1),,IFERROR(vlookup($A55,indirect("'TVC-"&text(month(Q$1),"00")&"'!$A:$D"),4,false),1)) | R55: =index(A55:Q55,,month(today())+5)-index(A55:Q55,,month(today())+4) -> 0
A56: =IFERROR(__xludf.DUMMYFUNCTION("""COMPUTED_VALUE"""),223.0) -> 223 | B56: =IFERROR(__xludf.DUMMYFUNCTION("""COMPUTED_VALUE"""),"Packers, Green Bay") -> Packers, Green Bay | C56: =IFERROR(__xludf.DUMMYFUNCTION("""COMPUTED_VALUE"""),"TMRB") -> TMRB | D56: =IFERROR(__xludf.DUMMYFUNCTION("""COMPUTED_VALUE"""),"GBP") -> GBP | E56: =mid(B56,find(",",B56)+2,30)&" "&left(B56,find(",",B56)-1) -> Green Bay Packers | F56: =IF(isblank(F$1),,IF(isblank($A56),,IFERROR(vlookup($A56,indirect("'TVC-"&text(month(F$1),"00")&"'!$A:$D"),4,false),1))) -> 1 | G56: =IF(isblank(G$1),,IF(isblank($A56),,IFERROR(vlookup($A56,indirect("'TVC-"&text(month(G$1),"00")&"'!$A:$D"),4,false),1))) -> 1 | H56: =IF(isblank(H$1),,IFERROR(vlookup($A56,indirect("'TVC-"&text(month(H$1),"00")&"'!$A:$D"),4,false),1)) -> 1 | I56: =IF(isblank(I$1),,IFERROR(vlookup($A56,indirect("'TVC-"&text(month(I$1),"00")&"'!$A:$D"),4,false),1)) -> 1 | J56: =IF(isblank(J$1),,IFERROR(vlookup($A56,indirect("'TVC-"&text(month(J$1),"00")&"'!$A:$D"),4,false),1)) -> 1 | K56: =IF(isblank(K$1),,IFERROR(vlookup($A56,indirect("'TVC-"&text(month(K$1),"00")&"'!$A:$D"),4,false),1)) -> 1 | L56: =IF(isblank(L$1),,IFERROR(vlookup($A56,indirect("'TVC-"&text(month(L$1),"00")&"'!$A:$D"),4,false),1)) -> 1 | M56: =IF(isblank(M$1),,IFERROR(vlookup($A56,indirect("'TVC-"&text(month(M$1),"00")&"'!$A:$D"),4,false),1)) -> 1 | N56: =IF(isblank(N$1),,IFERROR(vlookup($A56,indirect("'TVC-"&text(month(N$1),"00")&"'!$A:$D"),4,false),1)) -> 1 | O56: =IF(isblank(O$1),,IFERROR(vlookup($A56,indirect("'TVC-"&text(month(O$1),"00")&"'!$A:$D"),4,false),1)) -> 1 | ... Q56: =IF(isblank(Q$1),,IFERROR(vlookup($A56,indirect("'TVC-"&text(month(Q$1),"00")&"'!$A:$D"),4,false),1)) | R56: =index(A56:Q56,,month(today())+5)-index(A56:Q56,,month(today())+4) -> 0
A57: =IFERROR(__xludf.DUMMYFUNCTION("""COMPUTED_VALUE"""),224.0) -> 224 | B57: =IFERROR(__xludf.DUMMYFUNCTION("""COMPUTED_VALUE"""),"Vikings, Minnesota") -> Vikings, Minnesota | C57: =IFERROR(__xludf.DUMMYFUNCTION("""COMPUTED_VALUE"""),"TMRB") -> TMRB | D57: =IFERROR(__xludf.DUMMYFUNCTION("""COMPUTED_VALUE"""),"MIN") -> MIN | E57: =mid(B57,find(",",B57)+2,30)&" "&left(B57,find(",",B57)-1) -> Minnesota Vikings | F57: =IF(isblank(F$1),,IF(isblank($A57),,IFERROR(vlookup($A57,indirect("'TVC-"&text(month(F$1),"00")&"'!$A:$D"),4,false),1))) -> 1 | G57: =IF(isblank(G$1),,IF(isblank($A57),,IFERROR(vlookup($A57,indirect("'TVC-"&text(month(G$1),"00")&"'!$A:$D"),4,false),1))) -> 1 | H57: =IF(isblank(H$1),,IFERROR(vlookup($A57,indirect("'TVC-"&text(month(H$1),"00")&"'!$A:$D"),4,false),1)) -> 1 | I57: =IF(isblank(I$1),,IFERROR(vlookup($A57,indirect("'TVC-"&text(month(I$1),"00")&"'!$A:$D"),4,false),1)) -> 1 | J57: =IF(isblank(J$1),,IFERROR(vlookup($A57,indirect("'TVC-"&text(month(J$1),"00")&"'!$A:$D"),4,false),1)) -> 1 | K57: =IF(isblank(K$1),,IFERROR(vlookup($A57,indirect("'TVC-"&text(month(K$1),"00")&"'!$A:$D"),4,false),1)) -> 1 | L57: =IF(isblank(L$1),,IFERROR(vlookup($A57,indirect("'TVC-"&text(month(L$1),"00")&"'!$A:$D"),4,false),1)) -> 1 | M57: =IF(isblank(M$1),,IFERROR(vlookup($A57,indirect("'TVC-"&text(month(M$1),"00")&"'!$A:$D"),4,false),1)) -> 1 | N57: =IF(isblank(N$1),,IFERROR(vlookup($A57,indirect("'TVC-"&text(month(N$1),"00")&"'!$A:$D"),4,false),1)) -> 1 | O57: =IF(isblank(O$1),,IFERROR(vlookup($A57,indirect("'TVC-"&text(month(O$1),"00")&"'!$A:$D"),4,false),1)) -> 1 | ... Q57: =IF(isblank(Q$1),,IFERROR(vlookup($A57,indirect("'TVC-"&text(month(Q$1),"00")&"'!$A:$D"),4,false),1)) | R57: =index(A57:Q57,,month(today())+5)-index(A57:Q57,,month(today())+4) -> 0
A58: =IFERROR(__xludf.DUMMYFUNCTION("""COMPUTED_VALUE"""),225.0) -> 225 | B58: =IFERROR(__xludf.DUMMYFUNCTION("""COMPUTED_VALUE"""),"Buccaneers, Tampa Bay") -> Buccaneers, Tampa Bay | C58: =IFERROR(__xludf.DUMMYFUNCTION("""COMPUTED_VALUE"""),"TMRB") -> TMRB | D58: =IFERROR(__xludf.DUMMYFUNCTION("""COMPUTED_VALUE"""),"TBB") -> TBB | E58: =mid(B58,find(",",B58)+2,30)&" "&left(B58,find(",",B58)-1) -> Tampa Bay Buccaneers | F58: =IF(isblank(F$1),,IF(isblank($A58),,IFERROR(vlookup($A58,indirect("'TVC-"&text(month(F$1),"00")&"'!$A:$D"),4,false),1))) -> 1 | G58: =IF(isblank(G$1),,IF(isblank($A58),,IFERROR(vlookup($A58,indirect("'TVC-"&text(month(G$1),"00")&"'!$A:$D"),4,false),1))) -> 1 | H58: =IF(isblank(H$1),,IFERROR(vlookup($A58,indirect("'TVC-"&text(month(H$1),"00")&"'!$A:$D"),4,false),1)) -> 1 | I58: =IF(isblank(I$1),,IFERROR(vlookup($A58,indirect("'TVC-"&text(month(I$1),"00")&"'!$A:$D"),4,false),1)) -> 1 | J58: =IF(isblank(J$1),,IFERROR(vlookup($A58,indirect("'TVC-"&text(month(J$1),"00")&"'!$A:$D"),4,false),1)) -> 1 | K58: =IF(isblank(K$1),,IFERROR(vlookup($A58,indirect("'TVC-"&text(month(K$1),"00")&"'!$A:$D"),4,false),1)) -> 1 | L58: =IF(isblank(L$1),,IFERROR(vlookup($A58,indirect("'TVC-"&text(month(L$1),"00")&"'!$A:$D"),4,false),1)) -> 1 | M58: =IF(isblank(M$1),,IFERROR(vlookup($A58,indirect("'TVC-"&text(month(M$1),"00")&"'!$A:$D"),4,false),1)) -> 1 | N58: =IF(isblank(N$1),,IFERROR(vlookup($A58,indirect("'TVC-"&text(month(N$1),"00")&"'!$A:$D"),4,false),1)) -> 1 | O58: =IF(isblank(O$1),,IFERROR(vlookup($A58,indirect("'TVC-"&text(month(O$1),"00")&"'!$A:$D"),4,false),1)) -> 1 | ... Q58: =IF(isblank(Q$1),,IFERROR(vlookup($A58,indirect("'TVC-"&text(month(Q$1),"00")&"'!$A:$D"),4,false),1)) | R58: =index(A58:Q58,,month(today())+5)-index(A58:Q58,,month(today())+4) -> 0
A59: =IFERROR(__xludf.DUMMYFUNCTION("""COMPUTED_VALUE"""),226.0) -> 226 | B59: =IFERROR(__xludf.DUMMYFUNCTION("""COMPUTED_VALUE"""),"Falcons, Atlanta") -> Falcons, Atlanta | C59: =IFERROR(__xludf.DUMMYFUNCTION("""COMPUTED_VALUE"""),"TMRB") -> TMRB | D59: =IFERROR(__xludf.DUMMYFUNCTION("""COMPUTED_VALUE"""),"ATL") -> ATL | E59: =mid(B59,find(",",B59)+2,30)&" "&left(B59,find(",",B59)-1) -> Atlanta Falcons | F59: =IF(isblank(F$1),,IF(isblank($A59),,IFERROR(vlookup($A59,indirect("'TVC-"&text(month(F$1),"00")&"'!$A:$D"),4,false),1))) -> 1 | G59: =IF(isblank(G$1),,IF(isblank($A59),,IFERROR(vlookup($A59,indirect("'TVC-"&text(month(G$1),"00")&"'!$A:$D"),4,false),1))) -> 1 | H59: =IF(isblank(H$1),,IFERROR(vlookup($A59,indirect("'TVC-"&text(month(H$1),"00")&"'!$A:$D"),4,false),1)) -> 1 | I59: =IF(isblank(I$1),,IFERROR(vlookup($A59,indirect("'TVC-"&text(month(I$1),"00")&"'!$A:$D"),4,false),1)) -> 1 | J59: =IF(isblank(J$1),,IFERROR(vlookup($A59,indirect("'TVC-"&text(month(J$1),"00")&"'!$A:$D"),4,false),1)) -> 1 | K59: =IF(isblank(K$1),,IFERROR(vlookup($A59,indirect("'TVC-"&text(month(K$1),"00")&"'!$A:$D"),4,false),1)) -> 1 | L59: =IF(isblank(L$1),,IFERROR(vlookup($A59,indirect("'TVC-"&text(month(L$1),"00")&"'!$A:$D"),4,false),1)) -> 1 | M59: =IF(isblank(M$1),,IFERROR(vlookup($A59,indirect("'TVC-"&text(month(M$1),"00")&"'!$A:$D"),4,false),1)) -> 1 | N59: =IF(isblank(N$1),,IFERROR(vlookup($A59,indirect("'TVC-"&text(month(N$1),"00")&"'!$A:$D"),4,false),1)) -> 1 | O59: =IF(isblank(O$1),,IFERROR(vlookup($A59,indirect("'TVC-"&text(month(O$1),"00")&"'!$A:$D"),4,false),1)) -> 1 | ... Q59: =IF(isblank(Q$1),,IFERROR(vlookup($A59,indirect("'TVC-"&text(month(Q$1),"00")&"'!$A:$D"),4,false),1)) | R59: =index(A59:Q59,,month(today())+5)-index(A59:Q59,,month(today())+4) -> 0
A60: =IFERROR(__xludf.DUMMYFUNCTION("""COMPUTED_VALUE"""),227.0) -> 227 | B60: =IFERROR(__xludf.DUMMYFUNCTION("""COMPUTED_VALUE"""),"Panthers, Carolina") -> Panthers, Carolina | C60: =IFERROR(__xludf.DUMMYFUNCTION("""COMPUTED_VALUE"""),"TMRB") -> TMRB | D60: =IFERROR(__xludf.DUMMYFUNCTION("""COMPUTED_VALUE"""),"CAR") -> CAR | E60: =mid(B60,find(",",B60)+2,30)&" "&left(B60,find(",",B60)-1) -> Carolina Panthers | F60: =IF(isblank(F$1),,IF(isblank($A60),,IFERROR(vlookup($A60,indirect("'TVC-"&text(month(F$1),"00")&"'!$A:$D"),4,false),1))) -> 1 | G60: =IF(isblank(G$1),,IF(isblank($A60),,IFERROR(vlookup($A60,indirect("'TVC-"&text(month(G$1),"00")&"'!$A:$D"),4,false),1))) -> 1 | H60: =IF(isblank(H$1),,IFERROR(vlookup($A60,indirect("'TVC-"&text(month(H$1),"00")&"'!$A:$D"),4,false),1)) -> 1 | I60: =IF(isblank(I$1),,IFERROR(vlookup($A60,indirect("'TVC-"&text(month(I$1),"00")&"'!$A:$D"),4,false),1)) -> 1 | J60: =IF(isblank(J$1),,IFERROR(vlookup($A60,indirect("'TVC-"&text(month(J$1),"00")&"'!$A:$D"),4,false),1)) -> 1 | K60: =IF(isblank(K$1),,IFERROR(vlookup($A60,indirect("'TVC-"&text(month(K$1),"00")&"'!$A:$D"),4,false),1)) -> 1 | L60: =IF(isblank(L$1),,IFERROR(vlookup($A60,indirect("'TVC-"&text(month(L$1),"00")&"'!$A:$D"),4,false),1)) -> 1 | M60: =IF(isblank(M$1),,IFERROR(vlookup($A60,indirect("'TVC-"&text(month(M$1),"00")&"'!$A:$D"),4,false),1)) -> 1 | N60: =IF(isblank(N$1),,IFERROR(vlookup($A60,indirect("'TVC-"&text(month(N$1),"00")&"'!$A:$D"),4,false),1)) -> 1 | O60: =IF(isblank(O$1),,IFERROR(vlookup($A60,indirect("'TVC-"&text(month(O$1),"00")&"'!$A:$D"),4,false),1)) -> 1 | ... Q60: =IF(isblank(Q$1),,IFERROR(vlookup($A60,indirect("'TVC-"&text(month(Q$1),"00")&"'!$A:$D"),4,false),1)) | R60: =index(A60:Q60,,month(today())+5)-index(A60:Q60,,month(today())+4) -> 0
A61: =IFERROR(__xludf.DUMMYFUNCTION("""COMPUTED_VALUE"""),228.0) -> 228 | B61: =IFERROR(__xludf.DUMMYFUNCTION("""COMPUTED_VALUE"""),"Rams, Los Angeles") -> Rams, Los Angeles | C61: =IFERROR(__xludf.DUMMYFUNCTION("""COMPUTED_VALUE"""),"TMRB") -> TMRB | D61: =IFERROR(__xludf.DUMMYFUNCTION("""COMPUTED_VALUE"""),"LAR") -> LAR | E61: =mid(B61,find(",",B61)+2,30)&" "&left(B61,find(",",B61)-1) -> Los Angeles Rams | F61: =IF(isblank(F$1),,IF(isblank($A61),,IFERROR(vlookup($A61,indirect("'TVC-"&text(month(F$1),"00")&"'!$A:$D"),4,false),1))) -> 1 | G61: =IF(isblank(G$1),,IF(isblank($A61),,IFERROR(vlookup($A61,indirect("'TVC-"&text(month(G$1),"00")&"'!$A:$D"),4,false),1))) -> 1 | H61: =IF(isblank(H$1),,IFERROR(vlookup($A61,indirect("'TVC-"&text(month(H$1),"00")&"'!$A:$D"),4,false),1)) -> 1 | I61: =IF(isblank(I$1),,IFERROR(vlookup($A61,indirect("'TVC-"&text(month(I$1),"00")&"'!$A:$D"),4,false),1)) -> 1 | J61: =IF(isblank(J$1),,IFERROR(vlookup($A61,indirect("'TVC-"&text(month(J$1),"00")&"'!$A:$D"),4,false),1)) -> 1 | K61: =IF(isblank(K$1),,IFERROR(vlookup($A61,indirect("'TVC-"&text(month(K$1),"00")&"'!$A:$D"),4,false),1)) -> 1 | L61: =IF(isblank(L$1),,IFERROR(vlookup($A61,indirect("'TVC-"&text(month(L$1),"00")&"'!$A:$D"),4,false),1)) -> 1 | M61: =IF(isblank(M$1),,IFERROR(vlookup($A61,indirect("'TVC-"&text(month(M$1),"00")&"'!$A:$D"),4,false),1)) -> 1 | N61: =IF(isblank(N$1),,IFERROR(vlookup($A61,indirect("'TVC-"&text(month(N$1),"00")&"'!$A:$D"),4,false),1)) -> 1 | O61: =IF(isblank(O$1),,IFERROR(vlookup($A61,indirect("'TVC-"&text(month(O$1),"00")&"'!$A:$D"),4,false),1)) -> 1 | ... Q61: =IF(isblank(Q$1),,IFERROR(vlookup($A61,indirect("'TVC-"&text(month(Q$1),"00")&"'!$A:$D"),4,false),1)) | R61: =index(A61:Q61,,month(today())+5)-index(A61:Q61,,month(today())+4) -> 0
A62: =IFERROR(__xludf.DUMMYFUNCTION("""COMPUTED_VALUE"""),229.0) -> 229 | B62: =IFERROR(__xludf.DUMMYFUNCTION("""COMPUTED_VALUE"""),"Saints, New Orleans") -> Saints, New Orleans | C62: =IFERROR(__xludf.DUMMYFUNCTION("""COMPUTED_VALUE"""),"TMRB") -> TMRB | D62: =IFERROR(__xludf.DUMMYFUNCTION("""COMPUTED_VALUE"""),"NOS") -> NOS | E62: =mid(B62,find(",",B62)+2,30)&" "&left(B62,find(",",B62)-1) -> New Orleans Saints | F62: =IF(isblank(F$1),,IF(isblank($A62),,IFERROR(vlookup($A62,indirect("'TVC-"&text(month(F$1),"00")&"'!$A:$D"),4,false),1))) -> 1 | G62: =IF(isblank(G$1),,IF(isblank($A62),,IFERROR(vlookup($A62,indirect("'TVC-"&text(month(G$1),"00")&"'!$A:$D"),4,false),1))) -> 1 | H62: =IF(isblank(H$1),,IFERROR(vlookup($A62,indirect("'TVC-"&text(month(H$1),"00")&"'!$A:$D"),4,false),1)) -> 1 | I62: =IF(isblank(I$1),,IFERROR(vlookup($A62,indirect("'TVC-"&text(month(I$1),"00")&"'!$A:$D"),4,false),1)) -> 1 | J62: =IF(isblank(J$1),,IFERROR(vlookup($A62,indirect("'TVC-"&text(month(J$1),"00")&"'!$A:$D"),4,false),1)) -> 1 | K62: =IF(isblank(K$1),,IFERROR(vlookup($A62,indirect("'TVC-"&text(month(K$1),"00")&"'!$A:$D"),4,false),1)) -> 1 | L62: =IF(isblank(L$1),,IFERROR(vlookup($A62,indirect("'TVC-"&text(month(L$1),"00")&"'!$A:$D"),4,false),1)) -> 1 | M62: =IF(isblank(M$1),,IFERROR(vlookup($A62,indirect("'TVC-"&text(month(M$1),"00")&"'!$A:$D"),4,false),1)) -> 1 | N62: =IF(isblank(N$1),,IFERROR(vlookup($A62,indirect("'TVC-"&text(month(N$1),"00")&"'!$A:$D"),4,false),1)) -> 1 | O62: =IF(isblank(O$1),,IFERROR(vlookup($A62,indirect("'TVC-"&text(month(O$1),"00")&"'!$A:$D"),4,false),1)) -> 1 | ... Q62: =IF(isblank(Q$1),,IFERROR(vlookup($A62,indirect("'TVC-"&text(month(Q$1),"00")&"'!$A:$D"),4,false),1)) | R62: =index(A62:Q62,,month(today())+5)-index(A62:Q62,,month(today())+4) -> 0
A63: =IFERROR(__xludf.DUMMYFUNCTION("""COMPUTED_VALUE"""),230.0) -> 230 | B63: =IFERROR(__xludf.DUMMYFUNCTION("""COMPUTED_VALUE"""),"49ers, San Francisco") -> 49ers, San Francisco | C63: =IFERROR(__xludf.DUMMYFUNCTION("""COMPUTED_VALUE"""),"TMRB") -> TMRB | D63: =IFERROR(__xludf.DUMMYFUNCTION("""COMPUTED_VALUE"""),"SFO") -> SFO | E63: =mid(B63,find(",",B63)+2,30)&" "&left(B63,find(",",B63)-1) -> San Francisco 49ers | F63: =IF(isblank(F$1),,IF(isblank($A63),,IFERROR(vlookup($A63,indirect("'TVC-"&text(month(F$1),"00")&"'!$A:$D"),4,false),1))) -> 1 | G63: =IF(isblank(G$1),,IF(isblank($A63),,IFERROR(vlookup($A63,indirect("'TVC-"&text(month(G$1),"00")&"'!$A:$D"),4,false),1))) -> 1 | H63: =IF(isblank(H$1),,IFERROR(vlookup($A63,indirect("'TVC-"&text(month(H$1),"00")&"'!$A:$D"),4,false),1)) -> 1 | I63: =IF(isblank(I$1),,IFERROR(vlookup($A63,indirect("'TVC-"&text(month(I$1),"00")&"'!$A:$D"),4,false),1)) -> 1 | J63: =IF(isblank(J$1),,IFERROR(vlookup($A63,indirect("'TVC-"&text(month(J$1),"00")&"'!$A:$D"),4,false),1)) -> 1 | K63: =IF(isblank(K$1),,IFERROR(vlookup($A63,indirect("'TVC-"&text(month(K$1),"00")&"'!$A:$D"),4,false),1)) -> 1 | L63: =IF(isblank(L$1),,IFERROR(vlookup($A63,indirect("'TVC-"&text(month(L$1),"00")&"'!$A:$D"),4,false),1)) -> 1 | M63: =IF(isblank(M$1),,IFERROR(vlookup($A63,indirect("'TVC-"&text(month(M$1),"00")&"'!$A:$D"),4,false),1)) -> 1 | N63: =IF(isblank(N$1),,IFERROR(vlookup($A63,indirect("'TVC-"&text(month(N$1),"00")&"'!$A:$D"),4,false),1)) -> 1 | O63: =IF(isblank(O$1),,IFERROR(vlookup($A63,indirect("'TVC-"&text(month(O$1),"00")&"'!$A:$D"),4,false),1)) -> 1 | ... Q63: =IF(isblank(Q$1),,IFERROR(vlookup($A63,indirect("'TVC-"&text(month(Q$1),"00")&"'!$A:$D"),4,false),1)) | R63: =index(A63:Q63,,month(today())+5)-index(A63:Q63,,month(today())+4) -> 0
A64: =IFERROR(__xludf.DUMMYFUNCTION("""COMPUTED_VALUE"""),231.0) -> 231 | B64: =IFERROR(__xludf.DUMMYFUNCTION("""COMPUTED_VALUE"""),"Ravens, Baltimore") -> Ravens, Baltimore | C64: =IFERROR(__xludf.DUMMYFUNCTION("""COMPUTED_VALUE"""),"TMRB") -> TMRB | D64: =IFERROR(__xludf.DUMMYFUNCTION("""COMPUTED_VALUE"""),"BAL") -> BAL | E64: =mid(B64,find(",",B64)+2,30)&" "&left(B64,find(",",B64)-1) -> Baltimore Ravens | F64: =IF(isblank(F$1),,IF(isblank($A64),,IFERROR(vlookup($A64,indirect("'TVC-"&text(month(F$1),"00")&"'!$A:$D"),4,false),1))) -> 1 | G64: =IF(isblank(G$1),,IF(isblank($A64),,IFERROR(vlookup($A64,indirect("'TVC-"&text(month(G$1),"00")&"'!$A:$D"),4,false),1))) -> 1 | H64: =IF(isblank(H$1),,IFERROR(vlookup($A64,indirect("'TVC-"&text(month(H$1),"00")&"'!$A:$D"),4,false),1)) -> 1 | I64: =IF(isblank(I$1),,IFERROR(vlookup($A64,indirect("'TVC-"&text(month(I$1),"00")&"'!$A:$D"),4,false),1)) -> 1 | J64: =IF(isblank(J$1),,IFERROR(vlookup($A64,indirect("'TVC-"&text(month(J$1),"00")&"'!$A:$D"),4,false),1)) -> 1 | K64: =IF(isblank(K$1),,IFERROR(vlookup($A64,indirect("'TVC-"&text(month(K$1),"00")&"'!$A:$D"),4,false),1)) -> 1 | L64: =IF(isblank(L$1),,IFERROR(vlookup($A64,indirect("'TVC-"&text(month(L$1),"00")&"'!$A:$D"),4,false),1)) -> 1 | M64: =IF(isblank(M$1),,IFERROR(vlookup($A64,indirect("'TVC-"&text(month(M$1),"00")&"'!$A:$D"),4,false),1)) -> 1 | N64: =IF(isblank(N$1),,IFERROR(vlookup($A64,indirect("'TVC-"&text(month(N$1),"00")&"'!$A:$D"),4,false),1)) -> 1 | O64: =IF(isblank(O$1),,IFERROR(vlookup($A64,indirect("'TVC-"&text(month(O$1),"00")&"'!$A:$D"),4,false),1)) -> 1 | ... Q64: =IF(isblank(Q$1),,IFERROR(vlookup($A64,indirect("'TVC-"&text(month(Q$1),"00")&"'!$A:$D"),4,false),1)) | R64: =index(A64:Q64,,month(today())+5)-index(A64:Q64,,month(today())+4) -> 0
A65: =IFERROR(__xludf.DUMMYFUNCTION("""COMPUTED_VALUE"""),232.0) -> 232 | B65: =IFERROR(__xludf.DUMMYFUNCTION("""COMPUTED_VALUE"""),"Texans, Houston") -> Texans, Houston | C65: =IFERROR(__xludf.DUMMYFUNCTION("""COMPUTED_VALUE"""),"TMRB") -> TMRB | D65: =IFERROR(__xludf.DUMMYFUNCTION("""COMPUTED_VALUE"""),"HOU") -> HOU | E65: =mid(B65,find(",",B65)+2,30)&" "&left(B65,find(",",B65)-1) -> Houston Texans | F65: =IF(isblank(F$1),,IF(isblank($A65),,IFERROR(vlookup($A65,indirect("'TVC-"&text(month(F$1),"00")&"'!$A:$D"),4,false),1))) -> 1 | G65: =IF(isblank(G$1),,IF(isblank($A65),,IFERROR(vlookup($A65,indirect("'TVC-"&text(month(G$1),"00")&"'!$A:$D"),4,false),1))) -> 1 | H65: =IF(isblank(H$1),,IFERROR(vlookup($A65,indirect("'TVC-"&text(month(H$1),"00")&"'!$A:$D"),4,false),1)) -> 1 | I65: =IF(isblank(I$1),,IFERROR(vlookup($A65,indirect("'TVC-"&text(month(I$1),"00")&"'!$A:$D"),4,false),1)) -> 1 | J65: =IF(isblank(J$1),,IFERROR(vlookup($A65,indirect("'TVC-"&text(month(J$1),"00")&"'!$A:$D"),4,false),1)) -> 1 | K65: =IF(isblank(K$1),,IFERROR(vlookup($A65,indirect("'TVC-"&text(month(K$1),"00")&"'!$A:$D"),4,false),1)) -> 1 | L65: =IF(isblank(L$1),,IFERROR(vlookup($A65,indirect("'TVC-"&text(month(L$1),"00")&"'!$A:$D"),4,false),1)) -> 1 | M65: =IF(isblank(M$1),,IFERROR(vlookup($A65,indirect("'TVC-"&text(month(M$1),"00")&"'!$A:$D"),4,false),1)) -> 1 | N65: =IF(isblank(N$1),,IFERROR(vlookup($A65,indirect("'TVC-"&text(month(N$1),"00")&"'!$A:$D"),4,false),1)) -> 1 | O65: =IF(isblank(O$1),,IFERROR(vlookup($A65,indirect("'TVC-"&text(month(O$1),"00")&"'!$A:$D"),4,false),1)) -> 1 | ... Q65: =IF(isblank(Q$1),,IFERROR(vlookup($A65,indirect("'TVC-"&text(month(Q$1),"00")&"'!$A:$D"),4,false),1)) | R65: =index(A65:Q65,,month(today())+5)-index(A65:Q65,,month(today())+4) -> 0
A66: =IFERROR(__xludf.DUMMYFUNCTION("""COMPUTED_VALUE"""),251.0) -> 251 | B66: =IFERROR(__xludf.DUMMYFUNCTION("""COMPUTED_VALUE"""),"Bills, Buffalo") -> Bills, Buffalo | C66: =IFERROR(__xludf.DUMMYFUNCTION("""COMPUTED_VALUE"""),"TMDL") -> TMDL | D66: =IFERROR(__xludf.DUMMYFUNCTION("""COMPUTED_VALUE"""),"BUF") -> BUF | E66: =mid(B66,find(",",B66)+2,30)&" "&left(B66,find(",",B66)-1) -> Buffalo Bills | F66: =IF(isblank(F$1),,IF(isblank($A66),,IFERROR(vlookup($A66,indirect("'TVC-"&text(month(F$1),"00")&"'!$A:$D"),4,false),1))) -> 1 | G66: =IF(isblank(G$1),,IF(isblank($A66),,IFERROR(vlookup($A66,indirect("'TVC-"&text(month(G$1),"00")&"'!$A:$D"),4,false),1))) -> 1 | H66: =IF(isblank(H$1),,IFERROR(vlookup($A66,indirect("'TVC-"&text(month(H$1),"00")&"'!$A:$D"),4,false),1)) -> 1 | I66: =IF(isblank(I$1),,IFERROR(vlookup($A66,indirect("'TVC-"&text(month(I$1),"00")&"'!$A:$D"),4,false),1)) -> 1 | J66: =IF(isblank(J$1),,IFERROR(vlookup($A66,indirect("'TVC-"&text(month(J$1),"00")&"'!$A:$D"),4,false),1)) -> 1 | K66: =IF(isblank(K$1),,IFERROR(vlookup($A66,indirect("'TVC-"&text(month(K$1),"00")&"'!$A:$D"),4,false),1)) -> 1 | L66: =IF(isblank(L$1),,IFERROR(vlookup($A66,indirect("'TVC-"&text(month(L$1),"00")&"'!$A:$D"),4,false),1)) -> 1 | M66: =IF(isblank(M$1),,IFERROR(vlookup($A66,indirect("'TVC-"&text(month(M$1),"00")&"'!$A:$D"),4,false),1)) -> 1 | N66: =IF(isblank(N$1),,IFERROR(vlookup($A66,indirect("'TVC-"&text(month(N$1),"00")&"'!$A:$D"),4,false),1)) -> 1 | O66: =IF(isblank(O$1),,IFERROR(vlookup($A66,indirect("'TVC-"&text(month(O$1),"00")&"'!$A:$D"),4,false),1)) -> 1 | ... Q66: =IF(isblank(Q$1),,IFERROR(vlookup($A66,indirect("'TVC-"&text(month(Q$1),"00")&"'!$A:$D"),4,false),1)) | R66: =index(A66:Q66,,month(today())+5)-index(A66:Q66,,month(today())+4) -> 0
A67: =IFERROR(__xludf.DUMMYFUNCTION("""COMPUTED_VALUE"""),252.0) -> 252 | B67: =IFERROR(__xludf.DUMMYFUNCTION("""COMPUTED_VALUE"""),"Colts, Indianapolis") -> Colts, Indianapolis | C67: =IFERROR(__xludf.DUMMYFUNCTION("""COMPUTED_VALUE"""),"TMDL") -> TMDL | D67: =IFERROR(__xludf.DUMMYFUNCTION("""COMPUTED_VALUE"""),"IND") -> IND | E67: =mid(B67,find(",",B67)+2,30)&" "&left(B67,find(",",B67)-1) -> Indianapolis Colts | F67: =IF(isblank(F$1),,IF(isblank($A67),,IFERROR(vlookup($A67,indirect("'TVC-"&text(month(F$1),"00")&"'!$A:$D"),4,false),1))) -> 1 | G67: =IF(isblank(G$1),,IF(isblank($A67),,IFERROR(vlookup($A67,indirect("'TVC-"&text(month(G$1),"00")&"'!$A:$D"),4,false),1))) -> 1 | H67: =IF(isblank(H$1),,IFERROR(vlookup($A67,indirect("'TVC-"&text(month(H$1),"00")&"'!$A:$D"),4,false),1)) -> 1 | I67: =IF(isblank(I$1),,IFERROR(vlookup($A67,indirect("'TVC-"&text(month(I$1),"00")&"'!$A:$D"),4,false),1)) -> 1 | J67: =IF(isblank(J$1),,IFERROR(vlookup($A67,indirect("'TVC-"&text(month(J$1),"00")&"'!$A:$D"),4,false),1)) -> 1 | K67: =IF(isblank(K$1),,IFERROR(vlookup($A67,indirect("'TVC-"&text(month(K$1),"00")&"'!$A:$D"),4,false),1)) -> 1 | L67: =IF(isblank(L$1),,IFERROR(vlookup($A67,indirect("'TVC-"&text(month(L$1),"00")&"'!$A:$D"),4,false),1)) -> 1 | M67: =IF(isblank(M$1),,IFERROR(vlookup($A67,indirect("'TVC-"&text(month(M$1),"00")&"'!$A:$D"),4,false),1)) -> 1 | N67: =IF(isblank(N$1),,IFERROR(vlookup($A67,indirect("'TVC-"&text(month(N$1),"00")&"'!$A:$D"),4,false),1)) -> 1 | O67: =IF(isblank(O$1),,IFERROR(vlookup($A67,indirect("'TVC-"&text(month(O$1),"00")&"'!$A:$D"),4,false),1)) -> 1 | ... Q67: =IF(isblank(Q$1),,IFERROR(vlookup($A67,indirect("'TVC-"&text(month(Q$1),"00")&"'!$A:$D"),4,false),1)) | R67: =index(A67:Q67,,month(today())+5)-index(A67:Q67,,month(today())+4) -> 0
A68: =IFERROR(__xludf.DUMMYFUNCTION("""COMPUTED_VALUE"""),253.0) -> 253 | B68: =IFERROR(__xludf.DUMMYFUNCTION("""COMPUTED_VALUE"""),"Dolphins, Miami") -> Dolphins, Miami | C68: =IFERROR(__xludf.DUMMYFUNCTION("""COMPUTED_VALUE"""),"TMDL") -> TMDL | D68: =IFERROR(__xludf.DUMMYFUNCTION("""COMPUTED_VALUE"""),"MIA") -> MIA | E68: =mid(B68,find(",",B68)+2,30)&" "&left(B68,find(",",B68)-1) -> Miami Dolphins | F68: =IF(isblank(F$1),,IF(isblank($A68),,IFERROR(vlookup($A68,indirect("'TVC-"&text(month(F$1),"00")&"'!$A:$D"),4,false),1))) -> 1 | G68: =IF(isblank(G$1),,IF(isblank($A68),,IFERROR(vlookup($A68,indirect("'TVC-"&text(month(G$1),"00")&"'!$A:$D"),4,false),1))) -> 1 | H68: =IF(isblank(H$1),,IFERROR(vlookup($A68,indirect("'TVC-"&text(month(H$1),"00")&"'!$A:$D"),4,false),1)) -> 1 | I68: =IF(isblank(I$1),,IFERROR(vlookup($A68,indirect("'TVC-"&text(month(I$1),"00")&"'!$A:$D"),4,false),1)) -> 1 | J68: =IF(isblank(J$1),,IFERROR(vlookup($A68,indirect("'TVC-"&text(month(J$1),"00")&"'!$A:$D"),4,false),1)) -> 1 | K68: =IF(isblank(K$1),,IFERROR(vlookup($A68,indirect("'TVC-"&text(month(K$1),"00")&"'!$A:$D"),4,false),1)) -> 1 | L68: =IF(isblank(L$1),,IFERROR(vlookup($A68,indirect("'TVC-"&text(month(L$1),"00")&"'!$A:$D"),4,false),1)) -> 1 | M68: =IF(isblank(M$1),,IFERROR(vlookup($A68,indirect("'TVC-"&text(month(M$1),"00")&"'!$A:$D"),4,false),1)) -> 1 | N68: =IF(isblank(N$1),,IFERROR(vlookup($A68,indirect("'TVC-"&text(month(N$1),"00")&"'!$A:$D"),4,false),1)) -> 1 | O68: =IF(isblank(O$1),,IFERROR(vlookup($A68,indirect("'TVC-"&text(month(O$1),"00")&"'!$A:$D"),4,false),1)) -> 1 | ... Q68: =IF(isblank(Q$1),,IFERROR(vlookup($A68,indirect("'TVC-"&text(month(Q$1),"00")&"'!$A:$D"),4,false),1)) | R68: =index(A68:Q68,,month(today())+5)-index(A68:Q68,,month(today())+4) -> 0
A69: =IFERROR(__xludf.DUMMYFUNCTION("""COMPUTED_VALUE"""),254.0) -> 254 | B69: =IFERROR(__xludf.DUMMYFUNCTION("""COMPUTED_VALUE"""),"Patriots, New England") -> Patriots, New England | C69: =IFERROR(__xludf.DUMMYFUNCTION("""COMPUTED_VALUE"""),"TMDL") -> TMDL | D69: =IFERROR(__xludf.DUMMYFUNCTION("""COMPUTED_VALUE"""),"NEP") -> NEP | E69: =mid(B69,find(",",B69)+2,30)&" "&left(B69,find(",",B69)-1) -> New England Patriots | F69: =IF(isblank(F$1),,IF(isblank($A69),,IFERROR(vlookup($A69,indirect("'TVC-"&text(month(F$1),"00")&"'!$A:$D"),4,false),1))) -> 1 | G69: =IF(isblank(G$1),,IF(isblank($A69),,IFERROR(vlookup($A69,indirect("'TVC-"&text(month(G$1),"00")&"'!$A:$D"),4,false),1))) -> 1 | H69: =IF(isblank(H$1),,IFERROR(vlookup($A69,indirect("'TVC-"&text(month(H$1),"00")&"'!$A:$D"),4,false),1)) -> 1 | I69: =IF(isblank(I$1),,IFERROR(vlookup($A69,indirect("'TVC-"&text(month(I$1),"00")&"'!$A:$D"),4,false),1)) -> 1 | J69: =IF(isblank(J$1),,IFERROR(vlookup($A69,indirect("'TVC-"&text(month(J$1),"00")&"'!$A:$D"),4,false),1)) -> 1 | K69: =IF(isblank(K$1),,IFERROR(vlookup($A69,indirect("'TVC-"&text(month(K$1),"00")&"'!$A:$D"),4,false),1)) -> 1 | L69: =IF(isblank(L$1),,IFERROR(vlookup($A69,indirect("'TVC-"&text(month(L$1),"00")&"'!$A:$D"),4,false),1)) -> 1 | M69: =IF(isblank(M$1),,IFERROR(vlookup($A69,indirect("'TVC-"&text(month(M$1),"00")&"'!$A:$D"),4,false),1)) -> 1 | N69: =IF(isblank(N$1),,IFERROR(vlookup($A69,indirect("'TVC-"&text(month(N$1),"00")&"'!$A:$D"),4,false),1)) -> 1 | O69: =IF(isblank(O$1),,IFERROR(vlookup($A69,indirect("'TVC-"&text(month(O$1),"00")&"'!$A:$D"),4,false),1)) -> 1 | ... Q69: =IF(isblank(Q$1),,IFERROR(vlookup($A69,indirect("'TVC-"&text(month(Q$1),"00")&"'!$A:$D"),4,false),1)) | R69: =index(A69:Q69,,month(today())+5)-index(A69:Q69,,month(today())+4) -> 0
A70: =IFERROR(__xludf.DUMMYFUNCTION("""COMPUTED_VALUE"""),255.0) -> 255 | B70: =IFERROR(__xludf.DUMMYFUNCTION("""COMPUTED_VALUE"""),"Jets, New York") -> Jets, New York | C70: =IFERROR(__xludf.DUMMYFUNCTION("""COMPUTED_VALUE"""),"TMDL") -> TMDL | D70: =IFERROR(__xludf.DUMMYFUNCTION("""COMPUTED_VALUE"""),"NYJ") -> NYJ | E70: =mid(B70,find(",",B70)+2,30)&" "&left(B70,find(",",B70)-1) -> New York Jets | F70: =IF(isblank(F$1),,IF(isblank($A70),,IFERROR(vlookup($A70,indirect("'TVC-"&text(month(F$1),"00")&"'!$A:$D"),4,false),1))) -> 1 | G70: =IF(isblank(G$1),,IF(isblank($A70),,IFERROR(vlookup($A70,indirect("'TVC-"&text(month(G$1),"00")&"'!$A:$D"),4,false),1))) -> 1 | H70: =IF(isblank(H$1),,IFERROR(vlookup($A70,indirect("'TVC-"&text(month(H$1),"00")&"'!$A:$D"),4,false),1)) -> 1 | I70: =IF(isblank(I$1),,IFERROR(vlookup($A70,indirect("'TVC-"&text(month(I$1),"00")&"'!$A:$D"),4,false),1)) -> 1 | J70: =IF(isblank(J$1),,IFERROR(vlookup($A70,indirect("'TVC-"&text(month(J$1),"00")&"'!$A:$D"),4,false),1)) -> 1 | K70: =IF(isblank(K$1),,IFERROR(vlookup($A70,indirect("'TVC-"&text(month(K$1),"00")&"'!$A:$D"),4,false),1)) -> 1 | L70: =IF(isblank(L$1),,IFERROR(vlookup($A70,indirect("'TVC-"&text(month(L$1),"00")&"'!$A:$D"),4,false),1)) -> 1 | M70: =IF(isblank(M$1),,IFERROR(vlookup($A70,indirect("'TVC-"&text(month(M$1),"00")&"'!$A:$D"),4,false),1)) -> 1 | N70: =IF(isblank(N$1),,IFERROR(vlookup($A70,indirect("'TVC-"&text(month(N$1),"00")&"'!$A:$D"),4,false),1)) -> 1 | O70: =IF(isblank(O$1),,IFERROR(vlookup($A70,indirect("'TVC-"&text(month(O$1),"00")&"'!$A:$D"),4,false),1)) -> 1 | ... Q70: =IF(isblank(Q$1),,IFERROR(vlookup($A70,indirect("'TVC-"&text(month(Q$1),"00")&"'!$A:$D"),4,false),1)) | R70: =index(A70:Q70,,month(today())+5)-index(A70:Q70,,month(today())+4) -> 0
A71: =IFERROR(__xludf.DUMMYFUNCTION("""COMPUTED_VALUE"""),256.0) -> 256 | B71: =IFERROR(__xludf.DUMMYFUNCTION("""COMPUTED_VALUE"""),"Bengals, Cincinnati") -> Bengals, Cincinnati | C71: =IFERROR(__xludf.DUMMYFUNCTION("""COMPUTED_VALUE"""),"TMDL") -> TMDL | D71: =IFERROR(__xludf.DUMMYFUNCTION("""COMPUTED_VALUE"""),"CIN") -> CIN | E71: =mid(B71,find(",",B71)+2,30)&" "&left(B71,find(",",B71)-1) -> Cincinnati Bengals | F71: =IF(isblank(F$1),,IF(isblank($A71),,IFERROR(vlookup($A71,indirect("'TVC-"&text(month(F$1),"00")&"'!$A:$D"),4,false),1))) -> 1 | G71: =IF(isblank(G$1),,IF(isblank($A71),,IFERROR(vlookup($A71,indirect("'TVC-"&text(month(G$1),"00")&"'!$A:$D"),4,false),1))) -> 1 | H71: =IF(isblank(H$1),,IFERROR(vlookup($A71,indirect("'TVC-"&text(month(H$1),"00")&"'!$A:$D"),4,false),1)) -> 1 | I71: =IF(isblank(I$1),,IFERROR(vlookup($A71,indirect("'TVC-"&text(month(I$1),"00")&"'!$A:$D"),4,false),1)) -> 1 | J71: =IF(isblank(J$1),,IFERROR(vlookup($A71,indirect("'TVC-"&text(month(J$1),"00")&"'!$A:$D"),4,false),1)) -> 1 | K71: =IF(isblank(K$1),,IFERROR(vlookup($A71,indirect("'TVC-"&text(month(K$1),"00")&"'!$A:$D"),4,false),1)) -> 1 | L71: =IF(isblank(L$1),,IFERROR(vlookup($A71,indirect("'TVC-"&text(month(L$1),"00")&"'!$A:$D"),4,false),1)) -> 1 | M71: =IF(isblank(M$1),,IFERROR(vlookup($A71,indirect("'TVC-"&text(month(M$1),"00")&"'!$A:$D"),4,false),1)) -> 1 | N71: =IF(isblank(N$1),,IFERROR(vlookup($A71,indirect("'TVC-"&text(month(N$1),"00")&"'!$A:$D"),4,false),1)) -> 1 | O71: =IF(isblank(O$1),,IFERROR(vlookup($A71,indirect("'TVC-"&text(month(O$1),"00")&"'!$A:$D"),4,false),1)) -> 1 | ... Q71: =IF(isblank(Q$1),,IFERROR(vlookup($A71,indirect("'TVC-"&text(month(Q$1),"00")&"'!$A:$D"),4,false),1)) | R71: =index(A71:Q71,,month(today())+5)-index(A71:Q71,,month(today())+4) -> 0
A72: =IFERROR(__xludf.DUMMYFUNCTION("""COMPUTED_VALUE"""),257.0) -> 257 | B72: =IFERROR(__xludf.DUMMYFUNCTION("""COMPUTED_VALUE"""),"Browns, Cleveland") -> Browns, Cleveland | C72: =IFERROR(__xludf.DUMMYFUNCTION("""COMPUTED_VALUE"""),"TMDL") -> TMDL | D72: =IFERROR(__xludf.DUMMYFUNCTION("""COMPUTED_VALUE"""),"CLE") -> CLE | E72: =mid(B72,find(",",B72)+2,30)&" "&left(B72,find(",",B72)-1) -> Cleveland Browns | F72: =IF(isblank(F$1),,IF(isblank($A72),,IFERROR(vlookup($A72,indirect("'TVC-"&text(month(F$1),"00")&"'!$A:$D"),4,false),1))) -> 1 | G72: =IF(isblank(G$1),,IF(isblank($A72),,IFERROR(vlookup($A72,indirect("'TVC-"&text(month(G$1),"00")&"'!$A:$D"),4,false),1))) -> 1 | H72: =IF(isblank(H$1),,IFERROR(vlookup($A72,indirect("'TVC-"&text(month(H$1),"00")&"'!$A:$D"),4,false),1)) -> 1 | I72: =IF(isblank(I$1),,IFERROR(vlookup($A72,indirect("'TVC-"&text(month(I$1),"00")&"'!$A:$D"),4,false),1)) -> 1 | J72: =IF(isblank(J$1),,IFERROR(vlookup($A72,indirect("'TVC-"&text(month(J$1),"00")&"'!$A:$D"),4,false),1)) -> 1 | K72: =IF(isblank(K$1),,IFERROR(vlookup($A72,indirect("'TVC-"&text(month(K$1),"00")&"'!$A:$D"),4,false),1)) -> 1 | L72: =IF(isblank(L$1),,IFERROR(vlookup($A72,indirect("'TVC-"&text(month(L$1),"00")&"'!$A:$D"),4,false),1)) -> 1 | M72: =IF(isblank(M$1),,IFERROR(vlookup($A72,indirect("'TVC-"&text(month(M$1),"00")&"'!$A:$D"),4,false),1)) -> 1 | N72: =IF(isblank(N$1),,IFERROR(vlookup($A72,indirect("'TVC-"&text(month(N$1),"00")&"'!$A:$D"),4,false),1)) -> 1 | O72: =IF(isblank(O$1),,IFERROR(vlookup($A72,indirect("'TVC-"&text(month(O$1),"00")&"'!$A:$D"),4,false),1)) -> 1 | ... Q72: =IF(isblank(Q$1),,IFERROR(vlookup($A72,indirect("'TVC-"&text(month(Q$1),"00")&"'!$A:$D"),4,false),1)) | R72: =index(A72:Q72,,month(today())+5)-index(A72:Q72,,month(today())+4) -> 0
A73: =IFERROR(__xludf.DUMMYFUNCTION("""COMPUTED_VALUE"""),258.0) -> 258 | B73: =IFERROR(__xludf.DUMMYFUNCTION("""COMPUTED_VALUE"""),"Titans, Tennessee") -> Titans, Tennessee | C73: =IFERROR(__xludf.DUMMYFUNCTION("""COMPUTED_VALUE"""),"TMDL") -> TMDL | D73: =IFERROR(__xludf.DUMMYFUNCTION("""COMPUTED_VALUE"""),"TEN") -> TEN | E73: =mid(B73,find(",",B73)+2,30)&" "&left(B73,find(",",B73)-1) -> Tennessee Titans | F73: =IF(isblank(F$1),,IF(isblank($A73),,IFERROR(vlookup($A73,indirect("'TVC-"&text(month(F$1),"00")&"'!$A:$D"),4,false),1))) -> 1 | G73: =IF(isblank(G$1),,IF(isblank($A73),,IFERROR(vlookup($A73,indirect("'TVC-"&text(month(G$1),"00")&"'!$A:$D"),4,false),1))) -> 1 | H73: =IF(isblank(H$1),,IFERROR(vlookup($A73,indirect("'TVC-"&text(month(H$1),"00")&"'!$A:$D"),4,false),1)) -> 1 | I73: =IF(isblank(I$1),,IFERROR(vlookup($A73,indirect("'TVC-"&text(month(I$1),"00")&"'!$A:$D"),4,false),1)) -> 1 | J73: =IF(isblank(J$1),,IFERROR(vlookup($A73,indirect("'TVC-"&text(month(J$1),"00")&"'!$A:$D"),4,false),1)) -> 1 | K73: =IF(isblank(K$1),,IFERROR(vlookup($A73,indirect("'TVC-"&text(month(K$1),"00")&"'!$A:$D"),4,false),1)) -> 1 | L73: =IF(isblank(L$1),,IFERROR(vlookup($A73,indirect("'TVC-"&text(month(L$1),"00")&"'!$A:$D"),4,false),1)) -> 1 | M73: =IF(isblank(M$1),,IFERROR(vlookup($A73,indirect("'TVC-"&text(month(M$1),"00")&"'!$A:$D"),4,false),1)) -> 1 | N73: =IF(isblank(N$1),,IFERROR(vlookup($A73,indirect("'TVC-"&text(month(N$1),"00")&"'!$A:$D"),4,false),1)) -> 1 | O73: =IF(isblank(O$1),,IFERROR(vlookup($A73,indirect("'TVC-"&text(month(O$1),"00")&"'!$A:$D"),4,false),1)) -> 1 | ... Q73: =IF(isblank(Q$1),,IFERROR(vlookup($A73,indirect("'TVC-"&text(month(Q$1),"00")&"'!$A:$D"),4,false),1)) | R73: =index(A73:Q73,,month(today())+5)-index(A73:Q73,,month(today())+4) -> 0
A74: =IFERROR(__xludf.DUMMYFUNCTION("""COMPUTED_VALUE"""),259.0) -> 259 | B74: =IFERROR(__xludf.DUMMYFUNCTION("""COMPUTED_VALUE"""),"Jaguars, Jacksonville") -> Jaguars, Jacksonville | C74: =IFERROR(__xludf.DUMMYFUNCTION("""COMPUTED_VALUE"""),"TMDL") -> TMDL | D74: =IFERROR(__xludf.DUMMYFUNCTION("""COMPUTED_VALUE"""),"JAC") -> JAC | E74: =mid(B74,find(",",B74)+2,30)&" "&left(B74,find(",",B74)-1) -> Jacksonville Jaguars | F74: =IF(isblank(F$1),,IF(isblank($A74),,IFERROR(vlookup($A74,indirect("'TVC-"&text(month(F$1),"00")&"'!$A:$D"),4,false),1))) -> 1 | G74: =IF(isblank(G$1),,IF(isblank($A74),,IFERROR(vlookup($A74,indirect("'TVC-"&text(month(G$1),"00")&"'!$A:$D"),4,false),1))) -> 1 | H74: =IF(isblank(H$1),,IFERROR(vlookup($A74,indirect("'TVC-"&text(month(H$1),"00")&"'!$A:$D"),4,false),1)) -> 1 | I74: =IF(isblank(I$1),,IFERROR(vlookup($A74,indirect("'TVC-"&text(month(I$1),"00")&"'!$A:$D"),4,false),1)) -> 1 | J74: =IF(isblank(J$1),,IFERROR(vlookup($A74,indirect("'TVC-"&text(month(J$1),"00")&"'!$A:$D"),4,false),1)) -> 1 | K74: =IF(isblank(K$1),,IFERROR(vlookup($A74,indirect("'TVC-"&text(month(K$1),"00")&"'!$A:$D"),4,false),1)) -> 1 | L74: =IF(isblank(L$1),,IFERROR(vlookup($A74,indirect("'TVC-"&text(month(L$1),"00")&"'!$A:$D"),4,false),1)) -> 1 | M74: =IF(isblank(M$1),,IFERROR(vlookup($A74,indirect("'TVC-"&text(month(M$1),"00")&"'!$A:$D"),4,false),1)) -> 1 | N74: =IF(isblank(N$1),,IFERROR(vlookup($A74,indirect("'TVC-"&text(month(N$1),"00")&"'!$A:$D"),4,false),1)) -> 1 | O74: =IF(isblank(O$1),,IFERROR(vlookup($A74,indirect("'TVC-"&text(month(O$1),"00")&"'!$A:$D"),4,false),1)) -> 1 | ... Q74: =IF(isblank(Q$1),,IFERROR(vlookup($A74,indirect("'TVC-"&text(month(Q$1),"00")&"'!$A:$D"),4,false),1)) | R74: =index(A74:Q74,,month(today())+5)-index(A74:Q74,,month(today())+4) -> 0
A75: =IFERROR(__xludf.DUMMYFUNCTION("""COMPUTED_VALUE"""),260.0) -> 260 | B75: =IFERROR(__xludf.DUMMYFUNCTION("""COMPUTED_VALUE"""),"Steelers, Pittsburgh") -> Steelers, Pittsburgh | C75: =IFERROR(__xludf.DUMMYFUNCTION("""COMPUTED_VALUE"""),"TMDL") -> TMDL | D75: =IFERROR(__xludf.DUMMYFUNCTION("""COMPUTED_VALUE"""),"PIT") -> PIT | E75: =mid(B75,find(",",B75)+2,30)&" "&left(B75,find(",",B75)-1) -> Pittsburgh Steelers | F75: =IF(isblank(F$1),,IF(isblank($A75),,IFERROR(vlookup($A75,indirect("'TVC-"&text(month(F$1),"00")&"'!$A:$D"),4,false),1))) -> 1 | G75: =IF(isblank(G$1),,IF(isblank($A75),,IFERROR(vlookup($A75,indirect("'TVC-"&text(month(G$1),"00")&"'!$A:$D"),4,false),1))) -> 1 | H75: =IF(isblank(H$1),,IFERROR(vlookup($A75,indirect("'TVC-"&text(month(H$1),"00")&"'!$A:$D"),4,false),1)) -> 1 | I75: =IF(isblank(I$1),,IFERROR(vlookup($A75,indirect("'TVC-"&text(month(I$1),"00")&"'!$A:$D"),4,false),1)) -> 1 | J75: =IF(isblank(J$1),,IFERROR(vlookup($A75,indirect("'TVC-"&text(month(J$1),"00")&"'!$A:$D"),4,false),1)) -> 1 | K75: =IF(isblank(K$1),,IFERROR(vlookup($A75,indirect("'TVC-"&text(month(K$1),"00")&"'!$A:$D"),4,false),1)) -> 1 | L75: =IF(isblank(L$1),,IFERROR(vlookup($A75,indirect("'TVC-"&text(month(L$1),"00")&"'!$A:$D"),4,false),1)) -> 1 | M75: =IF(isblank(M$1),,IFERROR(vlookup($A75,indirect("'TVC-"&text(month(M$1),"00")&"'!$A:$D"),4,false),1)) -> 1 | N75: =IF(isblank(N$1),,IFERROR(vlookup($A75,indirect("'TVC-"&text(month(N$1),"00")&"'!$A:$D"),4,false),1)) -> 1 | O75: =IF(isblank(O$1),,IFERROR(vlookup($A75,indirect("'TVC-"&text(month(O$1),"00")&"'!$A:$D"),4,false),1)) -> 1 | ... Q75: =IF(isblank(Q$1),,IFERROR(vlookup($A75,indirect("'TVC-"&text(month(Q$1),"00")&"'!$A:$D"),4,false),1)) | R75: =index(A75:Q75,,month(today())+5)-index(A75:Q75,,month(today())+4) -> 0
A76: =IFERROR(__xludf.DUMMYFUNCTION("""COMPUTED_VALUE"""),261.0) -> 261 | B76: =IFERROR(__xludf.DUMMYFUNCTION("""COMPUTED_VALUE"""),"Broncos, Denver") -> Broncos, Denver | C76: =IFERROR(__xludf.DUMMYFUNCTION("""COMPUTED_VALUE"""),"TMDL") -> TMDL | D76: =IFERROR(__xludf.DUMMYFUNCTION("""COMPUTED_VALUE"""),"DEN") -> DEN | E76: =mid(B76,find(",",B76)+2,30)&" "&left(B76,find(",",B76)-1) -> Denver Broncos | F76: =IF(isblank(F$1),,IF(isblank($A76),,IFERROR(vlookup($A76,indirect("'TVC-"&text(month(F$1),"00")&"'!$A:$D"),4,false),1))) -> 1 | G76: =IF(isblank(G$1),,IF(isblank($A76),,IFERROR(vlookup($A76,indirect("'TVC-"&text(month(G$1),"00")&"'!$A:$D"),4,false),1))) -> 1 | H76: =IF(isblank(H$1),,IFERROR(vlookup($A76,indirect("'TVC-"&text(month(H$1),"00")&"'!$A:$D"),4,false),1)) -> 1 | I76: =IF(isblank(I$1),,IFERROR(vlookup($A76,indirect("'TVC-"&text(month(I$1),"00")&"'!$A:$D"),4,false),1)) -> 1 | J76: =IF(isblank(J$1),,IFERROR(vlookup($A76,indirect("'TVC-"&text(month(J$1),"00")&"'!$A:$D"),4,false),1)) -> 1 | K76: =IF(isblank(K$1),,IFERROR(vlookup($A76,indirect("'TVC-"&text(month(K$1),"00")&"'!$A:$D"),4,false),1)) -> 1 | L76: =IF(isblank(L$1),,IFERROR(vlookup($A76,indirect("'TVC-"&text(month(L$1),"00")&"'!$A:$D"),4,false),1)) -> 1 | M76: =IF(isblank(M$1),,IFERROR(vlookup($A76,indirect("'TVC-"&text(month(M$1),"00")&"'!$A:$D"),4,false),1)) -> 1 | N76: =IF(isblank(N$1),,IFERROR(vlookup($A76,indirect("'TVC-"&text(month(N$1),"00")&"'!$A:$D"),4,false),1)) -> 1 | O76: =IF(isblank(O$1),,IFERROR(vlookup($A76,indirect("'TVC-"&text(month(O$1),"00")&"'!$A:$D"),4,false),1)) -> 1 | ... Q76: =IF(isblank(Q$1),,IFERROR(vlookup($A76,indirect("'TVC-"&text(month(Q$1),"00")&"'!$A:$D"),4,false),1)) | R76: =index(A76:Q76,,month(today())+5)-index(A76:Q76,,month(today())+4) -> 0
A77: =IFERROR(__xludf.DUMMYFUNCTION("""COMPUTED_VALUE"""),262.0) -> 262 | B77: =IFERROR(__xludf.DUMMYFUNCTION("""COMPUTED_VALUE"""),"Chiefs, Kansas City") -> Chiefs, Kansas City | C77: =IFERROR(__xludf.DUMMYFUNCTION("""COMPUTED_VALUE"""),"TMDL") -> TMDL | D77: =IFERROR(__xludf.DUMMYFUNCTION("""COMPUTED_VALUE"""),"KCC") -> KCC | E77: =mid(B77,find(",",B77)+2,30)&" "&left(B77,find(",",B77)-1) -> Kansas City Chiefs | F77: =IF(isblank(F$1),,IF(isblank($A77),,IFERROR(vlookup($A77,indirect("'TVC-"&text(month(F$1),"00")&"'!$A:$D"),4,false),1))) -> 1 | G77: =IF(isblank(G$1),,IF(isblank($A77),,IFERROR(vlookup($A77,indirect("'TVC-"&text(month(G$1),"00")&"'!$A:$D"),4,false),1))) -> 1 | H77: =IF(isblank(H$1),,IFERROR(vlookup($A77,indirect("'TVC-"&text(month(H$1),"00")&"'!$A:$D"),4,false),1)) -> 1 | I77: =IF(isblank(I$1),,IFERROR(vlookup($A77,indirect("'TVC-"&text(month(I$1),"00")&"'!$A:$D"),4,false),1)) -> 1 | J77: =IF(isblank(J$1),,IFERROR(vlookup($A77,indirect("'TVC-"&text(month(J$1),"00")&"'!$A:$D"),4,false),1)) -> 1 | K77: =IF(isblank(K$1),,IFERROR(vlookup($A77,indirect("'TVC-"&text(month(K$1),"00")&"'!$A:$D"),4,false),1)) -> 1 | L77: =IF(isblank(L$1),,IFERROR(vlookup($A77,indirect("'TVC-"&text(month(L$1),"00")&"'!$A:$D"),4,false),1)) -> 1 | M77: =IF(isblank(M$1),,IFERROR(vlookup($A77,indirect("'TVC-"&text(month(M$1),"00")&"'!$A:$D"),4,false),1)) -> 1 | N77: =IF(isblank(N$1),,IFERROR(vlookup($A77,indirect("'TVC-"&text(month(N$1),"00")&"'!$A:$D"),4,false),1)) -> 1 | O77: =IF(isblank(O$1),,IFERROR(vlookup($A77,indirect("'TVC-"&text(month(O$1),"00")&"'!$A:$D"),4,false),1)) -> 1 | ... Q77: =IF(isblank(Q$1),,IFERROR(vlookup($A77,indirect("'TVC-"&text(month(Q$1),"00")&"'!$A:$D"),4,false),1)) | R77: =index(A77:Q77,,month(today())+5)-index(A77:Q77,,month(today())+4) -> 0
A78: =IFERROR(__xludf.DUMMYFUNCTION("""COMPUTED_VALUE"""),263.0) -> 263 | B78: =IFERROR(__xludf.DUMMYFUNCTION("""COMPUTED_VALUE"""),"Raiders, Las Vegas") -> Raiders, Las Vegas | C78: =IFERROR(__xludf.DUMMYFUNCTION("""COMPUTED_VALUE"""),"TMDL") -> TMDL | D78: =IFERROR(__xludf.DUMMYFUNCTION("""COMPUTED_VALUE"""),"LVR") -> LVR | E78: =mid(B78,find(",",B78)+2,30)&" "&left(B78,find(",",B78)-1) -> Las Vegas Raiders | F78: =IF(isblank(F$1),,IF(isblank($A78),,IFERROR(vlookup($A78,indirect("'TVC-"&text(month(F$1),"00")&"'!$A:$D"),4,false),1))) -> 1 | G78: =IF(isblank(G$1),,IF(isblank($A78),,IFERROR(vlookup($A78,indirect("'TVC-"&text(month(G$1),"00")&"'!$A:$D"),4,false),1))) -> 1 | H78: =IF(isblank(H$1),,IFERROR(vlookup($A78,indirect("'TVC-"&text(month(H$1),"00")&"'!$A:$D"),4,false),1)) -> 1 | I78: =IF(isblank(I$1),,IFERROR(vlookup($A78,indirect("'TVC-"&text(month(I$1),"00")&"'!$A:$D"),4,false),1)) -> 1 | J78: =IF(isblank(J$1),,IFERROR(vlookup($A78,indirect("'TVC-"&text(month(J$1),"00")&"'!$A:$D"),4,false),1)) -> 1 | K78: =IF(isblank(K$1),,IFERROR(vlookup($A78,indirect("'TVC-"&text(month(K$1),"00")&"'!$A:$D"),4,false),1)) -> 1 | L78: =IF(isblank(L$1),,IFERROR(vlookup($A78,indirect("'TVC-"&text(month(L$1),"00")&"'!$A:$D"),4,false),1)) -> 1 | M78: =IF(isblank(M$1),,IFERROR(vlookup($A78,indirect("'TVC-"&text(month(M$1),"00")&"'!$A:$D"),4,false),1)) -> 1 | N78: =IF(isblank(N$1),,IFERROR(vlookup($A78,indirect("'TVC-"&text(month(N$1),"00")&"'!$A:$D"),4,false),1)) -> 1 | O78: =IF(isblank(O$1),,IFERROR(vlookup($A78,indirect("'TVC-"&text(month(O$1),"00")&"'!$A:$D"),4,false),1)) -> 1 | ... Q78: =IF(isblank(Q$1),,IFERROR(vlookup($A78,indirect("'TVC-"&text(month(Q$1),"00")&"'!$A:$D"),4,false),1)) | R78: =index(A78:Q78,,month(today())+5)-index(A78:Q78,,month(today())+4) -> 0
A79: =IFERROR(__xludf.DUMMYFUNCTION("""COMPUTED_VALUE"""),264.0) -> 264 | B79: =IFERROR(__xludf.DUMMYFUNCTION("""COMPUTED_VALUE"""),"Chargers, Los Angeles") -> Chargers, Los Angeles | C79: =IFERROR(__xludf.DUMMYFUNCTION("""COMPUTED_VALUE"""),"TMDL") -> TMDL | D79: =IFERROR(__xludf.DUMMYFUNCTION("""COMPUTED_VALUE"""),"LAC") -> LAC | E79: =mid(B79,find(",",B79)+2,30)&" "&left(B79,find(",",B79)-1) -> Los Angeles Chargers | F79: =IF(isblank(F$1),,IF(isblank($A79),,IFERROR(vlookup($A79,indirect("'TVC-"&text(month(F$1),"00")&"'!$A:$D"),4,false),1))) -> 1 | G79: =IF(isblank(G$1),,IF(isblank($A79),,IFERROR(vlookup($A79,indirect("'TVC-"&text(month(G$1),"00")&"'!$A:$D"),4,false),1))) -> 1 | H79: =IF(isblank(H$1),,IFERROR(vlookup($A79,indirect("'TVC-"&text(month(H$1),"00")&"'!$A:$D"),4,false),1)) -> 1 | I79: =IF(isblank(I$1),,IFERROR(vlookup($A79,indirect("'TVC-"&text(month(I$1),"00")&"'!$A:$D"),4,false),1)) -> 1 | J79: =IF(isblank(J$1),,IFERROR(vlookup($A79,indirect("'TVC-"&text(month(J$1),"00")&"'!$A:$D"),4,false),1)) -> 1 | K79: =IF(isblank(K$1),,IFERROR(vlookup($A79,indirect("'TVC-"&text(month(K$1),"00")&"'!$A:$D"),4,false),1)) -> 1 | L79: =IF(isblank(L$1),,IFERROR(vlookup($A79,indirect("'TVC-"&text(month(L$1),"00")&"'!$A:$D"),4,false),1)) -> 1 | M79: =IF(isblank(M$1),,IFERROR(vlookup($A79,indirect("'TVC-"&text(month(M$1),"00")&"'!$A:$D"),4,false),1)) -> 1 | N79: =IF(isblank(N$1),,IFERROR(vlookup($A79,indirect("'TVC-"&text(month(N$1),"00")&"'!$A:$D"),4,false),1)) -> 1 | O79: =IF(isblank(O$1),,IFERROR(vlookup($A79,indirect("'TVC-"&text(month(O$1),"00")&"'!$A:$D"),4,false),1)) -> 1 | ... Q79: =IF(isblank(Q$1),,IFERROR(vlookup($A79,indirect("'TVC-"&text(month(Q$1),"00")&"'!$A:$D"),4,false),1)) | R79: =index(A79:Q79,,month(today())+5)-index(A79:Q79,,month(today())+4) -> 0
A80: =IFERROR(__xludf.DUMMYFUNCTION("""COMPUTED_VALUE"""),265.0) -> 265 | B80: =IFERROR(__xludf.DUMMYFUNCTION("""COMPUTED_VALUE"""),"Seahawks, Seattle") -> Seahawks, Seattle | C80: =IFERROR(__xludf.DUMMYFUNCTION("""COMPUTED_VALUE"""),"TMDL") -> TMDL | D80: =IFERROR(__xludf.DUMMYFUNCTION("""COMPUTED_VALUE"""),"SEA") -> SEA | E80: =mid(B80,find(",",B80)+2,30)&" "&left(B80,find(",",B80)-1) -> Seattle Seahawks | F80: =IF(isblank(F$1),,IF(isblank($A80),,IFERROR(vlookup($A80,indirect("'TVC-"&text(month(F$1),"00")&"'!$A:$D"),4,false),1))) -> 1 | G80: =IF(isblank(G$1),,IF(isblank($A80),,IFERROR(vlookup($A80,indirect("'TVC-"&text(month(G$1),"00")&"'!$A:$D"),4,false),1))) -> 1 | H80: =IF(isblank(H$1),,IFERROR(vlookup($A80,indirect("'TVC-"&text(month(H$1),"00")&"'!$A:$D"),4,false),1)) -> 1 | I80: =IF(isblank(I$1),,IFERROR(vlookup($A80,indirect("'TVC-"&text(month(I$1),"00")&"'!$A:$D"),4,false),1)) -> 1 | J80: =IF(isblank(J$1),,IFERROR(vlookup($A80,indirect("'TVC-"&text(month(J$1),"00")&"'!$A:$D"),4,false),1)) -> 1 | K80: =IF(isblank(K$1),,IFERROR(vlookup($A80,indirect("'TVC-"&text(month(K$1),"00")&"'!$A:$D"),4,false),1)) -> 1 | L80: =IF(isblank(L$1),,IFERROR(vlookup($A80,indirect("'TVC-"&text(month(L$1),"00")&"'!$A:$D"),4,false),1)) -> 1 | M80: =IF(isblank(M$1),,IFERROR(vlookup($A80,indirect("'TVC-"&text(month(M$1),"00")&"'!$A:$D"),4,false),1)) -> 1 | N80: =IF(isblank(N$1),,IFERROR(vlookup($A80,indirect("'TVC-"&text(month(N$1),"00")&"'!$A:$D"),4,false),1)) -> 1 | O80: =IF(isblank(O$1),,IFERROR(vlookup($A80,indirect("'TVC-"&text(month(O$1),"00")&"'!$A:$D"),4,false),1)) -> 1 | ... Q80: =IF(isblank(Q$1),,IFERROR(vlookup($A80,indirect("'TVC-"&text(month(Q$1),"00")&"'!$A:$D"),4,false),1)) | R80: =index(A80:Q80,,month(today())+5)-index(A80:Q80,,month(today())+4) -> 0
A81: =IFERROR(__xludf.DUMMYFUNCTION("""COMPUTED_VALUE"""),266.0) -> 266 | B81: =IFERROR(__xludf.DUMMYFUNCTION("""COMPUTED_VALUE"""),"Cowboys, Dallas") -> Cowboys, Dallas | C81: =IFERROR(__xludf.DUMMYFUNCTION("""COMPUTED_VALUE"""),"TMDL") -> TMDL | D81: =IFERROR(__xludf.DUMMYFUNCTION("""COMPUTED_VALUE"""),"DAL") -> DAL | E81: =mid(B81,find(",",B81)+2,30)&" "&left(B81,find(",",B81)-1) -> Dallas Cowboys | F81: =IF(isblank(F$1),,IF(isblank($A81),,IFERROR(vlookup($A81,indirect("'TVC-"&text(month(F$1),"00")&"'!$A:$D"),4,false),1))) -> 1 | G81: =IF(isblank(G$1),,IF(isblank($A81),,IFERROR(vlookup($A81,indirect("'TVC-"&text(month(G$1),"00")&"'!$A:$D"),4,false),1))) -> 1 | H81: =IF(isblank(H$1),,IFERROR(vlookup($A81,indirect("'TVC-"&text(month(H$1),"00")&"'!$A:$D"),4,false),1)) -> 1 | I81: =IF(isblank(I$1),,IFERROR(vlookup($A81,indirect("'TVC-"&text(month(I$1),"00")&"'!$A:$D"),4,false),1)) -> 1 | J81: =IF(isblank(J$1),,IFERROR(vlookup($A81,indirect("'TVC-"&text(month(J$1),"00")&"'!$A:$D"),4,false),1)) -> 1 | K81: =IF(isblank(K$1),,IFERROR(vlookup($A81,indirect("'TVC-"&text(month(K$1),"00")&"'!$A:$D"),4,false),1)) -> 1 | L81: =IF(isblank(L$1),,IFERROR(vlookup($A81,indirect("'TVC-"&text(month(L$1),"00")&"'!$A:$D"),4,false),1)) -> 1 | M81: =IF(isblank(M$1),,IFERROR(vlookup($A81,indirect("'TVC-"&text(month(M$1),"00")&"'!$A:$D"),4,false),1)) -> 1 | N81: =IF(isblank(N$1),,IFERROR(vlookup($A81,indirect("'TVC-"&text(month(N$1),"00")&"'!$A:$D"),4,false),1)) -> 1 | O81: =IF(isblank(O$1),,IFERROR(vlookup($A81,indirect("'TVC-"&text(month(O$1),"00")&"'!$A:$D"),4,false),1)) -> 1 | ... Q81: =IF(isblank(Q$1),,IFERROR(vlookup($A81,indirect("'TVC-"&text(month(Q$1),"00")&"'!$A:$D"),4,false),1)) | R81: =index(A81:Q81,,month(today())+5)-index(A81:Q81,,month(today())+4) -> 0
